Workbook

Sheet Automation Monitoring
D1: Last Update 20 July 2026 16:25 WIB
B4: Project ID | C4: Application ID | D4: Nama Aplikasi | E4: Estimated / Total TC | F4: Final TC | G4: Done Scripting | I4: Done Running | K4: Timeline Scripting / Regression in Year 2024 | L4: Platform | M4: Pdf | N4: Git | O4: Excel | P4: Branch Git | Q4: PIC B2B | R4: PIC FTE | T4: Device | V4: Chart | AM4: Nama Aplikasi | AN4: Estimated / Total TC | AO4: Final TC | AP4: Done Scripting | AR4: Done Running | AU4: Nama Aplikasi | AV4: Estimated / Total TC | AW4: Final TC | AX4: Done Scripting | AZ4: Done Running | BC4: Nama Aplikasi | BD4: Estimated / Total TC | BE4: Final TC | BF4: Done Scripting | BH4: Done Running
G5: TC | H5: Percentage | I5: TC | J5: Percentage | S5: Tools Auto | AP5: TC | AQ5: Percentage | AR5: TC | AS5: Percentage | AX5: TC | AY5: Percentage | AZ5: TC | BA5: Percentage | BF5: TC | BG5: Percentage | BH5: TC | BI5: Percentage
B6: P24095 | C6: ABOAST0135 | D6: Integrated & Centralized Online System (ICONS)-Tokyo | E6: 1079 | F6: 1079 | G6: 1079 | H6: =G6/F6 -> 1 | I6: 1079 | J6: =I6/F6 -> 1 | K6: Aug-Sept | L6: Web | M6: https://bankbnitbk-my.sharepoint.com/:f:/g/personal/67063_hq_bni_co_id/EioRDAk7tqJPhuKwrES1L6wBVVJh6wJLeRC7QuskMdzpLg?e=NkMAm7 | N6: https://gitlab-dc.bni.co.id/marchy.tio/icons.git | P6: dev_tokyo_merge | S6: UFT​ | AM6: BNI Direct Reguler / Reskinning | AN6: 740 | AO6: 695 | AP6: 623 | AQ6: =AP6/AO6 -> 0.89640288 | AR6: 623 | AS6: =AR6/AO6 -> 0.89640288 | AU6: BNI Direct Reguler / Reskinning | AV6: 740 | AW6: 695 | AX6: 623 | AY6: =AX6/AW6 -> 0.89640288 | AZ6: 623 | BA6: =AZ6/AW6 -> 0.89640288 | BC6: ICONS Tokyo | BD6: 1079 | BE6: 1079 | BF6: 1079 | BG6: =BF6/BE6 -> 1 | BH6: 1079 | BI6: =BH6/BE6 -> 1
B7: P24095 | C7: ABOAST0141 | D7: Integrated & Centralized Online System (LDN)-London | E7: 1006 | F7: 1006 | G7: 699 | H7: =G7/F7 -> 0.69483101 | I7: =BH7 -> 694 | J7: =I7/F7 -> 0.68986083 | K7: Okt-Nov | L7: Web | M7: https://bankbnitbk-my.sharepoint.com/:f:/g/personal/67063_hq_bni_co_id/EuJYUqs4i9pFljj3tLIKD_ABTVsQGOw747c_n_zduBE5-w?e=ir28YJ | N7: https://gitlab-dc.bni.co.id/marchy.tio/icons.git | P7: dev_london_merge | S7: UFT​ | AM7: BNI Direct Lite | AN7: 1748 | AO7: 1603 | AP7: 917 | AQ7: =AP7/AO7 -> 0.5720524 | AR7: 917 | AS7: =AR7/AO7 -> 0.5720524 | AU7: CXO Onboarding | AV7: 443 | AW7: 397 | AX7: 397 | AY7: =AX7/AW7 -> 1 | AZ7: 397 | BA7: =AZ7/AW7 -> 1 | BC7: ICONS London | BD7: 1006 | BE7: 1006 | BF7: 699 | BG7: =BF7/BE7 -> 0.69483101 | BH7: 694 | BI7: =BH7/BE7 -> 0.68986083
B8: P24095 | C8: ABOAST0142 | D8: Integrated & Centralized Online System (NYA)-New York | E8: 1013 | F8: 1013 | G8: 573 | H8: =G8/F8 -> 0.56564659 | I8: 565 | J8: =I8/F8 -> 0.55774926 | K8: Nov | L8: Web | M8: https://bankbnitbk-my.sharepoint.com/:f:/g/personal/67063_hq_bni_co_id/EjVOeAe_2_dEsC8Zvi54WZsBpHAq_N1suUGmclnT87wPpw?e=rm3sTp | N8: https://gitlab-dc.bni.co.id/marchy.tio/icons.git | P8: dev_newyork_merge | S8: UFT​ | AM8: CXO Onboarding | AN8: 443 | AO8: 397 | AP8: 397 | AQ8: =AP8/AO8 -> 1 | AR8: 397 | AS8: =AR8/AO8 -> 1 | AU8: Ibank Remittance Fase 1 | AV8: 203 | AW8: 185 | AX8: 185 | AY8: =AX8/AW8 -> 1 | AZ8: 185 | BA8: =AZ8/AW8 -> 1 | BC8: ICONS New York | BD8: 1013 | BE8: 1013 | BF8: 573 | BG8: =BF8/BE8 -> 0.56564659 | BH8: 565 | BI8: =BH8/BE8 -> 0.55774926
B9: P24095 | C9: ABOAST0140 | D9: Integrated & Centralized Online System (HKG)-Hongkong | E9: 932 | F9: 932 | G9: 406 | H9: =G9/F9 -> 0.43562232 | I9: 406 | J9: =I9/F9 -> 0.43562232 | K9: Feb-Mar | L9: Web | M9: https://bankbnitbk-my.sharepoint.com/:f:/g/personal/67063_hq_bni_co_id/EhCZ_7N9tNJIgATRbmpYaiQBdeT1-CRl5iGafkKuKTPiZQ?e=zLjz5h | N9: https://gitlab-dc.bni.co.id/marchy.tio/icons.git | P9: dev_hongkong_merge | S9: UFT​
B10: P24095 | C10: ABOAST0143 | D10: Integrated & Centralized Online System (SEO)-Seoul | E10: 921 | F10: 921 | G10: 338 | H10: =G10/F10 -> 0.3669924 | I10: 338 | J10: =I10/F10 -> 0.3669924 | K10: Mar-Apr | L10: Web | M10: https://bankbnitbk-my.sharepoint.com/:f:/g/personal/67063_hq_bni_co_id/EsBNhr_IOGZFi183hsODeQkBtAeT1vSg7cuoGc_uC31tLA?e=lOMw0E | N10: https://gitlab-dc.bni.co.id/marchy.tio/icons.git | P10: dev_seoul_merge | S10: UFT​
B11: P24095 | C11: ABOAST0144 | D11: Integrated & Centralized Online System (SNG)-Singapore | E11: 918 | F11: 918 | G11: 424 | H11: =G11/F11 -> 0.46187364 | I11: 424 | J11: =I11/F11 -> 0.46187364 | K11: April | L11: Web | M11: https://bankbnitbk-my.sharepoint.com/:f:/g/personal/67063_hq_bni_co_id/EmPaCuMegxFFsa-ggkUGxqcB3ihP__H4lUFyGJj9DtT8wQ?e=UtXsow | N11: https://gitlab-dc.bni.co.id/marchy.tio/icons.git | P11: dev_singapore_merge | S11: UFT​
B12: P23055 | C12: ABOAST0135 | D12: Integrated & Centralized Online System (ICONS)-Poseidon | E12: =BD12 -> 1567 | F12: =BE12 -> 1554 | G12: =BF12 -> 1416 | H12: =G12/F12 -> 0.91119691 | I12: =BH12 -> 1416 | J12: =I12/F12 -> 0.91119691 | K12: Jan | L12: Web | N12: https://gitlab-dc.bni.co.id/marchy.tio/icons.git | P12: dev_alternity_merging | S12: UFT​ | AM12: Tiplus UFE | AN12: 299 | AO12: 252 | AP12: 252 | AQ12: =AP12/AO12 -> 1 | AR12: 252 | AS12: =AR12/AO12 -> 1 | AU12: Ibank Remittance Fase 2 | AV12: 481 | AW12: 457 | AX12: 457 | AY12: =AX12/AW12 -> 1 | AZ12: 457 | BA12: =AZ12/AW12 -> 1 | BC12: ICONS Poseidon | BD12: 1567 | BE12: 1554 | BF12: 1416 | BG12: =BF12/BE12 -> 0.91119691 | BH12: 1416 | BI12: =BH12/BE12 -> 0.91119691
B13: P24015 | C13: AFONFO0032 | D13: BNIDirect Cash Management-BNI Direct Reguler / Reskinning | E13: 763 | F13: 695 | G13: 623 | H13: =G13/F13 -> 0.89640288 | I13: 623 | J13: =I13/F13 -> 0.89640288 | K13: Jul-Nov | L13: Web | M13: https://bankbnitbk.sharepoint.com/:f:/s/TEST212/EjoE11ji--FKn_mAQAz4i8oBtXukZNAGOhwCVulYtzAAIw?e=yikl5b | N13: https://gitlab-dc.bni.co.id/coe-duplicate/test-automation/katalon-bni-direct-reguler.git | Q13: Aulia, Akbar | R13: Thomas | S13: Katalon​ | AM13: Tiplus SFE | AN13: 273 | AO13: 231 | AP13: 231 | AQ13: =AP13/AO13 -> 1 | AR13: 231 | AS13: =AR13/AO13 -> 1 | AU13: Ibank Remittance Fase 3 | AV13: 400 | AW13: 194 | AX13: 194 | AY13: =AX13/AW13 -> 1 | AZ13: 194 | BA13: =AZ13/AW13 -> 1 | BC13: Mobile Banking (Android) | BD13: 11180 | BE13: 1709 | BF13: 1709 | BG13: =BF13/BE13 -> 1 | BH13: 1709 | BI13: =BH13/BE13 -> 1
B14: P24015 | C14: AFONFO0032 | D14: BNIDirect Cash Management-BNI Direct Lite | E14: 1750 | F14: 1603 | G14: 917 | H14: =G14/F14 -> 0.5720524 | I14: 917 | J14: =I14/F14 -> 0.5720524 | K14: Jul-Oct | L14: Web | M14: https://bankbnitbk.sharepoint.com/:f:/s/TEST212/EpfIVe6XOoxBplTCYePMJa0BkxvW5XBagBxVsZQHZwJadQ?e=M35rtn | N14: https://gitlab-dc.bni.co.id/coe-duplicate/test-automation/katalon-bni-direct-lite.git | Q14: Aulia, Burhan | R14: Thomas | S14: Katalon​ | AM14: Tiplus Export Local | AN14: 522 | AO14: 133 | AP14: 0 | AQ14: =AP14/AO14 -> 0 | AR14: 0 | AS14: =AR14/AO14 -> 0 | AU14: Mobile Wondr Business (Android) | AV14: 732 | AW14: 93 | AX14: 80 | AY14: =AX14/AW14 -> 0.86021505 | AZ14: 80 | BA14: =AZ14/AX14 -> 1 | BC14: Mobile Banking (iOS) | BD14: 11180 | BE14: 1328 | BF14: 1328 | BG14: =BF14/BE14 -> 1 | BH14: 1328 | BI14: =BH14/BE14 -> 1
B15: P24015 | C15: AFONFO0175 | D15: BNIDirect Portal-CXO | E15: 1158 | F15: 896 | G15: 896 | H15: =G15/F15 -> 1 | I15: 896 | J15: =I15/F15 -> 1 | K15: Sep-Dec | L15: Web | M15: https://bankbnitbk.sharepoint.com/:f:/s/TEST212/EshJqUQ8NgtJrM1fA3NLjP0BPMd-vipEJVXTXkGsyi7Biw?e=EJxxfA | N15: https://gitlab-dc.bni.co.id/coe-duplicate/test-automation/katalon-cxo-onboarding.git | Q15: Gafi | R15: Thomas, Mbincar | S15: Katalon​ | AM15: Tiplus GB Local | AN15: 5264 | AO15: 5264 | AP15: 214 | AQ15: =AP15/AO15 -> 0.040653495 | AR15: 214 | AS15: =AR15/AO15 -> 0.040653495 | AU15: Mobile Wondr Business (iOS) | AV15: 732 | AW15: 92 | AX15: 92 | AY15: =AX15/AW15 -> 1 | AZ15: 74 | BA15: =AZ15/AX15 -> 0.80434783 | BC15: GB Online | BD15: 555 | BE15: 420 | BF15: 0 | BG15: =BF15/BE15 -> 0 | BH15: 0 | BI15: =BH15/BE15 -> 0
B16: P24016 | C16: ABOAST0245 | D16: TIPlus-Tiplus UFE | E16: 395 | F16: 312 | G16: 256 | H16: =G16/F16 -> 0.82051282 | I16: 256 | J16: =I16/F16 -> 0.82051282 | K16: Aug-Mar | L16: Web | M16: https://bankbnitbk.sharepoint.com/:f:/s/TEST212/El9fXPrW_0xEprlffGoewXkB11ZARqXcvZV5_6zbpZffWg?e=rrbDbV | N16: https://gitlab-dc.bni.co.id/coe-duplicate/test-automation/katalon-tiplus-ufe.git | Q16: Alkha, Andin | R16: Thomas | S16: Katalon​ | AM16: Ibank Remittance Fase 1 | AN16: 203 | AO16: 185 | AP16: 185 | AQ16: =AP16/AO16 -> 1 | AR16: 185 | AS16: =AR16/AO16 -> 1 | AU16: Mobile SMS Menu (Android) | AV16: 898 | AW16: 780 | AX16: 772 | AY16: =AX16/AW16 -> 0.98974359 | AZ16: 772 | BA16: =AZ16/AW16 -> 0.98974359
B17: P24016 | C17: ABOAST0245 | D17: TIPlus-Tiplus SFE | E17: 399 | F17: 318 | G17: 312 | H17: =G17/F17 -> 0.98113208 | I17: 312 | J17: =I17/F17 -> 0.98113208 | K17: Aug-Mar | L17: Web | M17: https://bankbnitbk.sharepoint.com/:f:/s/TEST212/Emapha_Bb-9DkeVfXC8xJYUBRyjYGeVp-Oe6NTAG5ipn9A?e=ONdMX9 | N17: https://gitlab-dc.bni.co.id/coe-duplicate/test-automation/katalon-tiplus-sfe.git | Q17: Andin | R17: Thomas | S17: Katalon​ | AM17: Ibank Remittance Fase 2 | AN17: 481 | AO17: 457 | AP17: 457 | AQ17: =AP17/AO17 -> 1 | AR17: 457 | AS17: =AR17/AO17 -> 1 | AU17: Mobile SMS Menu (iOS) | AV17: 898 | AW17: 772 | AX17: 772 | AY17: =AX17/AW17 -> 1 | AZ17: 772 | BA17: =AZ17/AW17 -> 1
A18: out | B18: P24016 | C18: ABOAST0245 | D18: TIPlus-Tiplus Export Local | E18: 522 | F18: 133 | G18: 0 | H18: =G18/F18 -> 0 | I18: 0 | J18: =I18/F18 -> 0 | K18: - | L18: Web | M18: https://bankbnitbk.sharepoint.com/:f:/s/TEST212/Ep78Qlmxo0pEht8rdfyamzoBHfhkycCopqAyr9XvvAECMQ?e=aLtBmW | N18: https://gitlab-dc.bni.co.id/coe-duplicate/test-automation/katalon-tiplus-export-local.git | S18: Katalon​ | AM18: Ibank Remittance Fase 3 | AN18: 400 | AO18: 194 | AP18: 194 | AQ18: =AP18/AO18 -> 1 | AR18: 194 | AS18: =AR18/AO18 -> 1 | AU18: Mobile Banking (Android) | AV18: 11180 | AW18: 1709 | AX18: 1709 | AY18: =AX18/AW18 -> 1 | AZ18: 1709 | BA18: =AZ18/AW18 -> 1
B19: P24016 | C19: ABOAST0245 | D19: TIPlus-Tiplus GB Local | E19: 5264 | F19: 5264 | G19: 812 | H19: =G19/F19 -> 0.15425532 | I19: 812 | J19: =I19/F19 -> 0.15425532 | K19: Nov-Mar | L19: Web | M19: https://bankbnitbk.sharepoint.com/:f:/s/TEST212/EnPhbOuIHQVBn-o711gDTwIB3eOLJ6GgqxeHav5V_212Aw?e=NPMo37 | N19: https://gitlab-dc.bni.co.id/coe-duplicate/test-automation/katalon-tiplus-gb.git | Q19: Andin, Ali, Alkha | R19: Thomas | S19: Katalon​ | AM19: Mobile SMS Menu (Android) | AN19: 898 | AO19: 780 | AP19: 772 | AQ19: =AP19/AO19 -> 0.98974359 | AR19: 772 | AS19: =AR19/AO19 -> 0.98974359 | AU19: Mobile Banking (iOS) | AV19: 11180 | AW19: 1328 | AX19: 1328 | AY19: =AX19/AW19 -> 1 | AZ19: 1328 | BA19: =AZ19/AW19 -> 1
B20: P23108 | C20: AFOAFO0134 | D20: iBank Remitt-Ibank Remittance Fase 1 | E20: 203 | F20: 185 | G20: 185 | H20: =G20/F20 -> 1 | I20: 185 | J20: =I20/F20 -> 1 | K20: Jan-Mar | L20: Web | M20: https://bankbnitbk.sharepoint.com/:f:/s/TEST212/EtmuKzkVd5RIl1KkUpVF9R4BoiHpVsBFUBQoOYHvh7oDPQ?e=kC7VLy | N20: https://gitlab-dc.bni.co.id/coe-duplicate/test-automation/katalon-ibank-remit.git | Q20: Akbar | R20: Thomas | S20: Katalon​ | AM20: Mobile SMS Menu (iOS) | AN20: 898 | AO20: 780 | AP20: 407 | AQ20: =AP20/AO20 -> 0.52179487 | AR20: 407 | AS20: =AR20/AO20 -> 0.52179487 | AU20: Web Agen46 | AV20: 353 | AW20: 329 | AX20: 329 | AY20: =AX20/AW20 -> 1 | AZ20: 329 | BA20: =AZ20/AW20 -> 1 | BD20: Web Agen46 | BE20: Ibank Remittance Fase 1,2 dan 3
B21: P23108 | C21: AFOAFO0134 | D21: iBank Remitt-Ibank Remittance Fase 2 | E21: 481 | F21: 457 | G21: 457 | H21: =G21/F21 -> 1 | I21: 457 | J21: =I21/F21 -> 1 | K21: Mar-Jun | L21: Web | M21: https://bankbnitbk.sharepoint.com/:f:/s/TEST212/ErrL0pVIbCJLm0b1orcWaU8BvqVAwz9-D1w3xohN5Jupmw?e=OSAFJR | N21: https://gitlab-dc.bni.co.id/coe-duplicate/test-automation/katalon-ibank-remit-fase-2.git | Q21: Akbar | R21: Thomas | S21: Katalon​ | AM21: Mobile Banking (Android) | AN21: 11180 | AO21: 1709 | AP21: 1709 | AQ21: =AP21/AO21 -> 1 | AR21: 1709 | AS21: =AR21/AO21 -> 1 | AU21: Mobile Agen46 (Android) | AV21: 712 | AW21: 609 | AX21: 609 | AY21: =AX21/AW21 -> 1 | AZ21: 609 | BA21: =AZ21/AW21 -> 1 | BD21: Mobile Banking | BE21: LMS Wholesale Sprint 1,2,3 dan 4
B22: P23108 | C22: AFOAFO0134 | D22: iBank Remitt-Ibank Remittance Fase 3 | E22: 400 | F22: 194 | G22: 194 | H22: =G22/F22 -> 1 | I22: 194 | J22: =I22/F22 -> 1 | K22: Jun-Oct | L22: Web | M22: https://bankbnitbk.sharepoint.com/:f:/s/TEST212/EkHjWT_UNQVOuyzvn_wuAsIBDRxid-37YpANPr_MFDJmDA?e=sloXmk | N22: https://gitlab-dc.bni.co.id/coe-duplicate/test-automation/katalon-ibank-fase-3.git | Q22: Akbar | R22: Thomas | S22: Katalon​ | AM22: Mobile Banking (iOS) | AN22: 11180 | AO22: 1328 | AP22: 1328 | AQ22: =AP22/AO22 -> 1 | AR22: 1328 | AS22: =AR22/AO22 -> 1 | AU22: Mobile Agen46 (iOS) | AV22: 712 | AW22: 306 | AX22: 306 | AY22: =AX22/AW22 -> 1 | AZ22: 306 | BA22: =AZ22/AW22 -> 1 | BD22: Mobile SMS Menu | BE22: Mobile Wondr Bussiness
B23: P24111 | C23: AFONFO0265 | D23: Wondr-Mobile Wondr Business (Android) | E23: 732 | F23: 80 | G23: 80 | H23: =G23/F23 -> 1 | I23: 80 | J23: =I23/F23 -> 1 | K23: Sep-Nov | L23: Mobile | M23: https://drive.google.com/drive/folders/17ELgFdGoXCIye04cj8w9d-hsfML1s-vV | N23: https://gitlab-dc.bni.co.id/coe-duplicate/test-automation/katalon-wondr-bussiness-android.git | O23: https://bankbnitbk.sharepoint.com/:x:/r/sites/TEST212/Shared%20Documents/General/Sheet%20Monitoring%20Project/UFT%20Katalon%20Automation%202024%20-%202025.xlsx?d=wc03feacd37994a94b2715e297ba9a69e&csf=1&web=1&e=aoQZQg | Q23: Mafa | R23: Mbincar | S23: Katalon​ | AM23: Web Agen46 | AN23: 353 | AO23: 329 | AP23: 329 | AQ23: =AP23/AO23 -> 1 | AR23: 329 | AS23: =AR23/AO23 -> 1 | AU23: Web Portal Admin | AV23: 39 | AW23: 37 | AX23: 37 | AY23: =AX23/AW23 -> 1 | AZ23: 36 | BA23: =AZ23/AX23 -> 0.97297297 | BD23: Mobile Agen46 | BE23: Web Portal Admin
B24: P24111 | C24: AFONFO0265 | D24: Wondr-Mobile Wondr Business (iOS) | E24: 732 | F24: 92 | G24: 92 | H24: =G24/F24 -> 1 | I24: 74 | J24: =I24/F24 -> 0.80434783 | K24: Sep-Nov | L24: Mobile | M24: https://drive.google.com/drive/folders/17ELgFdGoXCIye04cj8w9d-hsfML1s-vV | N24: https://gitlab-dc.bni.co.id/coe-duplicate/test-automation/katalon-wondr-bussiness-ios.git | O24: https://bankbnitbk.sharepoint.com/:x:/r/sites/TEST212/Shared%20Documents/General/Sheet%20Monitoring%20Project/UFT%20Katalon%20Automation%202024%20-%202025.xlsx?d=wc03feacd37994a94b2715e297ba9a69e&csf=1&web=1&e=aoQZQg | Q24: Alvin | R24: Mbincar | S24: Katalon​ | AM24: Mobile Agen46 (Android) | AN24: 712 | AO24: 609 | AP24: 609 | AQ24: =AP24/AO24 -> 1 | AR24: 609 | AS24: =AR24/AO24 -> 1 | AU24: LMS Sprint 1 | AV24: 15 | AW24: 15 | AX24: 15 | AY24: =AX24/AW24 -> 1 | AZ24: 15 | BA24: =AZ24/AW24 -> 1 | BD24: Tiplus SFE | BE24: Digisales Portal
B25: A24001 | C25: AFONFO0229 | D25: SMS Banking-Mobile SMS Menu (Android) | E25: 898 | F25: 780 | G25: 772 | H25: =G25/F25 -> 0.98974359 | I25: 772 | J25: =I25/F25 -> 0.98974359 | K25: Oct-Nov | L25: Mobile | M25: https://bankbnitbk.sharepoint.com/:f:/s/TEST212/EkBwukLUexlCvNbiS9xVLOwBec_4sO1J5vspDybADFMf8g?e=YPNGbQ | N25: https://gitlab-dc.bni.co.id/coe-duplicate/test-automation/katalon-sms-menu-android.git | Q25: Alvin | R25: Mbincar | S25: Katalon​ | AM25: Mobile Agen46 (iOS) | AN25: 712 | AO25: 306 | AP25: 306 | AQ25: =AP25/AO25 -> 1 | AR25: 306 | AS25: =AR25/AO25 -> 1 | AU25: LMS Sprint 2 | AV25: 16 | AW25: 16 | AX25: 16 | AY25: =AX25/AW25 -> 1 | AZ25: 16 | BA25: =AZ25/AW25 -> 1 | BD25: Tiplus UFE | BE25: Digisales APK Generalis dan FTE
B26: A24001 | C26: AFONFO0229 | D26: SMS Banking-Mobile SMS Menu (iOS) | E26: 898 | F26: 780 | G26: 772 | H26: =G26/F26 -> 0.98974359 | I26: 772 | J26: =I26/F26 -> 0.98974359 | K26: Oct-Nov | L26: Mobile | M26: https://bankbnitbk.sharepoint.com/:f:/s/TEST212/EsU0M1xMRx9PokMQJ0xEYqoBFapR-d2DAIfXACNcm1GImQ?e=Td26y3 | N26: https://gitlab-dc.bni.co.id/coe-duplicate/test-automation/katalon-sms-menu-ios.git | Q26: Alvin | R26: Mbincar | S26: Katalon​ | W26: Stop / Aplikasi sudah tidak dilanjutkan scripting / Service Down | AM26: Mobile Credit Card (Android) | AN26: 75 | AO26: 60 | AP26: 40 | AQ26: =AP26/AO26 -> 0.66666667 | AR26: 40 | AS26: =AR26/AO26 -> 0.66666667 | AU26: LMS Sprint 3 | AV26: 37 | AW26: 37 | AX26: 37 | AY26: =AX26/AW26 -> 1 | AZ26: 37 | BA26: =AZ26/AX26 -> 1 | BD26: BNI Direct Lite | BE26: Digisales Browser Generalis dan FTE
B27: A24001 | C27: AFONFO0167 | D27: Mobile Banking (Android) | E27: 11180 | F27: 5590 | G27: 5590 | H27: =G27/F27 -> 1 | I27: 5590 | J27: =I27/F27 -> 1 | K27: Jan-Dec | L27: Mobile | M27: https://bankbnitbk.sharepoint.com/:f:/s/COETeam/EhexkvrncmhPkKrQ88RFFeQBpANxgmBvAXlLKTC6aoqqPw?e=CAjb0u | N27: https://gitlab-dc.bni.co.id/marchy.tio/mobile-banking-android.git | Q27: Adit, Thomas | R27: Thomas | S27: UFT dan Katalon​ | W27: Done | AM27: Mobile Credit Card (iOS) | AN27: 75 | AO27: 60 | AP27: 40 | AQ27: =AP27/AO27 -> 0.66666667 | AR27: 40 | AS27: =AR27/AO27 -> 0.66666667 | AU27: LMS Sprint 4 | AV27: 21 | AW27: 21 | AX27: 21 | AY27: =AX27/AW27 -> 1 | AZ27: 21 | BA27: =AZ27/AX27 -> 1 | BD27: BNI Direct Reguler | BE27: ICONS Tokyo
B28: A24001 | C28: AFONFO0167 | D28: Mobile Banking (iOS) | E28: 11180 | F28: 5590 | G28: 5590 | H28: =G28/F28 -> 1 | I28: 5590 | J28: =I28/F28 -> 1 | K28: Jan-Dec | L28: Mobile | M28: https://bankbnitbk.sharepoint.com/:f:/s/COETeam/EhexkvrncmhPkKrQ88RFFeQBpANxgmBvAXlLKTC6aoqqPw?e=CAjb0u | N28: https://gitlab-dc.bni.co.id/marchy.tio/mobile-agen-ios.git | Q28: Adit, Thomas | R28: Thomas | S28: UFT dan Katalon​ | W28: In Progress | AM28: DMS Sprint 1 | AN28: 134 | AO28: 97 | AP28: 97 | AQ28: =AP28/AO28 -> 1 | AR28: 97 | AS28: =AR28/AO28 -> 1 | AU28: Digisales Portal | AV28: 60 | AW28: 47 | AX28: 47 | AY28: =AX28/AW28 -> 1 | AZ28: 47 | BA28: =AZ28/AW28 -> 1 | BD28: CXO Onboarding | BE28: ICONS Alternity
B29: P23014 | C29: AFOAFO0154 | D29: Keagenan-Web Agen46 | E29: 353 | F29: 329 | G29: 329 | H29: =G29/F29 -> 1 | I29: 329 | J29: =I29/F29 -> 1 | K29: Jan-Dec | L29: Web | M29: https://bankbnitbk.sharepoint.com/:f:/s/TEST212/EgbVkGyr9-pFiln6NEqUKygBcfmEacAgN3FK0RjDiivwMg?e=nPUY5s | N29: https://gitlab-dc.bni.co.id/marchy.tio/keagenan46-uft.git | P29: dev_alex | Q29: Yusuf, Alex | R29: Thomas, Marin | S29: UFT​ | T29: Oppo Reno 7 | W29: Hold | AM29: DMS Sprint 2 | AN29: 136 | AO29: 136 | AP29: 136 | AQ29: =AP29/AO29 -> 1 | AR29: 136 | AS29: =AR29/AO29 -> 1 | AU29: Digisales Generalis Mobile Browser | AV29: 49 | AW29: 47 | AX29: 47 | AY29: =AX29/AW29 -> 1 | AZ29: 47 | BA29: =AZ29/AW29 -> 1 | BD29: DigiMS | BE29: ICONS Poisedon
B30: P23014 | C30: AFOAFO0154 | D30: Keagenan-Mobile Agen46 (Android) | E30: 712 | F30: 609 | G30: 609 | H30: =G30/F30 -> 1 | I30: 609 | J30: =I30/F30 -> 1 | K30: Jan-Dec | L30: Mobile | M30: https://bankbnitbk.sharepoint.com/:f:/s/TEST212/EiEcoPf2gTxAmcZmpvA4fNgBhiFsoebZ1LZC4eefKSbWvg?e=nX1kh8 | N30: https://gitlab-dc.bni.co.id/marchy.tio/mobile-agen-android.git | P30: dev_yudho | Q30: Akbar, Yudho | R30: Thomas, Mbincar, Marin | S30: UFT​ | AM30: DMS Sprint 3 | AN30: 210 | AO30: 210 | AP30: 210 | AQ30: =AP30/AO30 -> 1 | AR30: 210 | AS30: =AR30/AO30 -> 1 | AU30: Digisales Generalis Mobile APK | AV30: 49 | AW30: 47 | AX30: 47 | AY30: =AX30/AW30 -> 1 | AZ30: 47 | BA30: =AZ30/AW30 -> 1 | BD30: Mobile MyCard | BE30: ICONS London
B31: P23014 | C31: AFOAFO0154 | D31: Keagenan-Mobile Agen46 (iOS) | E31: 712 | F31: 609 | G31: 609 | H31: =G31/F31 -> 1 | I31: 609 | J31: =I31/F31 -> 1 | K31: Jan-Dec | L31: Mobile | M31: https://bankbnitbk.sharepoint.com/:f:/s/TEST212/EgPcgA5jbJ9HrcgZ-GhhgCMB0UPYbPOvpQPH74Hk7dO4bA?e=8KbZ6f | N31: https://gitlab-dc.bni.co.id/marchy.tio/mobile-agen-ios.git | Q31: Thomas | R31: Thomas | S31: UFT​ | T31: iPhone SE | AM31: BAMS-TAT | AN31: 423 | AO31: 390 | AP31: 202 | AQ31: =AP31/AO31 -> 0.51794872 | AR31: 202 | AS31: =AR31/AO31 -> 0.51794872 | AU31: Digisales FTE Mobile Browser | AV31: 257 | AW31: 257 | AX31: 257 | AY31: =AX31/AW31 -> 1 | AZ31: 249 | BA31: =AZ31/AW31 -> 0.9688716 | BD31: DMS Sprint 1,2 dan 3
B32: A24001 | C32: AFONFO0173 | D32: MyCard-Mobile Credit Card (Android) | E32: 75 | F32: 60 | G32: 40 | H32: =G32/F32 -> 0.66666667 | I32: 40 | J32: =I32/F32 -> 0.66666667 | K32: Oct-Oct | L32: Mobile | M32: https://bankbnitbk.sharepoint.com/:f:/s/TEST212/EhxlVjo9HBdAm-H7eawQ7tABiE5bT5QZOeaXojeQgwtHig?e=cce0WK | N32: https://gitlab-dc.bni.co.id/marchy.tio/mobile-bni-credit-card-android.git | Q32: Willy | R32: Thomas | S32: Katalon​ | W32: normal | AM32: DigIMS | AN32: 198 | AO32: 115 | AP32: 115 | AQ32: =AP32/AO32 -> 1 | AR32: 115 | AS32: =AR32/AO32 -> 1 | AU32: Digisales FTE Mobile APK | AV32: 257 | AW32: 257 | AX32: 257 | AY32: =AX32/AW32 -> 1 | AZ32: 254 | BA32: =AZ32/AW32 -> 0.98832685
B33: A24001 | C33: AFONFO0173 | D33: MyCard-Mobile Credit Card (iOS) | E33: 75 | F33: 60 | G33: 40 | H33: =G33/F33 -> 0.66666667 | I33: 40 | J33: =I33/F33 -> 0.66666667 | K33: Oct-Oct | L33: Mobile | M33: https://bankbnitbk.sharepoint.com/:f:/s/TEST212/Ei5Zf9cttb5EjDeqTlOL06QBpKaucm6Sp8TatRFM_m3syg?e=Co7C5G | N33: https://gitlab-dc.bni.co.id/marchy.tio/mobile-bni-credit-card-ios.git | Q33: Thomas | R33: Thomas | S33: Katalon​ | V33: 7 hari | W33: 20 tc | X33: 25 hari | AM33: Digisales Portal | AN33: 60 | AO33: 47 | AP33: 47 | AQ33: =AP33/AO33 -> 1 | AR33: 47 | AS33: =AR33/AO33 -> 1 | AU33: Smart VA Portal | AV33: 669 | AW33: 669 | AX33: 157 | AY33: =AX33/AW33 -> 0.23467862 | AZ33: 157 | BA33: =AZ33/AW33 -> 0.23467862
B34: P23095 | C34: AMOOES0255 | D34: Document Management System-Sprint 1 | E34: 134 | F34: 97 | G34: 97 | H34: =G34/F34 -> 1 | I34: 97 | J34: =I34/F34 -> 1 | K34: Oct-Oct | L34: Web | M34: https://bankbnitbk.sharepoint.com/:f:/s/TEST212/EmHMOIlBNDhMgG0fqwfNLcMByJKReKkvJNI9KYFvfC6wag?e=8drVel | N34: https://gitlab-dc.bni.co.id/coe-duplicate/test-automation/katalon-dms.git | Q34: Willy | R34: Thomas | S34: Katalon​ | V34: 7 hari | W34: 20 tc | AM34: Digisales Generalis Mobile Browser | AN34: 49 | AO34: 47 | AP34: 47 | AQ34: =AP34/AO34 -> 1 | AR34: 47 | AS34: =AR34/AO34 -> 1
B35: P23095 | C35: AMOOES0255 | D35: Document Management System-Sprint 2 | E35: 136 | F35: 136 | G35: 136 | H35: =G35/F35 -> 1 | I35: 136 | J35: =I35/F35 -> 1 | K35: Oct-Nov | L35: Web | M35: https://bankbnitbk.sharepoint.com/:f:/s/TEST212/EpY4prIHBUtLrQN9JOy0ISEBtNP6CEy567sXf4qNOFEo7Q?e=bRxJ5j | N35: https://gitlab-dc.bni.co.id/coe-duplicate/test-automation/katalon-dms.git | Q35: Willy | R35: Thomas | S35: Katalon​ | V35: 11 hari | W35: 20 tc | AM35: Digisales Generalis Mobile APK | AN35: 49 | AO35: 47 | AP35: 47 | AQ35: =AP35/AO35 -> 1 | AR35: 47 | AS35: =AR35/AO35 -> 1
B36: P23095 | C36: AMOOES0255 | D36: Document Management System-Sprint 3 | E36: 210 | F36: 210 | G36: 210 | H36: =G36/F36 -> 1 | I36: 210 | J36: =I36/F36 -> 1 | K36: Nov-Dec | L36: Web | M36: https://bankbnitbk.sharepoint.com/:f:/s/TEST212/Erxs-oPMn19Air8-liocoq4BGeFyQJ0enNcHClbhAI4e2Q?e=zUdiKh | N36: https://gitlab-dc.bni.co.id/coe-duplicate/test-automation/katalon-dms.git | Q36: Willy | R36: Thomas | S36: Katalon​ | V36: 22 hari / 1 bulan | W36: 20 tc | AM36: Digisales FTE Mobile Browser | AN36: 257 | AO36: 257 | AP36: 257 | AQ36: =AP36/AO36 -> 1 | AR36: 249 | AS36: =AR36/AO36 -> 0.9688716
B37: P23144 | C37: AMOLOM0174 | D37: New BAMS & CPR-BAMS-TAT | E37: 423 | F37: 390 | G37: 362 | H37: =G37/F37 -> 0.92820513 | I37: 362 | J37: =I37/F37 -> 0.92820513 | K37: Oct-Jan | L37: Web | M37: https://bankbnitbk.sharepoint.com/:f:/s/TEST212/EmiB9mpkX1tFldLUVOVY5SsBY1WjAqn_mc_ygxcWlPhRfg?e=442imQ | N37: https://gitlab-dc.bni.co.id/coe-duplicate/test-automation/katalon-bams-tat.git | Q37: Burhan | R37: Thomas | S37: Katalon​ | V37: 10 hari | W37: 20 tc | AM37: Digisales FTE Mobile APK | AN37: 257 | AO37: 257 | AP37: 257 | AQ37: =AP37/AO37 -> 1 | AR37: 254 | AS37: =AR37/AO37 -> 0.98832685
B38: P23094 | C38: AMOOES0309 | D38: DigIMS | E38: 1153 | F38: 1137 | G38: 590 | H38: =G38/F38 -> 0.51890941 | I38: 583 | J38: =I38/F38 -> 0.51275286 | K38: Oct-Nov | L38: Web | M38: https://bankbnitbk.sharepoint.com/:f:/s/TEST212/EmDQeI6wuE9Erk-8RtI6KBsBdR4mp5abwD8GJYpgrlXEyA?e=FOsV8R | N38: https://gitlab-dc.bni.co.id/coe-duplicate/test-automation/katalon-digims.git | Q38: Alkha | R38: Thomas | S38: Katalon​ | V38: 3 hari | W38: 20 tc | X38: 35 hari/ 1 bulan 2 minggu | AM38: Smart VA Portal | AN38: 669 | AO38: 669 | AP38: 157 | AQ38: =AP38/AO38 -> 0.23467862 | AR38: 157 | AS38: =AR38/AO38 -> 0.23467862
B39: P24091 | C39: AMOSAL0068 | D39: Digisales-Portal (4B) | E39: 60 | F39: 47 | G39: 47 | H39: =G39/F39 -> 1 | I39: 47 | J39: =I39/F39 -> 1 | K39: Oct-Nov | L39: Web | M39: https://bankbnitbk.sharepoint.com/:f:/s/TEST212/EpwQ_mowTgRIsBNX-yqk1SsBydKz148dpodB8gftHbFBaw?e=24HPLd | N39: https://gitlab-dc.bni.co.id/coe-duplicate/test-automation/katalon-digisales-portal.git | S39: Katalon​ | V39: 3 hari | W39: 20 tc | AM39: Cash Management Lite | AN39: 29603 | AO39: 29603 | AP39: 28 | AQ39: =AP39/AO39 -> 0.00094585008 | AR39: 18 | AS39: =AR39/AO39 -> 0.00060804648
B40: P24091 | C40: AMOSAL0068 | D40: Digisales-Generalis Mobile Browser (4B) | E40: 49 | F40: 47 | G40: 47 | H40: =G40/F40 -> 1 | I40: 47 | J40: =I40/F40 -> 1 | K40: Oct-Nov | L40: Mobile | M40: https://bankbnitbk.sharepoint.com/:f:/s/TEST212/ElybKHNWvkxDjZztpmaLLWUBbK7bk4AXKBTpXRbjFe-LvQ?e=zw4Rt1 | N40: https://gitlab-dc.bni.co.id/coe-duplicate/test-automation/katalon-digisales-generalis-mobile-browser.git | S40: Katalon​ | V40: 3 hari | W40: 20 tc | AM40: GB Online | AN40: 555 | AO40: 420 | AP40: 0 | AQ40: =AP40/AO40 -> 0 | AR40: 0 | AS40: =AR40/AO40 -> 0
B41: P24091 | C41: AMOSAL0068 | D41: Digisales-Generalis Mobile APK (4B) | E41: 49 | F41: 47 | G41: 47 | H41: =G41/F41 -> 1 | I41: 47 | J41: =I41/F41 -> 1 | K41: Oct-Nov | L41: Mobile | M41: https://bankbnitbk.sharepoint.com/:f:/s/TEST212/ElM4wgKu4IpEo1aN26W6_xEBbG1DgM8lJCMGlpG4MzZ0Mg?e=ugHmtA | N41: https://gitlab-dc.bni.co.id/coe-duplicate/test-automation/katalon-digisales-generalis-mobile-apk.git | Q41: Unedo | S41: Katalon​ | V41: 13 hari | W41: 20 tc
B42: P24091 | C42: AMOSAL0068 | D42: Digisales-FTE Mobile Browser (4B) | E42: 257 | F42: 257 | G42: 257 | H42: =G42/F42 -> 1 | I42: 249 | J42: =I42/F42 -> 0.9688716 | K42: Nov-Dec | L42: Mobile | M42: https://bankbnitbk.sharepoint.com/:f:/s/TEST212/Eup95DJS-rFLljrtCvblvq0BOzTzM9ulTTYDds9KCmcULw?e=eHpNAF | N42: https://gitlab-dc.bni.co.id/coe-duplicate/test-automation/katalon-digisales-fte-mobile-browser.git | S42: Katalon​ | V42: 13 hari | W42: 20 tc
B43: P24091 | C43: AMOSAL0068 | D43: Digisales-FTE Mobile APK (4B) | E43: 257 | F43: 257 | G43: 257 | H43: =G43/F43 -> 1 | I43: 254 | J43: =I43/F43 -> 0.98832685 | K43: Nov-Dec | L43: Mobile | M43: https://bankbnitbk.sharepoint.com/:f:/s/TEST212/EvzzQSkZgHtIo46EbcwpAKUBVU-0l60enMgmHRDjNWBkbQ?e=k341oe | N43: https://gitlab-dc.bni.co.id/coe-duplicate/test-automation/katalon-digisales-fte-mobile-apk.git | Q43: Unedo | S43: Katalon​ | V43: 264 hari / 12 bulan | W43: 20 tc | Y43: > | Z43: 88 hari / 4 bulan | AA43: asumsi 3 resource
B44: P24019 | C44: AMOCSR0273 | D44: Smart VA-Portal | E44: 669 | F44: 629 | G44: 629 | H44: =G44/F44 -> 1 | I44: 629 | J44: =I44/F44 -> 1 | K44: Dec-Jan | L44: Web | M44: https://bankbnitbk.sharepoint.com/:f:/s/TEST212/EsE_n7BKP49DtZV_DeXugQcBATb7DB5RJ5f3NFGwOL9xhw?e=0F4t6H | N44: https://gitlab.bni.co.id/coe-duplicate/test-automation/katalon-smartva-portal | Q44: Alkha, Akbar | R44: Thomas | S44: Katalon​
B45: P24015 | C45: AFONFO0032 | D45: BNIDirect Cash Management Lite-Cash Management Lite | E45: 32967 | F45: 32967 | G45: 4123 | H45: =G45/F45 -> 0.12506446 | I45: 4123 | J45: =I45/F45 -> 0.12506446 | K45: Dec-Mar | L45: Web | M45: https://bankbnitbk.sharepoint.com/:f:/s/TEST212/Egsdb85tRmRCjJTdK7ESwUcBZW6sNXh7vBtHANYVKTslLg?e=PHmO6I | N45: https://gitlab-dc.bni.co.id/coe-duplicate/test-automation/katalon-cash-management-lite.git | P45: cmlite_merge | Q45: Aulia, Unedo, Ilyas | R45: Thomas | S45: Katalon​
B46: P24016 | C46: AFONFO0078 | D46: BNIDirect Trade (e-Bank Guarantee)-GB Online | E46: 420 | F46: 329 | G46: 329 | H46: =G46/F46 -> 1 | I46: 329 | J46: =I46/F46 -> 1 | K46: Dec | L46: Web | M46: https://bankbnitbk.sharepoint.com/:f:/s/TEST212/EuvNp1NjryNPvVKPeNcz8cUB3NwobpvMfIWP6ChkfD4r5w?e=VvQG8q | N46: https://gitlab-dc.bni.co.id/coe-duplicate/test-automation/katalon-garansi-bank-online.git | Q46: Yudho, Willy | R46: Thomas, Marin | S46: Katalon​
B47: P24023 | C47: AMOLOM0276 | D47: Lendix (LMS Wholesale)-MVP 1 Sprint 1 | E47: 15 | F47: 15 | G47: 15 | H47: =G47/F47 -> 1 | I47: 15 | J47: =I47/F47 -> 1 | K47: Dec | L47: Web | N47: https://gitlab-dc.bni.co.id/coe-duplicate/test-automation/katalon-lms-wholesale.git | Q47: Mafa, Willy | R47: Mbincar, Thomas | S47: Katalon​
B48: P24023 | C48: AMOLOM0276 | D48: Lendix (LMS Wholesale)-MVP 1 Sprint 2 | E48: 16 | F48: 16 | G48: 16 | H48: =G48/F48 -> 1 | I48: 16 | J48: =I48/F48 -> 1 | K48: Dec | L48: Web | N48: https://gitlab-dc.bni.co.id/coe-duplicate/test-automation/katalon-lms-wholesale.git | Q48: Mafa, Willy | R48: Mbincar, Thomas | S48: Katalon​
B49: P24023 | C49: AMOLOM0276 | D49: Lendix (LMS Wholesale)-MVP 1 Sprint 3 | E49: 37 | F49: 37 | G49: 37 | H49: =G49/F49 -> 1 | I49: 37 | J49: =I49/G49 -> 1 | K49: Jan | L49: Web | N49: https://gitlab-dc.bni.co.id/coe-duplicate/test-automation/katalon-lms-wholesale.git | Q49: Mafa, Willy | R49: Mbincar, Thomas | S49: Katalon​
B50: P24023 | C50: AMOLOM0276 | D50: Lendix (LMS Wholesale)-MVP 1 Sprint 4 | E50: 21 | F50: 21 | G50: 21 | H50: =G50/F50 -> 1 | I50: 21 | J50: =I50/G50 -> 1 | K50: Jan | L50: Web | N50: https://gitlab-dc.bni.co.id/coe-duplicate/test-automation/katalon-lms-wholesale.git | Q50: Mafa, Willy | R50: Mbincar, Thomas | S50: Katalon​
B51: P24023 | C51: AMOCSR0268 | D51: Host QRIS-Web Portal Admin | E51: 39 | F51: 37 | G51: 37 | H51: =G51/F51 -> 1 | I51: 36 | J51: =I51/G51 -> 0.97297297 | K51: Nov | L51: Web | M51: https://bankbnitbk.sharepoint.com/:f:/s/COETeam/EugCZ5-rSd9GuUY9kaSt7pIBCLaxm3tdNVVoAsRss3_SXw?e=q9FY5x | N51: https://gitlab-dc.bni.co.id/coe-duplicate/test-automation/katalon-web-portal-admin.git | Q51: Mafa | R51: Mbincar | S51: Katalon​
B52: A24001 | C52: AMOMWI0302 | D52: Global File Exchange (GFX) | E52: 27 | F52: 27 | G52: 27 | H52: =G52/F52 -> 1 | I52: 27 | J52: =I52/F52 -> 1 | K52: Dec-Mar | L52: Dekstop | M52: https://bankbnitbk.sharepoint.com/:f:/s/TEST212/EmHDDzW75hxMkZ8Ld4K2AXkB1uEh9JmBnh-_fVmmSm5Teg?e=5gVlOq | N52: https://gitlab-dc.bni.co.id/coe-duplicate/test-automation/uft-gfx.git | Q52: Mafa | R52: Mbincar | S52: UFT​
B53: A24001 | C53: AMOSAL0259 | D53: RM Tool | E53: 2900 | F53: 307 | G53: 307 | H53: =G53/F53 -> 1 | I53: 307 | J53: =I53/F53 -> 1 | K53: Jan-Feb | L53: Web | M53: https://bankbnitbk.sharepoint.com/:f:/s/TEST212/En44M6Dgx1JNmHnpum_-qC4BqZNp-rDMF8sAIACMq7f6Og?e=Q5K8Xf | N53: https://gitlab-dc.bni.co.id/coe-duplicate/test-automation/uft-rm-tools.git | P53: rm_tools_merge | Q53: Willy, Yudho | R53: Thomas, Marin | S53: UFT​
B54: P24023 | C54: AMOSAL0038 | D54: BNI Move (Digitalisasi KUR)-Mobile BNI Move (Android) | E54: 169 | F54: 169 | G54: 160 | H54: =G54/F54 -> 0.94674556 | I54: 160 | J54: =I54/F54 -> 0.94674556 | K54: Feb-Jun | L54: Mobile | M54: https://bankbnitbk.sharepoint.com/:f:/s/TEST212/EnGaOMaxvvpMt1YXvnMJUoYBwWSQ6-ASx9MtqORLnLdw-w?e=HUA9sb | N54: https://gitlab-dc.bni.co.id/coe-duplicate/test-automation/katalon-bni-move.git | P54: yusuf | Q54: Yusuf | R54: Marin | S54: Katalon​ | T54: Samsung Galaxy A52
B55: P23003 | C55: AMOMWI0004 | D55: API Management-API Gateway | E55: 660 | F55: 658 | G55: 658 | H55: =G55/F55 -> 1 | I55: 658 | J55: =I55/F55 -> 1 | K55: Jan-Oct | L55: API | M55: https://bankbnitbk.sharepoint.com/:f:/s/TEST212/EkHylvVI_-NHkreXGOrLvDgBuEj6fKPO3ktyu_-69pu-nA?e=EVyUWF | N55: https://gitlab-dc.bni.co.id/coe-duplicate/test-automation/katalon-bni-api-gateway.git | Q55: Alkha, Andin | R55: Thomas | S55: Katalon​
B56: P23008 | C56: AMOOES0180 | D56: CX COMM | E56: 329 | F56: 329 | G56: 68 | H56: =G56/F56 -> 0.20668693 | I56: 68 | J56: =I56/F56 -> 0.20668693 | K56: Mar | L56: Web | M56: https://bankbnitbk.sharepoint.com/:f:/s/TEST212/EpE8MORMBY9LpiVlrjrHBSEBLU5JCww1dRj2oD3BRZaxZQ?e=NNMi3A | N56: https://gitlab-dc.bni.co.id/coe-duplicate/test-automation/katalon-cx-comm/-/tree/CXCOMM_alex?ref_type=heads | R56: Marin | S56: Katalon​
C57: AMOLOM0276 | D57: Lendix (LMS Wholesale)-MVP 2 Sprint 1 | E57: 704 | F57: 704 | G57: 59 | H57: =G57/F57 -> 0.083806818 | I57: 59 | J57: =I57/F57 -> 0.083806818 | K57: Mar | L57: Web | M57: https://bankbnitbk.sharepoint.com/:f:/s/TEST212/ErtDBAMjlOVEhInAqEwJMg4BS1QJKJWJ4EPzDH8BoZLRjg?e=P1LmP3 | N57: https://gitlab.bni.co.id/coe-duplicate/test-automation/katalon-lms-wholesale/-/tree/lms_mvp_2_sprint_1?ref_type=heads | Q57: Mafa | R57: Mbincar | S57: Katalon​
C58: AMOSAL0068 | D58: Digisales-Portal (5B) | E58: 143 | F58: 137 | G58: 137 | H58: =G58/F58 -> 1 | I58: 137 | J58: =I58/F58 -> 1 | K58: Mar | L58: Web | M58: https://bankbnitbk.sharepoint.com/:f:/s/TEST212/EnO2rxJNuchFpX8AeccRGBwB6E4KL2HD-pnyq4oaIIkGkg?e=1UX2KP | N58: https://gitlab-dc.bni.co.id/coe-duplicate/test-automation/katalon-digisales-portal-5b-fase-1.git | R58: Mbincar | S58: Katalon​
C59: AMOSAL0068 | D59: Digisales-Generalis Mobile Browser (5B) | E59: 261 | F59: 227 | G59: 227 | H59: =G59/F59 -> 1 | I59: 227 | J59: =I59/F59 -> 1 | K59: Mar | L59: Mobile | M59: https://bankbnitbk.sharepoint.com/:f:/s/TEST212/EjSIIQ-UTuhOn0w35tAgE7cBCajtwbZD_5MwixPwtcGVRQ?e=cC8p34 | N59: https://gitlab-dc.bni.co.id/coe-duplicate/test-automation/katalon-digisales-generalis-mobile-browser.git | S59: Katalon​
C60: AMOSAL0068 | D60: Digisales-Generalis Mobile APK (5B) | E60: 261 | F60: 232 | G60: 232 | H60: =G60/F60 -> 1 | I60: 232 | J60: =I60/F60 -> 1 | K60: Mar | L60: Mobile | M60: https://bankbnitbk.sharepoint.com/:f:/s/TEST212/EkBmeaU1c85IiWJlJWAM5M8BLepL1R6T8-lh8zjTEzCT9w?e=lk9hZb | N60: https://gitlab-dc.bni.co.id/coe-duplicate/test-automation/katalon-digisales-generalis-mobile-apk.git | S60: Katalon​ | W60: =E58+E59+E60+E18 -> 1187 | X60: =F58+F59+F60+F18 -> 729
C61: AMOSAL0068 | D61: Digisales-FTE Mobile Browser (5B) | E61: 311 | F61: 272 | G61: 270 | H61: =G61/F61 -> 0.99264706 | I61: 270 | J61: =I61/F61 -> 0.99264706 | K61: Feb-Mar | L61: Mobile | M61: https://bankbnitbk.sharepoint.com/:f:/s/TEST212/EiH7yAM0rVtMpHzYtcLAZ2kBfdhgzLfhROjy1G-3181jQA?e=Bii74T | N61: https://gitlab-dc.bni.co.id/coe-duplicate/test-automation/katalon-digisales-fte-mobile-browser.git | S61: Katalon​
C62: AMOSAL0068 | D62: Digisales-FTE Mobile APK (5B) | E62: 311 | F62: 299 | G62: 299 | H62: =G62/$F$62 -> 1 | I62: 299 | J62: =I62/F62 -> 1 | K62: Feb-Mar | L62: Mobile | M62: https://bankbnitbk.sharepoint.com/:f:/s/TEST212/EhfCiubekcNDqws3_z6Qs88Bf2O8z6EuXbjSBvjxGpV7jg?e=c997oc | N62: https://gitlab-dc.bni.co.id/coe-duplicate/test-automation/katalon-digisales-fte-mobile-apk.git | S62: Katalon​ | X62: 655
C63: AMOSAL0068 | D63: Digisales-Sales Farmer Mobile APK (5B) | E63: 259 | F63: 259 | G63: 259 | H63: =G63/$F$63 -> 1 | I63: 259 | J63: =I63/F63 -> 1 | K63: Feb-Mar | L63: Mobile | M63: https://bankbnitbk.sharepoint.com/:f:/s/TEST212/EpGn9xd6XFRFhfoQC-4eOp0BnnMmSnqdNgr0oq3Sh9ID_w?e=Tflu2X | N63: https://gitlab-dc.bni.co.id/coe-duplicate/test-automation/katalon-digisales-sales-farmer-mobile-apk.git | S63: Katalon​ | X63: 1952 | Z63: =SUM(X62:X68) -> 4336
C64: AMOSAL0068 | D64: Digisales-Sales Farmer Mobile Browser (5B) | E64: 259 | F64: 259 | G64: 259 | H64: =G64/$F$64 -> 1 | I64: 259 | J64: =I64/F64 -> 1 | K64: Feb-Mar | L64: Mobile | M64: https://bankbnitbk.sharepoint.com/:f:/s/TEST212/EtfHqjSV8Z9OnE7F75WlelwB3rOpoeV7wr4R181UlVuY8g?e=MXElRq | N64: https://gitlab-dc.bni.co.id/coe-duplicate/test-automation/katalon-digisales-sales-farmer-mobile-browser.git | S64: Katalon​ | X64: 134
C65: AMOSAL0068 | D65: Digisales-Portal (6C) | E65: 145 | F65: 134 | G65: 134 | H65: =G65/$F$65 -> 1 | I65: 134 | J65: =I65/F65 -> 1 | K65: Mei | L65: Web | M65: https://bankbnitbk.sharepoint.com/:f:/s/TEST212/EirMayUabUdEkXIAnu65NS8BqQKjYy3DaHy1YQ6MGjnUig?e=HV7due | N65: https://gitlab-dc.bni.co.id/coe-duplicate/test-automation/katalon-digisales-ms-form-portal-6c.git | S65: Katalon​ | X65: 98
C66: AMOSAL0068 | D66: Digisales-Portal (6D) | E66: 98 | F66: 98 | G66: 98 | H66: =G66/$F$66 -> 1 | I66: 98 | J66: =G66/$F$66 -> 1 | K66: Mei | L66: Web | M66: https://bankbnitbk.sharepoint.com/:f:/s/TEST212/EqKDBXnkBsNKim04CPE06vUBRk2AOSI3jMDlbnJizA-uCA?e=KdvnBn | N66: https://gitlab-dc.bni.co.id/coe-duplicate/test-automation/katalon-digisales-portal-6d/-/tree/dev_gafi?ref_type=heads | S66: Katalon​ | X66: 962
C67: AMOSAL0068 | D67: Digisales-Portal (7A) | E67: 55 | F67: 37 | G67: 37 | H67: =G67/$F$67 -> 1 | I67: 37 | J67: =G67/$F$67 -> 1 | K67: Mei | L67: Web | M67: https://bankbnitbk.sharepoint.com/:f:/s/TEST212/EpOdAPBTKopMnQkLcmeRrysBNqyQHgTEK_twRjTs45MNvw?e=V7pLlp | N67: https://gitlab-dc.bni.co.id/coe-duplicate/test-automation/katalon-digisales-portal-7a-portal.git | S67: Katalon​ | X67: 227
B68: P24015 | C68: ABOAST0111 | D68: BNI Direct FSCM | E68: 125 | F68: 125 | G68: 40 | H68: =G68/$F$68 -> 0.32 | I68: 40 | J68: =G68/$F$68 -> 0.32 | K68: Jun | L68: Web | M68: https://bankbnitbk.sharepoint.com/:f:/s/TEST212/Ev0NXfhPpW5Gkzs-mOGX16gBqNpNkJnpmDZWW9IYNXzwlw?e=F2Gqu2 | N68: https://gitlab-dc.bni.co.id/coe-duplicate/test-automation/bni-direct-fscm.git | S68: Katalon​ | X68: 308
B69: P24015 | C69: AFONFO0032 | D69: BNI Direct Bisnis | E69: =1672+515 -> 2187 | F69: =1653+515 -> 2168 | G69: =1002+644+308+60 -> 2014 | H69: =$G69/$F69 -> 0.92896679 | I69: =1002+644+308+60 -> 2014 | J69: =$I69/$F69 -> 0.92896679 | K69: July - | L69: Web | M69: https://bankbnitbk.sharepoint.com/:f:/s/TEST212/ElnsE9cKzSZNl0y4Yi22lYcB4ut0jQu60FUUFszXnRomWw?e=FBGvLa | N69: https://gitlab-dc.bni.co.id/coe-duplicate/test-automation/katalon-cash-management-lite.git | P69: cmlite_merge | S69: Katalon​
C70: AMOSAL0068 | D70: Digisales-Portal (7B) | E70: 297 | F70: 228 | G70: 227 | H70: =G70/$F$70 -> 0.99561404 | I70: 227 | J70: =G70/$F$70 -> 0.99561404 | K70: Aug | L70: Web | M70: https://bankbnitbk.sharepoint.com/sites/TEST212/Shared%20Documents/Forms/AllItems.aspx?id=%2Fsites%2FTEST212%2FShared%20Documents%2FGeneral%2FScripting%20Report%2FWeb%20Digisales%2FDigisales%20MVP%207B&viewid=5f45ee7e%2D4c73%2D41ad%2Dab32%2Dcf02db1420df&p=true&ga=1 | N70: https://gitlab.bni.co.id/coe-duplicate/test-automation/katalon-digisales-7b | S70: Katalon​
B71: P24015 | C71: AFONFO0032 | D71: BNI Direct Cash | E71: ='Modul BNI Direct 20260626'!C14 -> 12167 | F71: ='Modul BNI Direct 20260626'!D14 -> 7852 | G71: ='Modul BNI Direct 20260626'!E14 -> 5083 | H71: =$G71/$F71 -> 0.64735099 | I71: ='Modul BNI Direct 20260626'!E14 -> 5083 | J71: =$I71/$F71 -> 0.64735099 | K71: Dec-Oct | L71: Web | M71: https://bankbnitbk.sharepoint.com/:f:/s/COETeam/EvEFj3E9tBhCq_RyYCPs4ewBkMey9_B-sLYP-q1rkX5srw?e=0IKCpt | N71: https://gitlab-dc.bni.co.id/coe-duplicate/test-automation/katalon-cash-management-reguler.git
C72: AFONFO0032 | D72: SWMP / Direct Mobile | E72: 102 | F72: 102 | G72: 102 | H72: =$G72/$F72 -> 1 | I72: 102 | J72: =$G72/$F72 -> 1 | K72: Aug | L72: Mobile | M72: https://bankbnitbk.sharepoint.com/:f:/s/COETeam/EruzHPcPZoZGuA8i1T2C9WMB0fK30ITH24iVi_OLSMsNqA?e=XUTuBI | N72: https://gitlab-dc.bni.co.id/coe-duplicate/katalon-mobile-swmp-android.git
C73: AMOSAL0068 | D73: Digisales-Portal (8A) | E73: 754 | F73: 751 | G73: 751 | H73: =G73/F73 -> 1 | I73: 751 | J73: =G73/$F73 -> 1 | K73: Oct | L73: Web | M73: https://bankbnitbk.sharepoint.com/:f:/s/TEST212/ErRVf1KDEGNLr4zZOhZENJEBLrzdzXGX6LjY_3KXK9aYrA?e=cKfNIX | N73: https://gitlab-dc.bni.co.id/coe-duplicate/test-automation/katalon-digisales-8a | P73: andhini | S73: Katalon​
C74: AMOSAL0068 | D74: Digisales - Mobile Browser (7A) | E74: 499 | F74: 467 | G74: 457 | H74: =G74/F74 -> 0.97858672 | I74: 457 | J74: =G74/F74 -> 0.97858672 | K74: Oct | L74: Mobile | M74: https://bankbnitbk.sharepoint.com/:f:/s/TEST212/EnV4iKR0IUdBt5LizOfitP4BViEz4hX03Nm3xU-2xP2FNw?e=bxnKXx | N74: https://gitlab-dc.bni.co.id/coe-duplicate/test-automation/katalon-digisales-portal-7a-portal.git | P74: mikhael willy | S74: Katalon​
C75: AMOSAL0068 | D75: Digisales-Mobile APK (7A) | E75: 514 | F75: 468 | G75: 468 | H75: =G75/F75 -> 1 | I75: 468 | J75: =G75/F75 -> 1 | K75: Mei | L75: Mobile | M75: https://bankbnitbk.sharepoint.com/:f:/s/TEST212/Ev9QjAMCDF5PnE6lSb_cqWEBxNuZJSdHF0QPlrSLXvLIMw?e=Bsc9R0 | N75: https://gitlab-dc.bni.co.id/coe-duplicate/test-automation/katalon-digisales-portal-7a-portal.git | P75: alvin | S75: Katalon​
C76: AMOOES0309 | D76: DigIMS (Latest UI) | E76: 1151 | F76: 1125 | G76: 864 | H76: =G76/F76 -> 0.768 | I76: 864 | J76: =G76/F76 -> 0.768 | K76: Nov 2025 - now | L76: Web | M76: https://bankbnitbk.sharepoint.com/:f:/s/COETeam/IgDXkylQNrYJRqEdNtwzMEmzAe9Aqqc1qNYV3A8qNRTlVBo?e=6VfNeI | N76: https://gitlab-dc.bni.co.id/coe-duplicate/test-automation/katalon-digims.gitt | P76: dev_andhinyaye & dev_ali
C77: AMOSAL0068 | D77: Digisales Mobile APK (8A) | E77: 38 | F77: 38 | G77: 38 | H77: =G77/F77 -> 1 | I77: 38 | J77: =G77/$F77 -> 1 | K77: Oct | L77: Mobile | M77: https://bankbnitbk.sharepoint.com/:f:/s/TEST212/EqbDzLRXSqBPjveAyS7wVEoBOXJJK6fziPRjsCLc26vn9w?e=dPKnyD
C78: AMOSAL0068 | D78: Digisales Mobile Browser (8A) | E78: 38 | F78: 38 | G78: 38 | H78: =G78/F78 -> 1 | I78: 38 | J78: =G78/$F78 -> 1 | K78: Oct | L78: Mobile | M78: https://bankbnitbk.sharepoint.com/:f:/s/TEST212/EpX6nYWHcbVMnDs5avPcFJ0BxI7PZPjl8Ve86Mjwl1uT5g?e=7OLKAe | N78: https://gitlab-dc.bni.co.id/coe-duplicate/test-automation/katalon-digisales-8a/-/tree/dev_mobile_browser_mikhael?ref_type=heads
C79: AMOSAL0068 | D79: Digisales Mobile Browser (8b Phase 1) | E79: 1169 | F79: 1074 | G79: 997 | H79: =G79/F79 -> 0.9283054 | I79: 997 | J79: =G79/$F79 -> 0.9283054 | K79: Jan | L79: Mobile | M79: https://bankbnitbk.sharepoint.com/sites/TEST212/Shared%20Documents/Forms/AllItems.aspx?csf=1&web=1&e=aydZGo&CID=fffa208b%2D4f53%2D44d4%2Da03b%2D4372838d0eab&FolderCTID=0x01200013C42440C0BE0446A84C2940AA0E2843&id=%2Fsites%2FTEST212%2FShared%20Documents%2FGeneral%2FScripting%20Report%2FWeb%20Digisales%2FDigisales%20MVP%208b%20Phase%201 | N79: https://gitlab-dc.bni.co.id/coe-duplicate/test-automation/katalon-digisales-8b-phase-1
C80: AMOSAL0068 | D80: Digisales Portal (8b Phase 1) | E80: 1410 | F80: 1410 | G80: 217 | H80: =G80/F80 -> 0.15390071 | I80: 217 | J80: =G80/$F80 -> 0.15390071 | K80: Jan | L80: Web | M80: https://bankbnitbk.sharepoint.com/sites/TEST212/Shared%20Documents/Forms/AllItems.aspx?csf=1&web=1&e=aydZGo&CID=fffa208b%2D4f53%2D44d4%2Da03b%2D4372838d0eab&FolderCTID=0x01200013C42440C0BE0446A84C2940AA0E2843&id=%2Fsites%2FTEST212%2FShared%20Documents%2FGeneral%2FScripting%20Report%2FWeb%20Digisales%2FDigisales%20MVP%208b%20Phase%201 | N80: https://gitlab-dc.bni.co.id/coe-duplicate/test-automation/katalon-digisales-8b-phase-1
D81: Dashboard BGN | E81: 448 | F81: 362 | G81: 362 | H81: =G81/F81 -> 1 | I81: 362 | J81: =I81/F81 -> 1 | K81: 46113 | L81: Web | M81: https://bankbnitbk.sharepoint.com/:f:/s/TEST212/IgAmm4yf9iSJTItUHvNqmR9yASSMOa8HHNvDCbKzKykl5nM?e=a88cgn | N81: https://gitlab-dc.bni.co.id/coe-duplicate/test-automation/katalon-bgn | P81: dev
D82: Digisales New Platform (Mobile) | E82: 1123 | F82: 1000 | G82: 135 | H82: =G82/F82 -> 0.135 | I82: 135 | J82: =I82/F82 -> 0.135 | K82: 46174 | L82: Mobile | M82: https://bankbnitbk.sharepoint.com/sites/TEST212/Shared%20Documents/Forms/AllItems.aspx?id=%2Fsites%2FTEST212%2FShared%20Documents%2FGeneral%2FScripting%20Report%2FDigisales%20New%202026&viewid=5f45ee7e%2D4c73%2D41ad%2Dab32%2Dcf02db1420df&csf=1&CID=8c8ced04%2D801f%2D433a%2Da151%2Da1ae2c72e4a6&FolderCTID=0x01200013C42440C0BE0446A84C2940AA0E2843 | O82: https://bankbnitbk.sharepoint.com/:x:/r/sites/COETeam/_layouts/15/doc2.aspx?sourcedoc=%7Bd174dcaa-5001-4c31-acf0-3b3d63f86bcf%7D&action=edit&wdinitialsession=3f27e13e-2ca5-3928-dbd5-a5c05144c407&wdrldsc=3&wdrldc=1&wdrldr=RefreshingExpiredAccessToken&wdenableroaming=1&wdlcid=en-US&wdorigin=Other&wdredirectionreason=Force_SingleStepBoot
D83: Total | E83: =SUM(E6:E62) -> 89306 | F83: =SUM(F6:F62) -> 72096 | G83: =SUM(G6:G62) -> 33811 | I83: =SUM(I6:I62) -> 33761
G84: =G83/F83 -> 0.46897193 | I84: =I83/F83 -> 0.46827841
D86: 33 Aplikasi | E86: =E83-W60 -> 88119 | F86: =F83-X60 -> 71367
D92: Kelolaan Thomas | W92: Kelolaan Mbincar | AI92: Kelolaan Marin
B118: BNI Direct Cash
C119: Total tc | D119: Script automation
B120: Payroll | C120: 2773 | D120: 751
B121: Bulk Payment | C121: 2152 | D121: 577
B122: Transfer Management | C122: 3122 | D122: 180
B123: Tax Payment | C123: 753 | D123: 502
B124: VA Billing | C124: 979 | D124: 44
B125: Total | C125: =SUM(C120:C124) -> 9779 | D125: =SUM(D120:D124) -> 2054
B127: Api Gateway
C128: Total TC | D128: Scripting Automation
B129: Snap Service | C129: 51 | D129: 46
B130: Token snap v1&v1.0 | C130: 8 | D130: 8
B131: BNIDirect | C131: 37 | D131: 32
B132: OGP H2H | C132: 52 | D132: 47
B133: Snap BI Service (RTL) | C133: 76 | D133: 68
B134: SB Tapcash UBP | C134: 25 | D134: 21
...

Sheet Monthly Monitoring (2026)
B1: ="Last Update "&TEXT(NOW(),"DD MMMM YYYY HH:MM")&" WIB" -> Last Update 28 July 2026 16:18 WIB
B3: Data Capaian
B4: No | C4: Npp | D4: Nama | E4: Aplikasi | F4: Januari | G4: Februari | H4: Maret | I4: April | J4: Mei | K4: Juni | L4: Juli | M4: Agustus | N4: September | O4: Oktober | P4: November | Q4: Desember
B5: 1 | C5: P057974 | D5: SIlvester Kevin
B6: 2 | C6: P063945 | D6: Thomas Gunawan Sardjono
B7: 3 | C7: P062927 | D7: Marinda Ika Dewi Sakariana
B8: 4 | C8: P062928 | D8: Mbincar Rukun Sembiring
B9: 5 | C9: 821905 | D9: Burhan Aditya
B10: 6 | C10: 900654 | D10: Syafiq Ali Zhafran
B11: 7 | C11: 900800 | D11: Willy Honandar
B12: 8 | C12: 901164 | D12: Alfiko Utama
B13: 9 | C13: 901232 | D13: Mikhael Adriel Pratama Gana
B14: 10 | C14: 901233 | D14: Izaaz Waskito Widyarto
B15: 11 | C15: 901244 | D15: Dani Yudistira Maulana
B16: 12 | C16: 901450 | D16: Hanif Razin Rahmatullah
B17: 13 | C17: 901742 | D17: Pierre Azhanzi Ibrahim (Autodebet)
B18: 14 | C18: 901779 | D18: Zakiah Putri Madani (Avatar)
B19: 15 | C19: 901780 | D19: Marcelino Oktaviansyah (Avatar)
B20: 16 | C20: 901856 | D20: Firizki Fajri
... B23: 19 | C23: 901895 | D23: Abdul Aziz Permana (Avatar)

Sheet Weekly TC Application (2024)
B1: Last Update 04 October 2024 08:10 WIB
B3: Data Capaian Scripting per-Individu
B4: No | C4: Npp | D4: Nama | E4: Aplikasi | F4: 2024 | G4: Jan-W1 | H4: Jan-W2 | I4: Jan-W3 | J4: Jan-W4 | K4: Jan-W5 | L4: Feb-W1 | M4: Feb-W2 | N4: Feb-W3 | O4: Feb-W4 | P4: Mar-W1 | Q4: Mar-W2 | R4: Mar-W3 | S4: Mar-W4 | T4: Apr-W1 | U4: Apr-W2 | V4: Apr-W3 | W4: Apr-W4 | X4: May-W1 | Y4: May-W2 | Z4: May-W3 | AA4: May-W4 | AB4: May-W5 | AC4: Jun-W1 | AD4: Jun-W2 | AE4: Jun-W3 | AF4: Jun-W4 | AG4: Jul-W1 | AH4: Jul-W2 | AI4: Jul-W3 | AJ4: Jul-W4 | AK4: Jul-W5 | AL4: Aug-W1 | AM4: Aug-W2 | AN4: Aug-W3 | AO4: Aug-W4 | AP4: Sep-W1 | AQ4: Sep-W2 | AR4: Sep-W3 | AS4: Sep-W4 | AT4: Oct-W1 | AU4: Oct-W2 | AV4: Oct-W3 | AW4: Oct-W4 | AX4: Oct-W5 | AY4: Nov-W1 | AZ4: Nov-W2 | BA4: Nov-W3 | BB4: Nov-W4 | BC4: Dec-W1 | BD4: Dec-W2 | BE4: Dec-W3 | BF4: Dec-W4
B5: 1 | C5: P057974 | D5: SIlvester Kevin | E5: - | F5: =SUM(F6:F23) -> 3251 | G5: - | H5: - | I5: - | J5: - | K5: - | L5: - | M5: - | N5: - | O5: - | P5: - | Q5: - | R5: - | S5: - | T5: - | U5: - | V5: - | W5: - | X5: - | Y5: - | Z5: - | AA5: - | AB5: - | AC5: - | AD5: - | AE5: - | AF5: - | AG5: - | AH5: - | AI5: - | AJ5: - | AK5: - | AL5: - | AM5: - | AN5: - | AO5: - | AP5: - | AQ5: - | AR5: - | AS5: - | AT5: - | AU5: - | AV5: - | AW5: - | AX5: - | AY5: - | AZ5: - | BA5: - | BB5: - | BC5: - | BD5: - | BE5: - | BF5: -
B6: 2 | C6: P063945 | D6: Thomas Gunawan Sardjono | E6: BNI Direct Lite | F6: =SUM(G6:BF6) -> 922 | G6: 0 | H6: 0 | I6: 0 | J6: 0 | K6: 0 | L6: 0 | M6: 0 | N6: 0 | O6: 0 | P6: 0 | Q6: 416 | R6: 0 | S6: 0 | T6: 0 | U6: 0 | V6: 0 | W6: 0 | X6: 0 | Y6: 415 | Z6: 7 | AA6: 7 | AB6: 11 | AC6: 20 | AD6: 6 | AE6: 9 | AF6: 0 | AG6: 9 | AH6: 3 | AI6: 2 | AJ6: 7 | AK6: 7 | AL6: 3 | AM6: 0 | AN6: 0 | AO6: 0 | AP6: 0 | AQ6: 0 | AR6: 0 | AS6: 0 | AT6: 0 | AU6: 0 | AV6: 0 | AW6: 0 | AX6: 0 | AY6: 0 | AZ6: 0 | BA6: 0 | BB6: 0 | BC6: 0 | BD6: 0 | BE6: 0 | BF6: 0
E7: CXO Onboarding | F7: =SUM(G7:BF7) -> 0 | G7: 0 | H7: 0 | I7: 0 | J7: 0 | K7: 0 | L7: 0 | M7: 0 | N7: 0 | O7: 0 | P7: 0 | Q7: 0 | R7: 0 | S7: 0 | T7: 0 | U7: 0 | V7: 0 | W7: 0 | X7: 0 | Y7: 0 | Z7: 0 | AA7: 0 | AB7: 0 | AC7: 0 | AD7: 0 | AE7: 0 | AF7: 0 | AG7: 0 | AH7: 0 | AI7: 0 | AJ7: 0 | AK7: 0 | AL7: 0 | AM7: 0 | AN7: 0 | AO7: 0 | AP7: 0 | AQ7: 0 | AR7: 0 | AS7: 0 | AT7: 0 | AU7: 0 | AV7: 0 | AW7: 0 | AX7: 0 | AY7: 0 | AZ7: 0 | BA7: 0 | BB7: 0 | BC7: 0 | BD7: 0 | BE7: 0 | BF7: 0
E8: Tiplus SFE | F8: =SUM(G8:BF8) -> 218 | G8: 0 | H8: 0 | I8: 0 | J8: 0 | K8: 0 | L8: 0 | M8: 0 | N8: 0 | O8: 0 | P8: 0 | Q8: 0 | R8: 0 | S8: 0 | T8: 0 | U8: 0 | V8: 0 | W8: 0 | X8: 0 | Y8: 0 | Z8: 0 | AA8: 0 | AB8: 0 | AC8: 0 | AD8: 3 | AE8: 7 | AF8: 2 | AG8: 9 | AH8: 37 | AI8: 34 | AJ8: 30 | AK8: 35 | AL8: 28 | AM8: 9 | AN8: 12 | AO8: 12 | AP8: 0 | AQ8: 0 | AR8: 0 | AS8: 0 | AT8: 0 | AU8: 0 | AV8: 0 | AW8: 0 | AX8: 0 | AY8: 0 | AZ8: 0 | BA8: 0 | BB8: 0 | BC8: 0 | BD8: 0 | BE8: 0 | BF8: 0
E9: Tiplus UFE | F9: =SUM(G9:BF9) -> 0
E10: Web Agen46 | F10: =SUM(G10:BF10) -> 1003 | G10: 1000 | H10: 0 | I10: 1 | J10: 2
B11: 3 | C11: P062927 | D11: Marinda Ika Dewi Sakariana | E11: ICONS Tokyo | F11: =SUM(G11:BF11) -> 171 | G11: 171 | H11: 0 | I11: 0 | J11: 0 | K11: 0 | L11: 0 | M11: 0 | N11: 0 | O11: 0 | P11: 0 | Q11: 0 | R11: 0 | S11: 0 | T11: 0 | U11: 0 | V11: 0 | W11: 0 | X11: 0 | Y11: 0 | Z11: 0 | AA11: 0 | AB11: 0 | AC11: 0 | AD11: 0
E12: ICONS London | F12: =SUM(G12:BF12) -> 650 | G12: 0 | H12: 0 | I12: 0 | J12: 0 | K12: 0 | L12: 0 | M12: 0 | N12: 0 | O12: 0 | P12: 0 | Q12: 0 | R12: 0 | S12: 0 | T12: 0 | U12: 0 | V12: 0 | W12: 650 | X12: 0 | Y12: 0 | Z12: 0 | AA12: 0 | AB12: 0 | AC12: 0 | AD12: 0
E13: ICONS Alternity | F13: =SUM(G13:BF13) -> 0
E14: ICONS Poseidon | F14: =SUM(G14:BF14) -> 120 | G14: 0 | H14: 15 | I14: 15 | J14: 0 | K14: 0 | L14: 2 | M14: 25 | N14: 1 | O14: 0 | P14: 10 | Q14: 11 | R14: 22 | S14: 10 | T14: 0 | U14: 0 | V14: 0 | W14: 0 | X14: 0 | Y14: 0 | Z14: 8 | AA14: 1 | AB14: 0 | AC14: 0 | AD14: 0
B15: 4 | C15: P062928 | D15: Mbincar Rukun Sembiring | E15: Ibank Remittance Fase 1 | F15: =SUM(G15:BF15) -> 0
E16: Ibank Remittance Fase 2 | F16: =SUM(G16:BF16) -> 0
E17: Ibank Remittance Fase 3 | F17: =SUM(G17:BF17) -> 0
E18: BNI Direct Reguler / Reskining | F18: =SUM(G18:BF18) -> 0
E19: SMS Menu (Android) | F19: =SUM(G19:BF19) -> 0
E20: Wondr Bussiness | F20: =SUM(G20:BF20) -> 0
E21: LMS Wholesale Sprint 1 | F21: =SUM(G21:BF21) -> 0
E22: CXO Onboarding | F22: =SUM(G22:BF22) -> 0
E23: Web Agen46 | F23: =SUM(G23:BF23) -> 167 | G23: 0 | H23: 0 | I23: 0 | J23: 0 | K23: 0 | L23: 0 | M23: 65 | N23: 102 | O23: 0 | P23: 0 | Q23: 0 | R23: 0 | S23: 0 | T23: 0 | U23: 0 | V23: 0 | W23: 0 | X23: 0 | Y23: 0 | Z23: 0 | AA23: 0 | AB23: 0 | AC23: 0 | AD23: 0
B24: 5 | C24: 821905 | D24: Burhan Aditya | E24: BNI Direct Lite | F24: =SUM(G24:BF24) -> 7 | G24: 0 | H24: 0 | I24: 0 | J24: 0 | K24: 0 | L24: 0 | M24: 0 | N24: 0 | O24: 0 | P24: 0 | Q24: 0 | R24: 0 | S24: 0 | T24: 0 | U24: 0 | V24: 0 | W24: 1 | X24: 6 | Y24: 0 | Z24: 0 | AA24: 0 | AB24: 0 | AC24: 0 | AD24: 0
E25: Mobile Banking (Android) | F25: =SUM(G25:BF25) -> 0
E26: BAMS-TAT
B27: 6 | C27: 900674 | D27: Andinira Rizki Syafitri | E27: Tiplus SFE | F27: =SUM(G27:BF27) -> 0
E28: Tiplus Export Local | F28: =SUM(G28:BF28) -> 87 | G28: 0 | H28: 0 | I28: 0 | J28: 0 | K28: 0 | L28: 0 | M28: 0 | N28: 0 | O28: 0 | P28: 0 | Q28: 0 | R28: 0 | S28: 0 | T28: 0 | U28: 0 | V28: 0 | W28: 0 | Z28: 6 | AA28: 5 | AB28: 12 | AC28: 19 | AD28: 6 | AE28: 2 | AF28: 7 | AG28: 9 | AH28: 2 | AI28: 2 | AJ28: 10 | AK28: 7
B29: 7 | C29: 900733 | D29: Al Khawarismi Atma Pratama | E29: Tiplus UFE | F29: =SUM(G29:BF29) -> 171 | G29: 171 | H29: 0 | I29: 0 | J29: 0 | K29: 0 | L29: 0 | M29: 0 | N29: 0 | O29: 0 | P29: 0 | Q29: 0 | R29: 0 | S29: 0 | T29: 0 | U29: 0 | V29: 0 | W29: 0 | X29: 0 | Y29: 0 | Z29: 0 | AA29: 0 | AB29: 0 | AC29: 0 | AD29: 0
E30: Web Agen46 | F30: =SUM(G30:BF30) -> 415 | G30: 0 | H30: 0 | I30: 0 | J30: 0 | K30: 0 | L30: 0 | M30: 0 | N30: 0 | O30: 0 | P30: 0 | Q30: 415 | R30: 0 | S30: 0 | T30: 0 | U30: 0 | V30: 0 | W30: 0 | X30: 0 | Y30: 0 | Z30: 0 | AA30: 0 | AB30: 0 | AC30: 0 | AD30: 0
E31: DigIMS
B32: 8 | C32: 900692 | D32: Muhamad Ilyas Azmi Dewanto | E32: CXO Onboarding | F32: =SUM(G32:BF32) -> 366 | G32: 0 | H32: 0 | I32: 0 | J32: 0 | K32: 0 | L32: 0 | M32: 0 | N32: 4 | O32: 0 | P32: 0 | Q32: 0 | R32: 10 | S32: 0 | T32: 18 | U32: 37 | V32: 4 | W32: 3 | X32: 16 | Y32: 27 | Z32: 24 | AA32: 41 | AB32: 26 | AC32: 43 | AD32: 0 | AE32: 3 | AF32: 14 | AG32: 8 | AH32: 13 | AI32: 23 | AJ32: 38 | AK32: 14
F33: =SUM(G33:BF33) -> 0
B34: 9 | C34: 900800 | D34: Willy Honandar | E34: Mobile Credit Card (Android) | F34: =SUM(G34:BF34) -> 118 | G34: 0 | H34: 0 | I34: 0 | J34: 0 | K34: 0 | L34: 0 | M34: 0 | N34: 0 | O34: 0 | P34: 0 | Q34: 0 | R34: 0 | S34: 0 | T34: 0 | U34: 0 | V34: 0 | W34: 9 | X34: 1 | Y34: 7 | Z34: 29 | AA34: 22 | AB34: 21 | AC34: 0 | AD34: 0 | AH34: 17 | AI34: 4 | AJ34: 4 | AL34: 4
E35: Mobile Credit Card (iOS) | F35: =SUM(G35:BF35) -> 0 | G35: 0 | H35: 0 | I35: 0 | J35: 0 | K35: 0 | L35: 0 | M35: 0 | N35: 0 | O35: 0 | P35: 0 | Q35: 0 | R35: 0 | S35: 0 | T35: 0 | U35: 0 | V35: 0 | W35: 0 | X35: 0 | Y35: 0 | Z35: 0 | AA35: 0 | AB35: 0 | AC35: 0 | AD35: 0
E36: DMS Sprint 1
E37: DMS Sprint 2
E38: DMS Sprint 3
B39: 10 | C39: 900654 | D39: Syafiq Ali Zhafran | E39: Tiplus Guarante Bank | F39: =SUM(G39:BF39) -> 0 | G39: 0 | H39: 0 | I39: 0 | J39: 0 | K39: 0 | L39: 0 | M39: 0 | N39: 0 | O39: 0 | P39: 0 | Q39: 0 | R39: 0 | S39: 0 | T39: 0 | U39: 0 | V39: 0 | W39: 0 | X39: 0 | Y39: 0 | Z39: 0 | AA39: 0 | AB39: 0 | AC39: 0 | AD39: 0
F40: =SUM(G40:BF40) -> 49 | G40: 0 | H40: 0 | I40: 0 | J40: 0 | K40: 0 | L40: 0 | M40: 0 | N40: 0 | O40: 0 | P40: 0 | Q40: 0 | R40: 0 | S40: 0 | T40: 0 | U40: 0 | V40: 0 | W40: 0 | X40: 0 | Y40: 0 | Z40: 0 | AA40: 0 | AB40: 0 | AC40: 0 | AD40: 0 | AE40: 0 | AF40: 0 | AG40: 0 | AH40: 0 | AI40: 0 | AJ40: 39 | AK40: 9 | AL40: 1
B41: 11 | C41: 821972 | D41: Yusuf Tri Wibowo | E41: ICONS Alternity | F41: =SUM(G41:BF41) -> 0 | G41: 0 | H41: 0 | I41: 0 | J41: 0 | K41: 0 | L41: 0 | M41: 0 | N41: 0 | O41: 0 | P41: 0 | Q41: 0 | R41: 0 | S41: 0 | T41: 0 | U41: 0 | V41: 0 | W41: 0 | X41: 0 | Y41: 0 | Z41: 0 | AA41: 0 | AB41: 0 | AC41: 0 | AD41: 0 | AE41: 0 | AF41: 0 | AG41: 0 | AH41: 0 | AI41: 0
E42: ICONS Poseidon | F42: =SUM(G42:BF42) -> 0 | AB42: 0 | AC42: 0 | AD42: 0 | AE42: 0 | AF42: 0 | AG42: 0 | AH42: 0 | AI42: 0
E43: ICONS London | F43: =SUM(G43:BF43) -> 49 | G43: 0 | H43: 0 | I43: 0 | J43: 0 | K43: 0 | L43: 0 | M43: 0 | N43: 0 | O43: 0 | P43: 0 | Q43: 0 | R43: 0 | S43: 0 | T43: 0 | U43: 0 | V43: 0 | W43: 0 | X43: 0 | Y43: 0 | Z43: 0 | AA43: 0 | AB43: 0 | AC43: 0 | AD43: 0 | AE43: 0 | AF43: 0 | AG43: 0 | AH43: 0 | AI43: 0 | AJ43: 39 | AK43: 9 | AL43: 1
B44: 12 | C44: 900168 | D44: Alexander Bernadus Sungkono | E44: ICONS Alternity | F44: =SUM(G44:BF44) -> 0 | G44: 0 | H44: 0 | I44: 0 | J44: 0 | K44: 0 | L44: 0 | M44: 0 | N44: 0 | O44: 0 | P44: 0 | Q44: 0 | R44: 0 | S44: 0 | T44: 0 | U44: 0 | V44: 0 | W44: 0 | X44: 0 | Y44: 0 | Z44: 0 | AA44: 0 | AB44: 0 | AC44: 0 | AD44: 0 | AE44: 0 | AF44: 0 | AG44: 0 | AH44: 0 | AI44: 0
E45: ICONS Poseidon | F45: =SUM(G45:BF45) -> 0 | AB45: 0 | AC45: 0 | AD45: 0 | AE45: 0 | AF45: 0 | AG45: 0 | AH45: 0 | AI45: 0
E46: ICONS Tokyo | F46: =SUM(G46:BF46) -> 49 | G46: 0 | H46: 0 | I46: 0 | J46: 0 | K46: 0 | L46: 0 | M46: 0 | N46: 0 | O46: 0 | P46: 0 | Q46: 0 | R46: 0 | S46: 0 | T46: 0 | U46: 0 | V46: 0 | W46: 0 | X46: 0 | Y46: 0 | Z46: 0 | AA46: 0 | AB46: 0 | AC46: 0 | AD46: 0 | AE46: 0 | AF46: 0 | AG46: 0 | AH46: 0 | AI46: 0 | AJ46: 39 | AK46: 9 | AL46: 1
B47: 13 | C47: 900740 | D47: Muhammad Yudho Ardianto | E47: ICONS Alternity | F47: =SUM(G47:BF47) -> 0 | G47: 0 | H47: 0 | I47: 0 | J47: 0 | K47: 0 | L47: 0 | M47: 0 | N47: 0 | O47: 0 | P47: 0 | Q47: 0 | R47: 0 | S47: 0 | T47: 0 | U47: 0 | V47: 0 | W47: 0 | X47: 0 | Y47: 0 | Z47: 0 | AA47: 0 | AB47: 0 | AC47: 0 | AD47: 0 | AE47: 0 | AF47: 0 | AG47: 0 | AH47: 0 | AI47: 0
E48: ICONS Poseidon | F48: =SUM(G48:BF48) -> 49 | G48: 0 | H48: 0 | I48: 0 | J48: 0 | K48: 0 | L48: 0 | M48: 0 | N48: 0 | O48: 0 | P48: 0 | Q48: 0 | R48: 0 | S48: 0 | T48: 0 | U48: 0 | V48: 0 | W48: 0 | X48: 0 | Y48: 0 | Z48: 0 | AA48: 0 | AB48: 0 | AC48: 0 | AD48: 0 | AE48: 0 | AF48: 0 | AG48: 0 | AH48: 0 | AI48: 0 | AJ48: 39 | AK48: 9 | AL48: 1
B49: 14 | C49: 900201 | D49: Muhammad Akbar | E49: Ibank Remittance Fase 1 | F49: =SUM(G49:BF49) -> 0 | G49: 0 | H49: 0 | I49: 0 | J49: 0 | K49: 0 | L49: 0 | M49: 0 | N49: 0 | O49: 0 | P49: 0 | Q49: 0 | R49: 0 | S49: 0 | T49: 0 | U49: 0 | V49: 0 | W49: 0 | X49: 0 | Y49: 0 | Z49: 0 | AA49: 0 | AB49: 0 | AC49: 0 | AD49: 0 | AE49: 0 | AF49: 0 | AG49: 0 | AH49: 0 | AI49: 0
E50: Ibank Remittance Fase 2 | F50: =SUM(G50:BF50) -> 0 | AB50: 0 | AC50: 0 | AD50: 0 | AE50: 0 | AF50: 0 | AG50: 0 | AH50: 0 | AI50: 0
E51: Ibank Remittance Fase 3 | F51: =SUM(G51:BF51) -> 0 | AB51: 0 | AC51: 0 | AD51: 0 | AE51: 0 | AF51: 0 | AG51: 0 | AH51: 0 | AI51: 0
E52: BNI Direct Reguler / Reskining | F52: =SUM(G52:BF52) -> 49 | G52: 0 | H52: 0 | I52: 0 | J52: 0 | K52: 0 | L52: 0 | M52: 0 | N52: 0 | O52: 0 | P52: 0 | Q52: 0 | R52: 0 | S52: 0 | T52: 0 | U52: 0 | V52: 0 | W52: 0 | X52: 0 | Y52: 0 | Z52: 0 | AA52: 0 | AB52: 0 | AC52: 0 | AD52: 0 | AE52: 0 | AF52: 0 | AG52: 0 | AH52: 0 | AI52: 0 | AJ52: 39 | AK52: 9 | AL52: 1
E53: Mobile Banking (Android)
B54: 15 | C54: 821842 | D54: M. Alvin Fahrian | E54: SMS Menu (Android) | F54: =SUM(G54:BF54) -> 0 | G54: 0 | H54: 0 | I54: 0 | J54: 0 | K54: 0 | L54: 0 | M54: 0 | N54: 0 | O54: 0 | P54: 0 | Q54: 0 | R54: 0 | S54: 0 | T54: 0 | U54: 0 | V54: 0 | W54: 0 | X54: 0 | Y54: 0 | Z54: 0 | AA54: 0 | AB54: 0 | AC54: 0 | AD54: 0 | AE54: 0 | AF54: 0 | AG54: 0 | AH54: 0 | AI54: 0
E55: Wondr Bussiness | F55: =SUM(G55:BF55) -> 49 | G55: 0 | H55: 0 | I55: 0 | J55: 0 | K55: 0 | L55: 0 | M55: 0 | N55: 0 | O55: 0 | P55: 0 | Q55: 0 | R55: 0 | S55: 0 | T55: 0 | U55: 0 | V55: 0 | W55: 0 | X55: 0 | Y55: 0 | Z55: 0 | AA55: 0 | AB55: 0 | AC55: 0 | AD55: 0 | AE55: 0 | AF55: 0 | AG55: 0 | AH55: 0 | AI55: 0 | AJ55: 39 | AK55: 9 | AL55: 1
E56: Mobile Banking (Android)
B57: 16 | C57: 900738 | D57: Mafasyafa Annisa Zukhruff | E57: Wondr Bussiness | F57: =SUM(G57:BF57) -> 0 | G57: 0 | H57: 0 | I57: 0 | J57: 0 | K57: 0 | L57: 0 | M57: 0 | N57: 0 | O57: 0 | P57: 0 | Q57: 0 | R57: 0 | S57: 0 | T57: 0 | U57: 0 | V57: 0 | W57: 0 | X57: 0 | Y57: 0 | Z57: 0 | AA57: 0 | AB57: 0 | AC57: 0 | AD57: 0 | AE57: 0 | AF57: 0 | AG57: 0 | AH57: 0 | AI57: 0
E58: Ibank Remittance Fase 2 | F58: =SUM(G58:BF58) -> 0 | AB58: 0 | AC58: 0 | AD58: 0 | AE58: 0 | AF58: 0 | AG58: 0 | AH58: 0 | AI58: 0
E59: Ibank Remittance Fase 3 | F59: =SUM(G59:BF59) -> 0 | AB59: 0 | AC59: 0 | AD59: 0 | AE59: 0 | AF59: 0 | AG59: 0 | AH59: 0 | AI59: 0
E60: LMS Wholesale Sprint 1 | F60: =SUM(G60:BF60) -> 49 | G60: 0 | H60: 0 | I60: 0 | J60: 0 | K60: 0 | L60: 0 | M60: 0 | N60: 0 | O60: 0 | P60: 0 | Q60: 0 | R60: 0 | S60: 0 | T60: 0 | U60: 0 | V60: 0 | W60: 0 | X60: 0 | Y60: 0 | Z60: 0 | AA60: 0 | AB60: 0 | AC60: 0 | AD60: 0 | AE60: 0 | AF60: 0 | AG60: 0 | AH60: 0 | AI60: 0 | AJ60: 39 | AK60: 9 | AL60: 1
E61: LMS Wholesale Sprint 2
B62: 17 | C62: 900665 | D62: Gafiliano Gapili | E62: CXO Onboarding | F62: =SUM(G62:BF62) -> 0 | G62: 0 | H62: 0 | I62: 0 | J62: 0 | K62: 0 | L62: 0 | M62: 0 | N62: 0 | O62: 0 | P62: 0 | Q62: 0 | R62: 0 | S62: 0 | T62: 0 | U62: 0 | V62: 0 | W62: 0 | X62: 0 | Y62: 0 | Z62: 0 | AA62: 0 | AB62: 0 | AC62: 0 | AD62: 0 | AE62: 0 | AF62: 0 | AG62: 0 | AH62: 0 | AI62: 0
F63: =SUM(G63:BF63) -> 49 | G63: 0 | H63: 0 | I63: 0 | J63: 0 | K63: 0 | L63: 0 | M63: 0 | N63: 0 | O63: 0 | P63: 0 | Q63: 0 | R63: 0 | S63: 0 | T63: 0 | U63: 0 | V63: 0 | W63: 0 | X63: 0 | Y63: 0 | Z63: 0 | AA63: 0 | AB63: 0 | AC63: 0 | AD63: 0 | AE63: 0 | AF63: 0 | AG63: 0 | AH63: 0 | AI63: 0 | AJ63: 39 | AK63: 9 | AL63: 1
B64: 18 | C64: 900793 | D64: Unedo Ignasius Manalu | E64: Web Agen46 | F64: =SUM(G64:BF64) -> 0 | G64: 0 | H64: 0 | I64: 0 | J64: 0 | K64: 0 | L64: 0 | M64: 0 | N64: 0 | O64: 0 | P64: 0 | Q64: 0 | R64: 0 | S64: 0 | T64: 0 | U64: 0 | V64: 0 | W64: 0 | X64: 0 | Y64: 0 | Z64: 0 | AA64: 0 | AB64: 0 | AC64: 0 | AD64: 0 | AE64: 0 | AF64: 0 | AG64: 0 | AH64: 0 | AI64: 0
E65: DMS Sprint 2 | F65: =SUM(G65:BF65) -> 49 | G65: 0 | H65: 0 | I65: 0 | J65: 0 | K65: 0 | L65: 0 | M65: 0 | N65: 0 | O65: 0 | P65: 0 | Q65: 0 | R65: 0 | S65: 0 | T65: 0 | U65: 0 | V65: 0 | W65: 0 | X65: 0 | Y65: 0 | Z65: 0 | AA65: 0 | AB65: 0 | AC65: 0 | AD65: 0 | AE65: 0 | AF65: 0 | AG65: 0 | AH65: 0 | AI65: 0 | AJ65: 39 | AK65: 9 | AL65: 1
B68: No | C68: Aplikasi | D68: Status | E68: Pelaksana
B69: 1 | C69: ICONS Tokyo | E69: Marin
B70: 2 | C70: ICONS London | E70: Marin
B71: 3 | C71: ICONS Alternity | E71: Marin
B72: 4 | C72: ICONS Poseidon | E72: Marin
B73: 5 | C73: BNI Direct Reguler / Reskinning | E73: Thomas, Mbincar
B74: 6 | C74: BNI Direct Lite | E74: Thomas, Mbincar
B75: 7 | C75: CXO Onboarding | E75: Thomas, Mbincar
B76: 8 | C76: Tiplus UFE | E76: Thomas
B77: 9 | C77: Tiplus SFE | E77: Thomas
B78: 10 | C78: Tiplus Export Local | E78: Thomas
B79: 11 | C79: Ibank Remittance Fase 1 | E79: Thomas, Mbincar
B80: 12 | C80: Ibank Remittance Fase 2 | E80: Thomas, Mbincar
... B102: 34 | C102: Digisales FTE Mobile APK | E102: Thomas, Mbincar

Sheet Weekly TC Team
C1: Last Update 04 October 2024 08:10 WIB
B4: Year | D4: Thomas Gunawan Sardjono | E4: Andinira Rizki Syafitri | F4: Al Khawarismi Atma Pratama | G4: Burhan Aditya | H4: Muhamad Ilyas Azmi Dewanto | I4: Willy Honandar
C5: 2024 | D5: 0 | E5: 0 | F5: 0 | G5: 0 | H5: 0 | I5: 0
B6: January | C6: Jan-W1 | D6: 25 | E6: 0 | F6: 0 | G6: 0 | H6: 0 | I6: 0
C7: Jan-W2 | D7: 50 | E7: 0 | F7: 0 | G7: 0 | H7: 0 | I7: 0
C8: Jan-W3 | D8: 75 | E8: 0 | F8: 0 | G8: 0 | H8: 0 | I8: 0
C9: Jan-W4 | D9: 25 | E9: 0 | F9: 0 | G9: 0 | H9: 0 | I9: 0
C10: Jan-W5 | D10: 50 | E10: 0 | F10: 0 | G10: 0 | H10: 0 | I10: 0
B12: February | C12: Feb-W1 | D12: 50 | E12: 0 | F12: 0 | G12: 0 | H12: 0 | I12: 0
C13: Feb-W2 | D13: 75 | E13: 0 | F13: 0 | G13: 0 | H13: 0 | I13: 0
C14: Feb-W3 | D14: 25 | E14: 0 | F14: 0 | G14: 0 | H14: 0 | I14: 0
C15: Feb-W4 | D15: 50 | E15: 0 | F15: 0 | G15: 0 | H15: 0 | I15: 0
B17: March | C17: Mar-W1 | D17: 75 | E17: 0 | F17: 0 | G17: 0 | H17: 0 | I17: 0
C18: Mar-W2 | D18: 25 | E18: 0 | F18: 0 | G18: 0 | H18: 0 | I18: 0
C19: Mar-W3 | D19: 50 | E19: 0 | F19: 0 | G19: 0 | H19: 0 | I19: 0
C20: Mar-W4 | D20: 75 | E20: 0 | F20: 0 | G20: 0 | H20: 0 | I20: 0
B22: April | C22: Apr-W1 | D22: 40 | E22: 0 | F22: 0 | G22: 0 | H22: 0 | I22: 0
C23: Apr-W2 | D23: 40 | E23: 0 | F23: 0 | G23: 0 | H23: 0 | I23: 0
C24: Apr-W3 | D24: 40 | E24: 0 | F24: 0 | G24: 0 | H24: 0 | I24: 0
C25: Apr-W4 | D25: 40 | E25: 0 | F25: 0 | G25: 0 | H25: 0 | I25: 0
B27: May | C27: May-W1 | D27: 40 | E27: 0 | F27: 0 | G27: 0 | H27: 0 | I27: 0
C28: May-W2 | D28: 40 | E28: 0 | F28: 0 | G28: 0 | H28: 0 | I28: 0
C29: May-W3 | D29: 40 | E29: 0 | F29: 0 | G29: 0 | H29: 0 | I29: 0
C30: May-W4 | D30: 40 | E30: 0 | F30: 0 | G30: 0 | H30: 0 | I30: 0
C31: May-W5 | D31: 40 | E31: 0 | F31: 0 | G31: 0 | H31: 0 | I31: 0
B33: June | C33: Jun-W1 | D33: 40 | E33: 0 | F33: 0 | G33: 0 | H33: 0 | I33: 0
C34: Jun-W2 | D34: 40 | E34: 0 | F34: 0 | G34: 0 | H34: 0 | I34: 0
C35: Jun-W3 | D35: 40 | E35: 0 | F35: 0 | G35: 0 | H35: 0 | I35: 0
C36: Jun-W4 | D36: 40 | E36: 0 | F36: 0 | G36: 0 | H36: 0 | I36: 0
B38: July | C38: Jul-W1 | D38: 40 | E38: 0 | F38: 0 | G38: 0 | H38: 0 | I38: 0
C39: Jul-W2 | D39: 40 | E39: 0 | F39: 0 | G39: 0 | H39: 0 | I39: 0
C40: Jul-W3 | D40: 40 | E40: 0 | F40: 0 | G40: 0 | H40: 0 | I40: 0
C41: Jul-W4 | D41: 40 | E41: 0 | F41: 0 | G41: 0 | H41: 0 | I41: 0
C42: Jul-W5 | D42: 40 | E42: 0 | F42: 0 | G42: 0 | H42: 0 | I42: 0
B44: August | C44: Aug-W1 | D44: 40 | E44: 0 | F44: 0 | G44: 0 | H44: 0 | I44: 0
C45: Aug-W2 | D45: 40 | E45: 0 | F45: 0 | G45: 0 | H45: 0 | I45: 0
C46: Aug-W3 | D46: 40 | E46: 0 | F46: 0 | G46: 0 | H46: 0 | I46: 0
C47: Aug-W4 | D47: 40 | E47: 0 | F47: 0 | G47: 0 | H47: 0 | I47: 0
B49: September | C49: Sep-W1 | D49: 40 | E49: 0 | F49: 0 | G49: 0 | H49: 0 | I49: 0
C50: Sep-W2 | D50: 40 | E50: 0 | F50: 0 | G50: 0 | H50: 0 | I50: 0
C51: Sep-W3 | D51: 40 | E51: 0 | F51: 0 | G51: 0 | H51: 0 | I51: 0
C52: Sep-W4 | D52: 40 | E52: 0 | F52: 0 | G52: 0 | H52: 0 | I52: 0
B54: October | C54: Oct-W1 | D54: 40 | E54: 0 | F54: 0 | G54: 0 | H54: 0 | I54: 0
C55: Oct-W2 | D55: 40 | E55: 0 | F55: 0 | G55: 0 | H55: 0 | I55: 0
C56: Oct-W3 | D56: 40 | E56: 0 | F56: 0 | G56: 0 | H56: 0 | I56: 0
C57: Oct-W4 | D57: 40 | E57: 0 | F57: 0 | G57: 0 | H57: 0 | I57: 0
C58: Oct-W5 | D58: 40 | E58: 0 | F58: 0 | G58: 0 | H58: 0 | I58: 0
B60: November | C60: Nov-W1 | D60: 40 | E60: 0 | F60: 0 | G60: 0 | H60: 0 | I60: 0
C61: Nov-W2 | D61: 40 | E61: 0 | F61: 0 | G61: 0 | H61: 0 | I61: 0
C62: Nov-W3 | D62: 40 | E62: 0 | F62: 0 | G62: 0 | H62: 0 | I62: 0
C63: Nov-W4 | D63: 40 | E63: 0 | F63: 0 | G63: 0 | H63: 0 | I63: 0
B65: December | C65: Dec-W1 | D65: 40 | E65: 0 | F65: 0 | G65: 0 | H65: 0 | I65: 0
C66: Dec-W2 | D66: 40 | E66: 0 | F66: 0 | G66: 0 | H66: 0 | I66: 0
C67: Dec-W3 | D67: 40 | E67: 0 | F67: 0 | G67: 0 | H67: 0 | I67: 0
C68: Dec-W4 | D68: 40 | E68: 0 | F68: 0 | G68: 0 | H68: 0 | I68: 0
AT71: Aplikasi
B72: Year | D72: Mbincar Rukun Sembiring | E72: Muhammad Akbar | F72: Mafasyafa Annisa Zukhruff | G72: M. Alvin Fahrian | H72: Gafiliano Gapili | I72: Unedo Ignasius Manalu | AT72: Digisales | AU72: MyCard Mobile | AV72: RM Tools | AW72: XPora | AX72: SOA | AY72: New DPLK | AZ72: Web Keagenan | BA72: API Management | BB72: SISKA | BC72: MyCard Web | BD72: H2H Remmitence | BE72: SMS Menu | BF72: Mobile Banking | BG72: BNI Agen 46 | BH72: Icons
C73: 2024 | D73: 0 | E73: 0 | F73: 0 | G73: 0 | H73: 0 | I73: 0 | AS73: Status
B74: January | C74: Jan-W1 | D74: 0 | E74: 0 | F74: 0 | G74: 0 | H74: 0 | I74: 0 | AS74: Pelaksana
C75: Jan-W2 | D75: 0 | E75: 0 | F75: 0 | G75: 0 | H75: 0 | I75: 0
C76: Jan-W3 | D76: 0 | E76: 0 | F76: 0 | G76: 0 | H76: 0 | I76: 0
C77: Jan-W4 | D77: 0 | E77: 0 | F77: 0 | G77: 0 | H77: 0 | I77: 0
C78: Jan-W5 | D78: 0 | E78: 0 | F78: 0 | G78: 0 | H78: 0 | I78: 0
B80: February | C80: Feb-W1 | D80: 0 | E80: 0 | F80: 0 | G80: 0 | H80: 0 | I80: 0
C81: Feb-W2 | D81: 0 | E81: 0 | F81: 0 | G81: 0 | H81: 0 | I81: 0
C82: Feb-W3 | D82: 0 | E82: 0 | F82: 0 | G82: 0 | H82: 0 | I82: 0
C83: Feb-W4 | D83: 0 | E83: 0 | F83: 0 | G83: 0 | H83: 0 | I83: 0
B85: March | C85: Mar-W1 | D85: 0 | E85: 0 | F85: 0 | G85: 0 | H85: 0 | I85: 0
C86: Mar-W2 | D86: 0 | E86: 0 | F86: 0 | G86: 0 | H86: 0 | I86: 0
C87: Mar-W3 | D87: 0 | E87: 0 | F87: 0 | G87: 0 | H87: 0 | I87: 0
C88: Mar-W4 | D88: 0 | E88: 0 | F88: 0 | G88: 0 | H88: 0 | I88: 0
B90: April | C90: Apr-W1 | D90: 0 | E90: 0 | F90: 0 | G90: 0 | H90: 0 | I90: 0
C91: Apr-W2 | D91: 0 | E91: 0 | F91: 0 | G91: 0 | H91: 0 | I91: 0
C92: Apr-W3 | D92: 0 | E92: 0 | F92: 0 | G92: 0 | H92: 0 | I92: 0
C93: Apr-W4 | D93: 0 | E93: 0 | F93: 0 | G93: 0 | H93: 0 | I93: 0
B95: May | C95: May-W1 | D95: 0 | E95: 0 | F95: 0 | G95: 0 | H95: 0 | I95: 0
C96: May-W2 | D96: 0 | E96: 0 | F96: 0 | G96: 0 | H96: 0 | I96: 0
C97: May-W3 | D97: 0 | E97: 0 | F97: 0 | G97: 0 | H97: 0 | I97: 0
C98: May-W4 | D98: 0 | E98: 0 | F98: 0 | G98: 0 | H98: 0 | I98: 0
C99: May-W5 | D99: 0 | E99: 0 | F99: 0 | G99: 0 | H99: 0 | I99: 0
B101: June | C101: Jun-W1 | D101: 0 | E101: 0 | F101: 0 | G101: 0 | H101: 0 | I101: 0
C102: Jun-W2 | D102: 0 | E102: 0 | F102: 0 | G102: 0 | H102: 0 | I102: 0
C103: Jun-W3 | D103: 0 | E103: 0 | F103: 0 | G103: 0 | H103: 0 | I103: 0
C104: Jun-W4 | D104: 0 | E104: 0 | F104: 0 | G104: 0 | H104: 0 | I104: 0
B106: July | C106: Jul-W1 | D106: 0 | E106: 0 | F106: 0 | G106: 0 | H106: 0 | I106: 0
C107: Jul-W2 | D107: 0 | E107: 0 | F107: 0 | G107: 0 | H107: 0 | I107: 0
C108: Jul-W3 | D108: 0 | E108: 0 | F108: 0 | G108: 0 | H108: 0 | I108: 0
C109: Jul-W4 | D109: 0 | E109: 0 | F109: 0 | G109: 0 | H109: 0 | I109: 0
C110: Jul-W5 | D110: 0 | E110: 0 | F110: 0 | G110: 0 | H110: 0 | I110: 0
B112: August | C112: Aug-W1 | D112: 0 | E112: 0 | F112: 0 | G112: 0 | H112: 0 | I112: 0
C113: Aug-W2 | D113: 0 | E113: 0 | F113: 0 | G113: 0 | H113: 0 | I113: 0
C114: Aug-W3 | D114: 0 | E114: 0 | F114: 0 | G114: 0 | H114: 0 | I114: 0
C115: Aug-W4 | D115: 0 | E115: 0 | F115: 0 | G115: 0 | H115: 0 | I115: 0
B117: September | C117: Sep-W1 | D117: 0 | E117: 0 | F117: 0 | G117: 0 | H117: 0 | I117: 0
C118: Sep-W2 | D118: 0 | E118: 0 | F118: 0 | G118: 0 | H118: 0 | I118: 0
C119: Sep-W3 | D119: 0 | E119: 0 | F119: 0 | G119: 0 | H119: 0 | I119: 0
C120: Sep-W4 | D120: 0 | E120: 0 | F120: 0 | G120: 0 | H120: 0 | I120: 0
B122: October | C122: Oct-W1 | D122: 0 | E122: 0 | F122: 0 | G122: 0 | H122: 0 | I122: 0
C123: Oct-W2 | D123: 0 | E123: 0 | F123: 0 | G123: 0 | H123: 0 | I123: 0
C124: Oct-W3 | D124: 0 | E124: 0 | F124: 0 | G124: 0 | H124: 0 | I124: 0
...

Sheet Daftar Aplikasi BNI
A1: DAFTAR APLIKASI AKTIF BNI
A2: STA - ISA
A4: Application ID | B4: Nama Aplikasi | C4: Description/Definition | D4: Main Building Block | E4: Sub Building Block | F4: Business Owner | G4: System Owner | H4: Team APS | I4: Criticality | J4: Status | K4: Transactional/ Mission Critical Product (1) | L4: Regulatory (BI/ OJK/ SWIFT/MC/ VISA/GPN) (2) | M4: Revenue Loss /Biz Critical (1) | N4: Operational Impact (Bank wide (1)) | O4: Reputation/ Customer facing(1) | P4: Criticality Score
A5: AMOLOM0001 | B5: ADK NET - Elektronik Administrasi Kredit | C5: Aplikasi untuk proses administrasi kredit, terdiri dari: eADK Home, ePK, ePolis, eAkta, eTaksasi, eSettlement, eRekanan, eFilling | D5: Operational Services | E5: Loan Operations | F5: COP | G5: RDL - Retail Credit Operation Delivery | H5: BOA | I5: 3-Moderate | J5: Aktif | K5: 0 | L5: 0 | M5: 1 | N5: 1 | O5: 0 | P5: 2
A6: AMORAC0002 | B6: Ambit Focus - IRRBB (Interest Rate Risk In The Banking Book) | C6: Aplikasi utk perhitungan resiko tingkat suku bunga | D6: Risk & Compliance | E6: Regulatory | F6: TRS | G6: ADV - Wholesale Core Services Department | H6: CBS | I6: 2-High | J6: Aktif | K6: 0 | L6: 2 | M6: 0 | N6: 1 | O6: 0 | P6: 3
A7: AMOSAL0007 | B7: Aplikasi Pengundian | C7: Aplikasi undian untuk event/ program pemasaran BNI | D7: Customer Relationship Management | E7: Marketing | F7: CRP | G7: RDL - Customer Care Channel | H7: BOA | I7: 4-Non Critical | J7: Aktif | K7: 0 | L7: 0 | M7: 0 | N7: 1 | O7: 0 | P7: 1
A8: AMOOES0008 | B8: ASP | C8: Aplikasi Perpajakan | D8: Enterprise Support | E8: Finance & Accounting | F8: WPP/WDC | G8: WDL - Integrated Dashboard & Corporate Portal | H8: ???? | I8: 2-High | J8: Aktif | K8: 0 | L8: 2 | M8: 0 | N8: 1 | O8: 0 | P8: 3
A9: AMOOES0009 | B9: Asset Management | C9: Aplikasi untuk mencatat informasi aset tetap, dengan dilengkapi informasi tambahan : foto/gambar asset, nomor proyek, kode anggaran, geo tagging, legalitas, daftar penghuni Gedung/rumah dinas, asuransi dll | D9: Enterprise Support | E9: Facilities Management | F9: PFA | G9: ADV - Enterprise Services Departement | H9: BOA | I9: 3-Moderate | J9: Aktif | K9: 0 | L9: 0 | M9: 1 | N9: 1 | O9: 0 | P9: 2
A10: AFONFO0011 | B10: Autodebet (baru) | C10: Aplikasi berbasis web application untuk mengatur pembayaran tagihan- tagihan mulai dari tagihan listrik, pascabayar, kartu kredit, BPJS, PDAM, layanan | D10: Products & Services | E10: Payment | F10: RDP/RDC | G10: RDL - Customer Care Channel | H10: CBS | I10: 3-Moderate | J10: Aktif | K10: 0 | L10: 0 | M10: 1 | N10: 0 | O10: 1 | P10: 2
A11: AMORAC0012 | B11: Awareness & Supervision Report (ASR) | C11: Aplikasi Awareness & Supervision Report | D11: Risk & Compliance | E11: Internal Audit & Compliance | F11: IAD | G11: ADV - Enterprise Services Departement | H11: BOA | I11: 4-Non Critical | J11: Aktif | K11: 0 | L11: 0 | M11: 0 | N11: 1 | O11: 0 | P11: 1
A12: AMOCSR0013 | B12: Bancassurance Telesaving | C12: pengembangan berdasarkan aktivitas harian yang dilakukan, antara lain : 1. Rekonsil data Nasabah 2. Pendebetan/pembilingan premi 3. Pengembangan premi asuransi 4. Pembayaran no claim bonus | D12: Operational Services | E12: Reconciliation | F12: WEM | G12: RDL - Retail Sales System | H12: BOA | I12: 3-Moderate | J12: Aktif | K12: 0 | L12: 0 | M12: 1 | N12: 1 | O12: 0 | P12: 2
A13: AMOOES0016 | B13: BARS | C13: Account Registry Custody | D13: Products & Services | E13: Custody | F13: BOP | G13: ADV - Wholesale Core Services Department | H13: BOA | I13: 4-Non Critical | J13: Aktif | K13: 0 | L13: 0 | M13: 0 | N13: 1 | O13: 0 | P13: 1
A14: AMOOES0018 | B14: BB Online | C14: Portal untuk reporting sektor BB | D14: #N/A | E14: #N/A | F14: DMA (Data Management Analytic) | G14: DMA (Data Management Analytic) | H14: ???? | I14: 4-Non Critical | J14: Aktif | K14: 0 | L14: 0 | M14: 0 | N14: 1 | O14: 0 | P14: 1
A15: AMORAC0019 | B15: BCP Monitoring (AML System/Regional Compliance Officer) | C15: Aplikasi Monitoring BCP yang ada di Aplikasi AML System | D15: Risk & Compliance | E15: Anti Money Laundering | F15: CMP | G15: ADV - Enterprise Services Departement | H15: BOA | I15: 2-High | J15: Aktif | K15: 0 | L15: 2 | M15: 0 | N15: 1 | O15: 0 | P15: 3
A16: AMODAP0022 | B16: Big Data | C16: Data storage untuk Analytics dan Customer facing application | D16: Enterprise Information System | E16: Big Data | F16: DMA (Data Management Analytic) | G16: DMA (Data Management Analytic) | H16: IDS | I16: 3-Moderate | J16: Aktif | K16: 0 | L16: 0 | M16: 1 | N16: 1 | O16: 0 | P16: 2
A17: AMOCSR0024 | B17: Billing Payment System (BPS) | C17: Rekonsiliasi Bill Payment | D17: Operational Services | E17: Reconciliation | F17: DGO | G17: WDL | H17: BOA | I17: 2-High | J17: Aktif | K17: 1 | L17: 0 | M17: 1 | N17: 1 | O17: 0 | P17: 3
A18: AMORAC0027 | B18: BNI AML (Anti Money Laundering System) | C18: Aplikasi Anti Money Laundering | D18: Risk & Compliance | E18: Anti Money Laundering | F18: CMP | G18: ADV - Enterprise Services Departement | H18: BOA | I18: 2-High | J18: Aktif | K18: 0 | L18: 2 | M18: 0 | N18: 1 | O18: 0 | P18: 3
A19: AFOAFO0029 | B19: BNI Contact Center | C19: Pusat layanan dan complaint handling bagi Nasabah dan Non Nasabah via BNI Call 1500046 utk mendapatkan informasi, melakukan transaksi, dan memperoleh solusi atas permasalahan layanan perbankan. Dan complaint handling utk internal BNI via IT Helpdesk (021 29946000), SAT (021 29926011), dan HCT (021 29946088). | D19: Channels (Bank Channels) | E19: Virtual | F19: CXC | G19: IFM | H19: BOA | I19: 2-High | J19: Aktif | K19: 0 | L19: 0 | M19: 1 | N19: 1 | O19: 1 | P19: 3
A20: AMORAC0030 | B20: BNI Control Overview (BCO) | C20: Aplikasi untuk kontrol internal - Fase I | D20: Risk & Compliance | E20: Operational Risk | F20: IAD | G20: ADV - Enterprise Services Departement | H20: ???? | I20: 4-Non Critical | J20: Aktif | K20: 0 | L20: 0 | M20: 0 | N20: 1 | O20: 0 | P20: 1
A21: AMOOES0031 | B21: BNI Dashboard | C21: Portal untuk reporting sektor BB | D21: Enterprise Information System | E21: Business Intelligence & Analytics | F21: DMA (Data Management Analytic) | G21: DMA (Data Management Analytic) | H21: BOA | I21: 4-Non Critical | J21: Aktif | K21: 0 | L21: 0 | M21: 0 | N21: 1 | O21: 0 | P21: 1
A22: AFONFO0033 | B22: BNIdirect London (LDN) | C22: Global Transaction Banking (GTB) merupakan layanan transaction banking yang disediakan BNI bagi nasabah non perorangan yang ada di luar negeri, menggunakan aplikasi BNI Direct | D22: Channels (Customer Channels) | E22: Wholesale Customer | F22: WPP/WDC | G22: WDL - BNI Direct KCLN | H22: CBS | I22: 3-Moderate | J22: Aktif | M22: 1 | O22: 1 | P22: 2
A23: AFONFO0034 | B23: BNI Experience | C23: Aplikasi berbasis mobile yang berfungsi untuk memberikan informasi lokasi ATM dan Kantor Cabang BNI terdekat dari lokasi/posisi nasabah. | D23: Enterprise Support | E23: Content & Document Management | F23: MCM | G23: RDL - Retail Mobile App | H23: DCP | I23: 4-Non Critical | J23: Aktif | K23: 0 | L23: 0 | M23: 0 | N23: 0 | O23: 1 | P23: 1
A24: AMORAC0035 | B24: BNI for SLIK | C24: Aplikasi penunjang pelaporan Sistem Layanan Informasi Keuangan | D24: Risk & Compliance | E24: Regulatory | F24: CPM, DMA | G24: DMA (Data Management Analytic) | H24: BOA | I24: 3-Moderate | J24: Aktif | K24: 0 | L24: 0 | M24: 0 | N24: 1 | O24: 1 | P24: 2
A25: AMOOES0036 | B25: BNI Forum | C25: Portal media komunikasi internal berbasi Web Intranet untuk menyampaikan informasi berupa berita, panduan transaksi dan operasional juga sebagai media edukasi dan promosi yang terkoneksi ke iCons (Bancslink) | D25: Enterprise Support | E25: Team Collaboration | F25: - | G25: WDL | H25: BOA | I25: 4-Non Critical | J25: Aktif | K25: 0 | L25: 0 | M25: 0 | N25: 1 | O25: 0 | P25: 1
A26: AMOSAL0038 | B26: BNI Move (Digitalisasi KUR) | C26: Sistem onboarding dan pemrosesan pengajuan kredit secara digital yang terintegrasi dengan verifikator debitur | D26: Customer Relationship Management | E26: Sales | F26: CMR | G26: RDL - Retail Sales System | H26: BOA | I26: 3-Moderate | J26: Aktif | K26: 0 | L26: 0 | M26: 1 | N26: 1 | O26: 0 | P26: 2
A27: AFOAFO0039 | B27: BNI Obranch | C27: Aplikasi Pemantauan O-Branch yang bertujuan untuk meningkatkan jangkauan serta akses layanan perbankan kepada masyarakat khususnya pada daerah blank spot atau aksesbilitas terbatas. | D27: Channels (Bank Channels) | E27: Branch | F27: DNS | G27: ADV - Workflow & Automation Fepartment | H27: BOA | I27: 4-Non Critical | J27: Aktif | K27: 0 | L27: 0 | M27: 0 | N27: 1 | O27: 0 | P27: 1
A28: AMOSAL0040 | B28: BNI Poin Plus | C28: Aplikasi yang akan dipakai untuk program loyalti nasabah BNI berbasis teknologi. | D28: Customer Relationship Management | E28: Customer | F28: CRP | G28: RDL - Monitoring & Notification Service | H28: CBS | I28: 3-Moderate | J28: Aktif | K28: 0 | L28: 0 | M28: 0 | N28: 1 | O28: 1 | P28: 2
A29: AFONFO0041 | B29: BNI Simponi | C29: Aplikasi Mobile & Website yang merupakan layanan online DPLK kepada Nasabah (a.l inquiry saldo, monitoring klaim) dan Calon Nasabah (a.l pendaftaran, simulasi) | D29: Channels (Customer Channels) | E29: Retail Customer | F29: PSF | G29: RDL - Retail Mobile App (Simponi Mobile) & RDL - Internet Banking (Simponi Web) | H29: CBS | I29: 3-Moderate | J29: Aktif | K29: 0 | L29: 0 | M29: 0 | N29: 1 | O29: 1 | P29: 2
A30: AMOOES0042 | B30: Branch Navigation | C30: Tools monitoring kinerja dan aktivitas operasional cabang bagi pimpinan. | D30: Operational Services | E30: Reconciliation | F30: DNS | G30: ADV - Workflow & Automation Fepartment | H30: BOA | I30: 4-Non Critical | J30: Aktif | K30: 0 | L30: 0 | M30: 0 | N30: 1 | O30: 0 | P30: 1
A31: AFONFO0044 | B31: Card Derivative Management (CDMA) | C31: Merupakan aplikasi atau sistem berbasis web service dan mobile sebagai sarana bagi Cabang BNI, Mahasiswa, Universitas/Perguruan Tinggi maupun institusi lainnya dalam menyampaikan permohonan order kartu mahasiswa | D31: Channels (Customer Channels) | E31: Wholesale Customer | F31: BOP | G31: RDL - Retail Credit Operation Delivery | H31: BOA | I31: 3-Moderate | J31: Aktif | K31: 0 | L31: 0 | M31: 1 | N31: 1 | O31: 0 | P31: 2
A32: AMOLOM0046 | B32: Credit Bureau Automation System (CBAS) | C32: Credit Bureau Automation System (CBAS) | D32: Operational Services | E32: Loan Operations | F32: RTC | G32: WDL | H32: BOA | I32: 3-Moderate | J32: Aktif | K32: 0 | L32: 0 | M32: 1 | N32: 1 | O32: 0 | P32: 2
A33: AMORAC0048 | B33: CIMS - Compliance Information Management System | C33: Aplikasi Compliance Monitoring System yg terdiri dari : Gratifikasi Online, CIX, Sertifikasi PP, Review PP, Monitoring Denda, AML Report, Kajian PAB, Tindak Lanjut Peraturan | D33: Risk & Compliance | E33: Internal Audit & Compliance | F33: CMP | G33: ADV - Enterprise Services Departement | H33: IDS | I33: 2-High | J33: Aktif | K33: 0 | L33: 2 | M33: 0 | N33: 1 | O33: 0 | P33: 3
A34: AMOLOM0049 | B34: Collateral Data Management System (CDMS) | C34: Portal informasi data jaminan yang ada di BNI, dengan field tambahan yang harus dilengkapi di masing-masing unit. Data jaminan diperoleh dari ICONS | D34: Operational Services | E34: Loan Operations | F34: - | G34: RDL - Retail Credit Operation Delivery | H34: BOA | I34: 3-Moderate | J34: Aktif | K34: 0 | L34: 0 | M34: 1 | N34: 1 | O34: 0 | P34: 2
... A51: AMOSAL0068 | B51: Digisales | C51: Aplikasi penunjang aktivitas Sales | D51: Customer Relationship Management | E51: Sales | F51: SLN | G51: RDL - Retail Sales System | H51: BOA | I51: 2-High | J51: Aktif | K51: 0 | L51: 0 | M51: 1 | N51: 1 | O51: 1 | P51: 3
A52: AFONFO0069 | B52: Digital Invoice | C52: Aplikasi untuk membuat tagihan (invoice) dengan menggunakan metode transfer VA (Virtual Account) | D52: #N/A | E52: #N/A | F52: RDP/RDC | G52: RDL - Transaction & Services | H52: DCP | I52: 3-Moderate | J52: Aktif | K52: 0 | L52: 0 | M52: 0 | N52: 1 | O52: 1 | P52: 2
A53: AFONFO0070 | B53: Digital Platform (Omni Channel) | C53: Penyediaan BNI Digital Platform mencakup besaran Core Services (peningkatan elastisitas performance dan kapabilitas), Omni Channels (integrated & seamless experiences), dan Digital Core (pelengkap kapabilitas dan meningkatkan agility Core Banking). | D53: Channels (Customer Channels) | E53: Retail Customer | F53: RDP/RDC | G53: RDL - Internet Banking | H53: DCP | I53: 3-Moderate | J53: Aktif | K53: 1 | L53: 0 | M53: 1 | N53: 0 | O53: 0 | P53: 2
A54: AMOLOM0071 | B54: Direktori Debitur Ditolak (3D) | C54: Aplikasi untuk monitoring keputusan pengajuan permohonan kredit oleh debitur | D54: Risk & Compliance | E54: Credit Risk | F54: COP | G54: WDL - Relationship Management System | H54: BOA | I54: 2-High | J54: Aktif | K54: 0 | L54: 0 | M54: 1 | N54: 1 | O54: 1 | P54: 3
A55: AMODAP0072 | B55: DNA | C55: Informasi profil dan transaksi nasabah perorangan (nama aplikasi sebelumnya: Exadia) | D55: Enterprise Information System | E55: Data Models Management | F55: DMA (Data Management Analytic) | G55: DMA (Data Management Analytic) | H55: BOA | I55: 4-Non Critical | J55: Aktif | K55: 0 | L55: 0 | M55: 0 | N55: 1 | O55: 0 | P55: 1
A56: ABOLIB0073 | B56: DPLK Accrual | C56: BNI Simponi (Simpanan Pensiun Bank BNI) merupakan Layanan program pensiun yang diselenggarakan oleh Dana Pensiun Lembaga Keuangan PT. Bank Negara Indonesia (Persero) Tbk (DPLK BNI) sejak tahun 1994 berdasarkan Undang-Undang Nomor 11 Tahun 1992 tentang Dana Pensiun. | D56: Products & Services | E56: Pension Management | F56: PSF | G56: ADV - Wholesale Core Services Department | H56: CBS | I56: 3-Moderate | J56: Aktif | K56: 1 | L56: 0 | M56: 0 | N56: 1 | O56: 0 | P56: 2
A57: ABOLIB0074 | B57: DPLK Smile | C57: Aplikasi dana pensiun lembaga keuangan | D57: Products & Services | E57: Pension Management | F57: PSF | G57: ADV - Wholesale Core Services Department | H57: CBS | I57: 3-Moderate | J57: Aktif | K57: 0 | L57: 0 | M57: 1 | N57: 1 | O57: 0 | P57: 2
A58: AMOLOM0075 | B58: DPMS - Digital Pipeline Management System | C58: Aplikasi berbasis web untuk pre-Screening Digital Segmen Menengah | D58: Customer Relationship Management | E58: Sales | F58: CMB1/CMB2 | G58: ADV - Human Capital Management System | H58: BOA | I58: 3-Moderate | J58: Aktif | K58: 0 | L58: 0 | M58: 1 | N58: 1 | O58: 0 | P58: 2
A59: AMORAC0076 | B59: Early Warning System (EWS) | C59: Aplikasi Early Warning System | D59: Risk & Compliance | E59: Credit Risk | F59: ERM | G59: WDL - Relationship Management System | H59: BOA | I59: 2-High | J59: Aktif | K59: 0 | L59: 0 | M59: 1 | N59: 1 | O59: 1 | P59: 3
A60: AMOOES0077 | B60: e-Arsip | C60: e-Arsip | D60: Enterprise Support | E60: Content & Document Management | F60: PFA | G60: ADV - Workflow & Automation Fepartment | H60: BOA | I60: 4-Non Critical | J60: Aktif | K60: 0 | L60: 0 | M60: 0 | N60: 1 | O60: 0 | P60: 1
A61: AFONFO0078 | B61: BNIdirect Trade | C61: Aplikasi penerbitan, pengecekan, pelaporan garansi bank untuk nasabah. Terdiri dari Web (e-bank Guarantee) & Mobile (Bank Guarantee Mobile Checking). Nama lain: GB Online | D61: Channels (Customer Channels) | E61: Wholesale Customer | F61: WPP/WDC | G61: WDL - Supply Chain Service | H61: CBS | I61: 3-Moderate | J61: Aktif | K61: 0 | L61: 0 | M61: 0 | N61: 1 | O61: 1 | P61: 2
A62: AMOOES0079 | B62: E-Cash Supply | C62: Aplikasi berbasis web untuk mengendalikan permintaan cash suplly ATM/CRM dan untuk menilai kinerja pengelola ATM dalam melakukan manajement pengelolaan Kas ATM | D62: Operational Services | E62: Reconciliation | F62: DGO | G62: ADV - Branch Channel System | H62: BOA | I62: 3-Moderate | J62: Aktif | K62: 0 | L62: 0 | M62: 0 | N62: 1 | O62: 1 | P62: 2
A63: AMODAP0080 | B63: ECM - Enterprise Content Management | C63: Aplikasi untuk mengakomodir pengelolaan konten-konten seperti konten pedoman perusahaan | D63: Enterprise Support | E63: Content & Document Management | F63: PGV | G63: ADV - Workflow & Automation Fepartment | H63: BOA | I63: 3-Moderate | J63: Aktif | K63: 0 | L63: 0 | M63: 1 | N63: 1 | O63: 0 | P63: 2
A64: AFONFO0081 | B64: BNIdirect Receivable Solution | C64: Pengelolaan aktivitas penerimaan dana (collection) | D64: Channels | E64: Open Banking | F64: WPP/WDC | G64: WDL - API Management | H64: CBS | I64: 3-Moderate | J64: Aktif | K64: 0 | L64: 0 | M64: 1 | N64: 0 | O64: 1 | P64: 2
... A70: AFONFO0088 | B70: E-Form Prakerja | C70: Aplikasi untuk membuka rekening tabungan bagi Program Pra Kerja | D70: Channels (Customer Channels) | E70: Retail Customer | F70: CRP | G70: RDL - Customer Care Channel | H70: BOA | I70: 4-Non Critical | J70: Aktif | K70: 0 | L70: 0 | M70: 0 | N70: 0 | O70: 1 | P70: 1
A71: AFONFO0089 | B71: Eform Simpanan KCLN | C71: Aplikasi pengajuan pembukaan rekening KCLN | D71: Channels (Customer Channels) | E71: Wholesale Customer | F71: CRP | G71: RDL - Customer Care Channel | H71: CBS | I71: 3-Moderate | J71: Aktif | K71: #N/A | L71: #N/A | M71: #N/A | N71: #N/A | O71: #N/A | P71: #N/A
A72: AMOOES0090 | B72: Electronic Absensi (E-Absensi) | C72: Aplikasi pencatatan kehadiran | D72: Enterprise Support | E72: Human Resource Management | F72: RDL/WDL | G72: ADV - Enterprise Services Departement | H72: BOA | I72: 4-Non Critical | J72: Aktif | K72: 0 | L72: 0 | M72: 0 | N72: 1 | O72: 0 | P72: 1
A73: AMOOES0091 | B73: ELMS - Enterprise Leads Management System | C73: ELMS diharapkan mampu mengakomodir proses pemenuhan data leads secara end to end bagi DMA dan berbagai Divisi yang menggunakannya. | D73: Customer Relationship Management | E73: Sales | F73: DMA | G73: ADV - Enterprise Content Management | H73: BOA | I73: 3-Moderate | J73: Aktif | K73: 0 | L73: 0 | M73: 1 | N73: 1 | O73: 0 | P73: 2
A74: AMOLOM0092 | B74: eLo - Electronic Loan Origination Produktif | C74: Aplikasi berbasis web untuk Loan Origination untuk pemrosesan permohonan pinjaman produktif dibawah 3M (KUR, KUR TKI, KUR Tani, BWU dan BCM) | D74: Products & Services | E74: Loan | F74: CMR | G74: RDL - Consumer Loan | H74: BOA | I74: 2-High | J74: Aktif | K74: 1 | L74: 0 | M74: 1 | N74: 1 | O74: 0 | P74: 3
A75: AMOLOM0093 | B75: eLog | C75: Aplikasi pengajuan klaim ke asuransi | D75: Channels | E75: Open Banking | F75: SBP | G75: WDL - Consumer Loan | H75: BOA | I75: 4-Non Critical | J75: Aktif | K75: 0 | L75: 0 | M75: 0 | N75: 1 | O75: 0 | P75: 1
A76: AMOLOM0094 | B76: e-Lo Konsumtif - Electronic Loan Origination Konsumtif | C76: Loan Origination System | D76: Products & Services | E76: Loan | F76: RTC | G76: RDL - Consumer Loan | H76: BOA | I76: 2-High | J76: Aktif | K76: 1 | L76: 0 | M76: 1 | N76: 1 | O76: 0 | P76: 3
A77: AMOLOM0095 | B77: e-Lo Subsidi (BP Tapera) | C77: Aplikasi khusus untuk pemenuhan subsidi BP Tapera untuk e-Lo Konsumer | D77: Products & Services | E77: Loan | F77: SLN | G77: RDL - Corporate Transaction & Services | H77: BOA | I77: 2-High | J77: Aktif | K77: 0 | L77: 2 | M77: 0 | N77: 1 | O77: 0 | P77: 3
A78: AMOOES0096 | B78: Engine Notif CC | C78: Notifikasi pelanggan atas penggunakan Kartu Kredit | D78: Customer Relationship Management | E78: Service | F78: CRD | G78: RDL - Monitoring & Notification Service | H78: BOA | I78: 4-Non Critical | J78: Aktif | K78: 0 | L78: 0 | M78: 0 | N78: 1 | O78: 0 | P78: 1
A79: AMOCSR0097 | B79: Enterprise Rekon | C79: Citynet/Rec7. Rekonsiliasi DPT (Dana Pos Terbuka), bill payment, transfer antar bank | D79: Operational Services | E79: Reconciliation | F79: DGO | G79: ADV - Reconciliation System | H79: BOA | I79: 2-High | J79: Aktif | K79: 0 | L79: 0 | M79: 1 | N79: 1 | O79: 1 | P79: 3
A80: AMOOES0098 | B80: E-Office | C80: Aplikasi administrasi persuratan | D80: Enterprise Support | E80: Content & Document Management | F80: STA | G80: ADV - Enterprise Services Departement | H80: BOA | I80: 4-Non Critical | J80: Aktif | K80: 0 | L80: 0 | M80: 0 | N80: 1 | O80: 0 | P80: 1
A81: AMOSAL0099 | B81: e-PAK Lintas Musim (BNI Move Agri) | C81: Aplikasi perangkat analisa kredit yang dipergunakan untuk mengakomodir beberapa kali musim tanam musiman secara sekaligus dalam 1 (satu) perangkat. | D81: Customer Relationship Management | E81: Sales | F81: SBP | G81: RDL - Retail Sales System | H81: BOA | I81: 3-Moderate | J81: Aktif | K81: 0 | L81: 0 | M81: 1 | N81: 1 | O81: 0 | P81: 2
A82: AMOOES0100 | B82: ePolicy | C82: Aplikasi EPOLICY yang dipergunakan oleh user di unit penyalur KUR untuk menginput data pengajuan asuransi kerugian secara online kepada pihak asuradur Tripakarta | D82: Operational Services | E82: Loan Operations | F82: COP | G82: RDL | H82: BOA | I82: 3-Moderate | J82: Aktif | K82: 0 | L82: 0 | M82: 1 | N82: 1 | O82: 0 | P82: 2
A83: AFONFO0102 | B83: E-Procurement | C83: Aplikasi untuk proses pengadaan/procurement | D83: Enterprise Support | E83: Procurement | F83: PFA | G83: ADV - Regulatory Compliance | H83: BOA | I83: 3-Moderate | J83: Aktif | K83: 0 | L83: 0 | M83: 0 | N83: 1 | O83: 1 | P83: 2
A84: ABOLIB0103 | B84: e-Purse | C84: Mengelola pembayaran dengan menggunakan Kartu Uang Elektronik | D84: #N/A | E84: #N/A | F84: RDP/RDC | G84: ADV - Prepaid Card System | H84: CBS | I84: 2-High | J84: Aktif | K84: 1 | L84: 0 | M84: 1 | N84: 0 | O84: 1 | P84: 3
A85: AMOOES0104 | B85: e-Purse Portal | C85: Aplikasi E-Purse Portal merupakan aplikasi non transaksional (dengan cakupan di dalam internal Divisi/Satuan/Unit) perbankan BNI | D85: #N/A | E85: #N/A | F85: RDP/RDC | G85: ADV - Prepaid Card System | H85: BOA | I85: 4-Non Critical | J85: Aktif | K85: 0 | L85: 0 | M85: 0 | N85: 1 | O85: 0 | P85: 1
A86: AMOOES0105 | B86: Ereimbursement | C86: Sistem Reimburse Atensi Divisi Manajemen Wealth | D86: Enterprise Support | E86: Finance & Accounting | F86: CRP | G86: RDL | H86: BOA | I86: 4-Non Critical | J86: Aktif | K86: 0 | L86: 0 | M86: 0 | N86: 1 | O86: 0 | P86: 1
A87: AMOOES0106 | B87: Estatement | C87: Pengembangan Portal dan Dashboard New E-statement | D87: Operational Services | E87: Statement | F87: CRP | G87: RDL - Customer Care Channel | H87: BOA | I87: 4-Non Critical | J87: Aktif | K87: 0 | L87: 0 | M87: 0 | N87: 1 | O87: 0 | P87: 1
A88: AMOOES0108 | B88: Execution Management BNI (4DX) | C88: Execution Management BNI merupakan suatu proses untuk membantu organisasi dalam mengelola perencanaan, pemantauan dan evaluasi proses strategi-strategi yang digunakan untuk melakukan eksekusi suatu pekerjaan dengan menggunakan metode 4DX. | D88: Enterprise Support | E88: Human Resource Management | F88: HCS | G88: ADV - Enterprise Services Departement | H88: BOA | I88: 4-Non Critical | J88: Aktif | K88: 0 | L88: 0 | M88: 0 | N88: 1 | O88: 0 | P88: 1
A89: AMOOES0109 | B89: Finance One (F1) | C89: Aplikasi Reporting General Ledger | D89: Enterprise Support | E89: Finance & Accounting | F89: ACC | G89: ADV - Enterprise Services Departement | H89: CBS | I89: 2-High | J89: Aktif | K89: 0 | L89: 2 | M89: 0 | N89: 1 | O89: 0 | P89: 3
A90: AMOOES0110 | B90: Fraud Detection System | C90: Aplikasi untuk mencegah terjadinya Fraud di BNI | D90: Risk & Compliance | E90: Fraud Management | F90: AFR | G90: ADV - Enterprise Services Departement | H90: BOA | I90: 2-High | J90: Aktif | K90: 1 | L90: 0 | M90: 1 | N90: 1 | O90: 0 | P90: 3
A91: AFONFO0113 | B91: G20 | C91: Aplikasi untuk kegiatan penunjang event G20 terkait pembayaran dan pemesanan | D91: Customer Relationship Management | E91: Marketing | F91: RDP/RDC | G91: RDL - Retail Mobile App | H91: DCP | I91: 4-Non Critical | J91: Aktif | K91: 0 | L91: 0 | M91: 0 | N91: 0 | O91: 1 | P91: 1
A92: AMOOES0124 | B92: Go Trade HO | C92: Aplikasi document management trade | D92: Products & Services | E92: Trade Finance | F92: INT | G92: ADV - Wholesale Core Services Department | H92: CBS | I92: 2-High | J92: Aktif | K92: 1 | L92: 0 | M92: 1 | N92: 1 | O92: 0 | P92: 3
A93: AMODAP0129 | B93: GoVar (HKG) | C93: Aplikasi VAR KCLN | D93: Risk & Compliance | E93: Market Risk | F93: ERM | G93: ADV - KCLN Services | H93: CBS | I93: 2-High | J93: Aktif | L93: 2 | N93: 1 | P93: 3
A94: AMODAP0130 | B94: GoVAR (SNG) | C94: Aplikasi yang dipergunakan dalam pengukuran risiko pasar. | D94: Risk & Compliance | E94: Market Risk | F94: ERM | G94: ADV - KCLN Services | H94: CBS | I94: 2-High | J94: Aktif | L94: 2 | N94: 1 | P94: 3
A95: ABOTRX0132 | B95: GoWealth | C95: Wealth Management | D95: Products & Services | E95: Investment & Wealth Management | F95: WEM | G95: ADV - Wealth Management System | H95: CBS | I95: 2-High | J95: Aktif | K95: 1 | L95: 0 | M95: 1 | N95: 1 | O95: 0 | P95: 3
A96: AMOOES0133 | B96: Human Capital Management System (HCMS) | C96: Administrasi data personel pegawai BNI, sistem penggajian, e-learning | D96: Enterprise Support | E96: Human Resource Management | F96: HCS | G96: ADV - Enterprise Services Departement | H96: BOA | I96: 2-High | J96: Aktif | K96: 1 | L96: 0 | M96: 0 | N96: 1 | O96: 1 | P96: 3
A97: AFOAFO0134 | B97: iBank Remitt | C97: Front end transaksi remitt agent | D97: Channels (Bank Channels) | E97: 3rd Party | F97: INT | G97: WDL - BNI Direct KCLN | H97: DCP | I97: 2-High | J97: Aktif | K97: 1 | L97: 0 | M97: 1 | N97: 0 | O97: 1 | P97: 3
A98: AMOOES0136 | B98: iConverter | C98: Aplikasi untuk mapping data report Cardlink BND370 ke server landing untuk proses pembukuan | D98: Enterprise Support | E98: Finance & Accounting | F98: CPM | G98: ADV - Enterprise Services Departement | H98: CBS | I98: 3-Moderate | J98: Aktif | K98: 1 | L98: 0 | M98: 0 | N98: 1 | O98: 0 | P98: 2
A99: AMORAC0137 | B99: IFRS9 (PSAK71) | C99: Aplikasi laporan keuangan | D99: Enterprise Support | E99: Finance & Accounting | F99: ACC | G99: ADV - Enterprise Services Departement | H99: CBS | I99: 2-High | J99: Aktif | K99: 0 | L99: 2 | M99: 0 | N99: 1 | O99: 0 | P99: 3
A100: AMOOES0138 | B100: IGMS (CRM-TRS) | C100: Aplikasi yang membantu tenaga pemasar dalam melakukan strategi pemasaran kepada customer. | D100: Customer Relationship Management | E100: Marketing | F100: TRS | G100: WDL - Relationship Management System | H100: BOA | I100: 3-Moderate | J100: Aktif | K100: 0 | L100: 0 | M100: 1 | N100: 1 | O100: 0 | P100: 2
A101: AMOOES0139 | B101: Informasi Aset Tanah dan Bangunan | C101: Aplikasi berbasis website dan mobile yang dikembangkan untuk mempermudah tugas dari Divisi PFA untuk melakukan proses update (pengkinian data) maupun proses information retrieval (penelusuran informasi) terhadap aset yang ada. | D101: Enterprise Support | E101: Facilities Management | F101: PFA | G101: ADV - Enterprise Services Departement | H101: BOA | I101: 4-Non Critical | J101: Aktif | K101: 0 | L101: 0 | M101: 0 | N101: 1 | O101: 0 | P101: 1
A102: AMOOES0146 | B102: Integrated Biometric System | C102: Aplikasi yang terhubung dengan E-KTP Reader untuk proses verifikasi biometric (fingerprint) kepada nasabah maupun calon nasabah untuk keperluan transaksi | D102: Customer Relationship Management | E102: Customer | F102: DNS | G102: ADV - Bank Channel System | H102: BOA | I102: 3-Moderate | J102: Aktif | K102: 0 | L102: 0 | M102: 0 | N102: 1 | O102: 1 | P102: 2
A103: AMOLOM0147 | B103: Integrated Decision Automated System (IDEAS) | C103: Aplikasi Integrated Decision Automated System (IDEAS) aplikasi pengolahan credit scorecard model maupun pengaturan kebijakan dan strategis bisnis lainnya dalam segmen konsumer dan ritel. | D103: Risk & Compliance | E103: Credit Risk | F103: ERM | G103: RDL - Retail Scoring Application | H103: BOA | I103: 3-Moderate | J103: Aktif | K103: 0 | L103: 0 | M103: 1 | N103: 1 | O103: 0 | P103: 2
A104: AMOOES0148 | B104: Integrated Human Capital System (IHCS) | C104: HR System (berisi 60 modul komprehensif terintegrasi) | D104: Enterprise Support | E104: Human Resource Management | F104: HCS | G104: ADV - Enterprise Services Departement | H104: BOA | I104: 4-Non Critical | J104: Aktif | K104: 0 | L104: 0 | M104: 0 | N104: 1 | O104: 0 | P104: 1
A105: AFONFO0149 | B105: Internet Banking | C105: Aplikasi Internet Banking | D105: Channels (Customer Channels) | E105: Retail Customer | F105: RDP/RDC | G105: RDL - Internet Banking | H105: DCP | I105: 2-High | J105: Aktif | K105: 1 | L105: 0 | M105: 1 | N105: 0 | O105: 1 | P105: 3
A106: AMOOES0151 | B106: IT Framework | C106: Aplikasi Dokumentasi prosedur di BNI | D106: Enterprise Support | E106: Content & Document Management | F106: STA | G106: WDL | H106: BOA | I106: 4-Non Critical | J106: Aktif | K106: 0 | L106: 0 | M106: 0 | N106: 1 | O106: 0 | P106: 1
... A161: AFONFO0225 | B161: Smart Remitance | C161: Front End aplikasi remittance di koresponden | D161: Channels (Bank Channels) | E161: 3rd Party | F161: INT | G161: ADV | H161: CBS | I161: 2-High | J161: Aktif | K161: 1 | L161: 0 | M161: 1 | N161: 0 | O161: 1 | P161: 3
A162: AFONFO0226 | B162: Smart Remitance (SNG) | C162: Front end aplikasi remittance di KCLN Singapura | D162: Channels (Bank Channels) | E162: 3rd Party | F162: INT | G162: ADV - KCLN Services | H162: CBS | I162: 2-High | J162: Aktif | K162: 1 | M162: 1 | O162: 1 | P162: 3
A163: AMOOES0228 | B163: SMPM - Sistem Monitoring Pemeliharaan Merchant | C163: Aplikasi pemantauan operasional Merchant dari pemasangan sampai pemeliharaan EDC agar dapat dikelola secara akurat, dan SLA yang dijalankan. | D163: Operational Services | E163: Merchant | F163: DGO | G163: ADV - Merchant System | H163: BOA | I163: 4-Non Critical | J163: Aktif | K163: 0 | L163: 0 | M163: 0 | N163: 1 | O163: 0 | P163: 1
A164: AFONFO0229 | B164: SMS Banking | C164: Aplikasi SMS Banking | D164: Channels (Customer Channels) | E164: Retail Customer | F164: RDP/RDC | G164: RDL - Mobile Banking | H164: DCP | I164: 2-High | J164: Aktif | K164: 1 | L164: 0 | M164: 1 | N164: 0 | O164: 1 | P164: 3
A165: AMOMWI0230 | B165: sms token gateway | C165: One Time Password (OTP) yang akan dikirim oleh Bank melalui SMS ke nomor telepon selular sebagai multifactor authentication | D165: Customer Relationship Management | E165: Service | F165: CISO | G165: CISO | H165: DCP | I165: 2-High | J165: Aktif | K165: 1 | L165: 0 | M165: 1 | N165: 0 | O165: 1 | P165: 3
A166: AFONFO0231 | B166: Snap Direct Debit | C166: Aplikasi direct debit yang sudah disesuaikan oleh regulasi BI tentang publik API | D166: Channels | E166: Open Banking | F166: RDP/RDC | G166: RDL - Transaction & Services | H166: DCP | I166: 2-High | J166: Aktif | K166: #N/A | L166: #N/A | M166: #N/A | N166: #N/A | O166: #N/A | P166: #N/A
A167: AMOLOM0235 | B167: Sportif | C167: Aplikasi berbasis web digunakan untuk memberikan keputusan/persetujuan spesial rate produk kredit produktif yang diakses oleh Cabang/Wilayah dan Divisi | D167: Products & Services | E167: Treasury | F167: TRS | G167: ADV - Wholesale Core Services Department | H167: BOA | I167: 4-Non Critical | J167: Aktif | K167: 0 | L167: 0 | M167: 0 | N167: 0 | O167: 1 | P167: 1
A168: AFONFO0243 | B168: Tapcash Go | C168: Aplikasi pengguna Tapcash untuk inquiry, update, dan panduan top up balance | D168: Channels (Customer Channels) | E168: Retail Customer | F168: RDP/RDC | G168: RDL - Retail Mobile App | H168: DCP | I168: 3-Moderate | J168: Aktif | K168: 0 | L168: 0 | M168: 1 | N168: 0 | O168: 1 | P168: 2
A169: AFOAFO0244 | B169: Teras Custody | C169: Aplikasi berbasis web untuk mengendalikan permintaan cash supply ATM/CRM dan untuk menilai kinerja pengelola ATM dalam melakukan manajement pengelolaan Kas ATM | D169: Channels (Customer Channels) | E169: Wholesale Customer | F169: BOP | G169: WDL - Integrated Dashboard & Corporate Portal | H169: CBS | I169: 4-Non Critical | J169: Aktif | K169: 0 | L169: 0 | M169: 0 | N169: 0 | O169: 1 | P169: 1
A170: AMOOES0246 | B170: Token Velis (SDK based) | C170: Sistem kemanan tambahan untuk melindungi akun dan transaksi dengan mengirimkan token autentikasi di beberapa aplikasi | D170: Customer Relationship Management | E170: Service | F170: RDP/RDC | G170: RDL - Transaction & Services | H170: DCP | I170: 2-High | J170: Aktif | K170: 1 | L170: 0 | M170: 1 | N170: 0 | O170: 1 | P170: 3
A171: AFOAFO0250 | B171: Virtual Assistant | C171: BNI Call help center, sebelumnya Cinta (Chatbot) | D171: Channels (Customer Channels) | E171: Retail Customer | F171: CXC | G171: RDL - Customer Care Channel | H171: DCP | I171: 3-Moderate | J171: Aktif | K171: 0 | L171: 0 | M171: 0 | N171: 1 | O171: 1 | P171: 2
A172: AMOOES0251 | B172: Virtual EDC - Electronic Recurring Payment System (ERPS) | C172: Transaction System | D172: Channels (Bank Channels) | E172: Device/Machine | F172: RDP/RDC | G172: ADV - Workflow & Automation Fepartment | H172: BOA | I172: 2-High | J172: Aktif | K172: 1 | L172: 0 | M172: 1 | N172: 1 | O172: 0 | P172: 3
A173: AFOAFO0252 | B173: Walk In Customer (WIC) | C173: Aplikasi pencatatan nasabah WIC (setiap kali nasabah WIC bertransaksi icons akan mengirimkan data realtime ke WIC) | D173: Channels (Bank Channels) | E173: Branch | F173: CMP | G173: ADV - Enterprise Services Departement | H173: IDS | I173: 2-High | J173: Aktif | K173: 0 | L173: 2 | M173: 0 | N173: 1 | O173: 0 | P173: 3
A174: AMORAC0253 | B174: WBS - Whistle Blowing System | C174: Aplikasi pengaduan WBS Tindak Pidana Korupsi (TPK) yang terhubung dengan API Aroma KPK | D174: Risk & Compliance | E174: Internal Audit & Compliance | F174: CMP | G174: ADV - Enterprise Services Departement | H174: ???? | I174: 4-Non Critical | J174: Aktif | K174: 0 | L174: 0 | M174: 0 | N174: 1 | O174: 0 | P174: 1
A175: AFONFO0254 | B175: yap! | C175: Channel transaksi berbasis push payment dengan source of fund kartu debit, kartu kredit, dan uang elektronik | D175: Channels (Customer Channels) | E175: Retail Customer | F175: WPP/WDC | G175: RDL - Retail Mobile App | H175: DCP | I175: 3-Moderate | J175: Aktif | K175: 0 | L175: 0 | M175: 0 | N175: 1 | O175: 1 | P175: 2
A176: AMOOES0255 | B176: DMS - Document Management System | C176: Aplikasi DMS (Document Management System) merupakan aplikasi yang digunakan untuk menyimpan dokumen secara digital dan sebagai pencatatan peminjaman dokumen file asli dan file kerja seperti surat, memo, dll yang nantinya dipinjam oleh pihak internal maupun eksternal BNI | D176: Enterprise Support | E176: Content & Document Management | F176: COP | G176: ADV - Enterprise Content Management | H176: BOA | I176: 3-Moderate | J176: Aktif | K176: 0 | L176: 0 | M176: 1 | N176: 1 | O176: 0 | P176: 2
...

Sheet Automation Monitoring (2)
D1: Last Update 12 Dec 2025 16:25 WIB
B4: Project ID | C4: Application ID | D4: Nama Aplikasi | E4: Estimated / Total TC | F4: Final TC | G4: Done Scripting | I4: Done Running | K4: Timeline Scripting / Regression in Year 2024 | L4: Pdf | M4: Git | N4: Excel | O4: Branch Git | P4: PIC B2B | Q4: PIC FTE | S4: Device | U4: Chart | AL4: Nama Aplikasi | AM4: Estimated / Total TC | AN4: Final TC | AO4: Done Scripting | AQ4: Done Running | AT4: Nama Aplikasi | AU4: Estimated / Total TC | AV4: Final TC | AW4: Done Scripting | AY4: Done Running | BB4: Nama Aplikasi | BC4: Estimated / Total TC | BD4: Final TC | BE4: Done Scripting | BG4: Done Running
G5: TC | H5: Percentage | I5: TC | J5: Percentage | R5: Tools Auto | AO5: TC | AP5: Percentage | AQ5: TC | AR5: Percentage | AW5: TC | AX5: Percentage | AY5: TC | AZ5: Percentage | BE5: TC | BF5: Percentage | BG5: TC | BH5: Percentage
B6: P23055 | C6: ABOAST0135 | D6: Integrated & Centralized Online System (ICONS)-Poseidon | E6: =BC6 -> 1567 | F6: =BD6 -> 1554 | G6: =BE6 -> 1416 | H6: =G6/F6 -> 0.91119691 | I6: =BG6 -> 1416 | J6: =I6/F6 -> 0.91119691 | K6: Jan | M6: https://gitlab-dc.bni.co.id/marchy.tio/icons.git | O6: dev_alternity_merging | R6: UFT​ | AL6: Tiplus UFE | AM6: 299 | AN6: 252 | AO6: 252 | AP6: =AO6/AN6 -> 1 | AQ6: 252 | AR6: =AQ6/AN6 -> 1 | AT6: Ibank Remittance Fase 2 | AU6: 481 | AV6: 457 | AW6: 457 | AX6: =AW6/AV6 -> 1 | AY6: 457 | AZ6: =AY6/AV6 -> 1 | BB6: ICONS Poseidon | BC6: 1567 | BD6: 1554 | BE6: 1416 | BF6: =BE6/BD6 -> 0.91119691 | BG6: 1416 | BH6: =BG6/BD6 -> 0.91119691
B7: A24001 | C7: AFONFO0229 | D7: SMS Banking-Mobile SMS Menu (Android) | E7: 898 | F7: 780 | G7: 772 | H7: =G7/F7 -> 0.98974359 | I7: 772 | J7: =I7/F7 -> 0.98974359 | K7: Oct-Nov | L7: https://bankbnitbk.sharepoint.com/:f:/s/TEST212/EkBwukLUexlCvNbiS9xVLOwBec_4sO1J5vspDybADFMf8g?e=YPNGbQ | M7: https://gitlab-dc.bni.co.id/coe-duplicate/test-automation/katalon-sms-menu-android.git | P7: Alvin | Q7: Mbincar | R7: Katalon​ | AL7: Mobile Agen46 (iOS) | AM7: 712 | AN7: 306 | AO7: 306 | AP7: =AO7/AN7 -> 1 | AQ7: 306 | AR7: =AQ7/AN7 -> 1 | AT7: LMS Sprint 2 | AU7: 16 | AV7: 16 | AW7: 16 | AX7: =AW7/AV7 -> 1 | AY7: 16 | AZ7: =AY7/AV7 -> 1 | BC7: Tiplus UFE | BD7: Digisales APK Generalis dan FTE
B8: A24001 | C8: AFONFO0229 | D8: SMS Banking-Mobile SMS Menu (iOS) | E8: 898 | F8: 780 | G8: 772 | H8: =G8/F8 -> 0.98974359 | I8: 772 | J8: =I8/F8 -> 0.98974359 | K8: Oct-Nov | L8: https://bankbnitbk.sharepoint.com/:f:/s/TEST212/EsU0M1xMRx9PokMQJ0xEYqoBFapR-d2DAIfXACNcm1GImQ?e=Td26y3 | M8: https://gitlab-dc.bni.co.id/coe-duplicate/test-automation/katalon-sms-menu-ios.git | P8: Alvin | Q8: Mbincar | R8: Katalon​ | V8: Stop / Aplikasi sudah tidak dilanjutkan scripting / Service Down | AL8: Mobile Credit Card (Android) | AM8: 75 | AN8: 60 | AO8: 40 | AP8: =AO8/AN8 -> 0.66666667 | AQ8: 40 | AR8: =AQ8/AN8 -> 0.66666667 | AT8: LMS Sprint 3 | AU8: 37 | AV8: 37 | AW8: 37 | AX8: =AW8/AV8 -> 1 | AY8: 37 | AZ8: =AY8/AW8 -> 1 | BC8: BNI Direct Lite | BD8: Digisales Browser Generalis dan FTE
B9: P23094 | C9: AMOOES0309 | D9: DigIMS | E9: 1153 | F9: 1137 | G9: 590 | H9: =G9/F9 -> 0.51890941 | I9: 583 | J9: =I9/F9 -> 0.51275286 | K9: Oct-Nov | L9: https://bankbnitbk.sharepoint.com/:f:/s/TEST212/EmDQeI6wuE9Erk-8RtI6KBsBdR4mp5abwD8GJYpgrlXEyA?e=FOsV8R | M9: https://gitlab-dc.bni.co.id/coe-duplicate/test-automation/katalon-digims.git | P9: Alkha | Q9: Thomas | R9: Katalon​ | U9: 3 hari | V9: 20 tc | W9: 35 hari/ 1 bulan 2 minggu | AL9: Smart VA Portal | AM9: 669 | AN9: 669 | AO9: 157 | AP9: =AO9/AN9 -> 0.23467862 | AQ9: 157 | AR9: =AQ9/AN9 -> 0.23467862
B10: P24091 | C10: AMOSAL0068 | D10: Digisales-Portal (4B) | E10: 60 | F10: 47 | G10: 47 | H10: =G10/F10 -> 1 | I10: 47 | J10: =I10/F10 -> 1 | K10: Oct-Nov | L10: https://bankbnitbk.sharepoint.com/:f:/s/TEST212/EpwQ_mowTgRIsBNX-yqk1SsBydKz148dpodB8gftHbFBaw?e=24HPLd | M10: https://gitlab-dc.bni.co.id/coe-duplicate/test-automation/katalon-digisales-portal.git | R10: Katalon​ | U10: 3 hari | V10: 20 tc | AL10: Cash Management Lite | AM10: 29603 | AN10: 29603 | AO10: 28 | AP10: =AO10/AN10 -> 0.00094585008 | AQ10: 18 | AR10: =AQ10/AN10 -> 0.00060804648
B11: P24091 | C11: AMOSAL0068 | D11: Digisales-Generalis Mobile Browser (4B) | E11: 49 | F11: 47 | G11: 47 | H11: =G11/F11 -> 1 | I11: 47 | J11: =I11/F11 -> 1 | K11: Oct-Nov | L11: https://bankbnitbk.sharepoint.com/:f:/s/TEST212/ElybKHNWvkxDjZztpmaLLWUBbK7bk4AXKBTpXRbjFe-LvQ?e=zw4Rt1 | M11: https://gitlab-dc.bni.co.id/coe-duplicate/test-automation/katalon-digisales-generalis-mobile-browser.git | R11: Katalon​ | U11: 3 hari | V11: 20 tc | AL11: GB Online | AM11: 555 | AN11: 420 | AO11: 0 | AP11: =AO11/AN11 -> 0 | AQ11: 0 | AR11: =AQ11/AN11 -> 0
B12: P24091 | C12: AMOSAL0068 | D12: Digisales-Generalis Mobile APK (4B) | E12: 49 | F12: 47 | G12: 47 | H12: =G12/F12 -> 1 | I12: 47 | J12: =I12/F12 -> 1 | K12: Oct-Nov | L12: https://bankbnitbk.sharepoint.com/:f:/s/TEST212/ElM4wgKu4IpEo1aN26W6_xEBbG1DgM8lJCMGlpG4MzZ0Mg?e=ugHmtA | M12: https://gitlab-dc.bni.co.id/coe-duplicate/test-automation/katalon-digisales-generalis-mobile-apk.git | P12: Unedo | R12: Katalon​ | U12: 13 hari | V12: 20 tc
B13: P24091 | C13: AMOSAL0068 | D13: Digisales-FTE Mobile Browser (4B) | E13: 257 | F13: 257 | G13: 257 | H13: =G13/F13 -> 1 | I13: 249 | J13: =I13/F13 -> 0.9688716 | K13: Nov-Dec | L13: https://bankbnitbk.sharepoint.com/:f:/s/TEST212/Eup95DJS-rFLljrtCvblvq0BOzTzM9ulTTYDds9KCmcULw?e=eHpNAF | M13: https://gitlab-dc.bni.co.id/coe-duplicate/test-automation/katalon-digisales-fte-mobile-browser.git | R13: Katalon​ | U13: 13 hari | V13: 20 tc
B14: P24091 | C14: AMOSAL0068 | D14: Digisales-FTE Mobile APK (4B) | E14: 257 | F14: 257 | G14: 257 | H14: =G14/F14 -> 1 | I14: 254 | J14: =I14/F14 -> 0.98832685 | K14: Nov-Dec | L14: https://bankbnitbk.sharepoint.com/:f:/s/TEST212/EvzzQSkZgHtIo46EbcwpAKUBVU-0l60enMgmHRDjNWBkbQ?e=k341oe | M14: https://gitlab-dc.bni.co.id/coe-duplicate/test-automation/katalon-digisales-fte-mobile-apk.git | P14: Unedo | R14: Katalon​ | U14: 264 hari / 12 bulan | V14: 20 tc | X14: > | Y14: 88 hari / 4 bulan | Z14: asumsi 3 resource
B15: P24019 | C15: AMOCSR0273 | D15: Smart VA-Portal | E15: 669 | F15: 629 | G15: 629 | H15: =G15/F15 -> 1 | I15: 629 | J15: =I15/F15 -> 1 | K15: Dec-Jan | L15: https://bankbnitbk.sharepoint.com/:f:/s/TEST212/EsE_n7BKP49DtZV_DeXugQcBATb7DB5RJ5f3NFGwOL9xhw?e=0F4t6H | M15: https://gitlab.bni.co.id/coe-duplicate/test-automation/katalon-smartva-portal | P15: Alkha, Akbar | Q15: Thomas | R15: Katalon​
B16: P23003 | C16: AMOMWI0004 | D16: API Management-API Gateway | E16: 660 | F16: 658 | G16: 658 | H16: =G16/F16 -> 1 | I16: 658 | J16: =I16/F16 -> 1 | K16: Jan-Oct | L16: https://bankbnitbk.sharepoint.com/:f:/s/TEST212/EkHylvVI_-NHkreXGOrLvDgBuEj6fKPO3ktyu_-69pu-nA?e=EVyUWF | M16: https://gitlab-dc.bni.co.id/coe-duplicate/test-automation/katalon-bni-api-gateway.git | P16: Alkha, Andin | Q16: Thomas | R16: Katalon​
B17: P23008 | C17: AMOOES0180 | D17: CX COMM | E17: 329 | F17: 329 | G17: 68 | H17: =G17/F17 -> 0.20668693 | I17: 68 | J17: =I17/F17 -> 0.20668693 | K17: Mar | L17: https://bankbnitbk.sharepoint.com/:f:/s/TEST212/EpE8MORMBY9LpiVlrjrHBSEBLU5JCww1dRj2oD3BRZaxZQ?e=NNMi3A | M17: https://gitlab-dc.bni.co.id/coe-duplicate/test-automation/katalon-cx-comm/-/tree/CXCOMM_alex?ref_type=heads | Q17: Marin | R17: Katalon​
C18: AMOSAL0068 | D18: Digisales-Portal (5B) | E18: 143 | F18: 137 | G18: 137 | H18: =G18/F18 -> 1 | I18: 137 | J18: =I18/F18 -> 1 | K18: Mar | L18: https://bankbnitbk.sharepoint.com/:f:/s/TEST212/EnO2rxJNuchFpX8AeccRGBwB6E4KL2HD-pnyq4oaIIkGkg?e=1UX2KP | M18: https://gitlab-dc.bni.co.id/coe-duplicate/test-automation/katalon-digisales-portal-5b-fase-1.git | Q18: Mbincar | R18: Katalon​
C19: AMOSAL0068 | D19: Digisales-Generalis Mobile Browser (5B) | E19: 261 | F19: 227 | G19: 227 | H19: =G19/F19 -> 1 | I19: 227 | J19: =I19/F19 -> 1 | K19: Mar | L19: https://bankbnitbk.sharepoint.com/:f:/s/TEST212/EjSIIQ-UTuhOn0w35tAgE7cBCajtwbZD_5MwixPwtcGVRQ?e=cC8p34 | M19: https://gitlab-dc.bni.co.id/coe-duplicate/test-automation/katalon-digisales-generalis-mobile-browser.git | R19: Katalon​
C20: AMOSAL0068 | D20: Digisales-Generalis Mobile APK (5B) | E20: 261 | F20: 232 | G20: 232 | H20: =G20/F20 -> 1 | I20: 232 | J20: =I20/F20 -> 1 | K20: Mar | L20: https://bankbnitbk.sharepoint.com/:f:/s/TEST212/EkBmeaU1c85IiWJlJWAM5M8BLepL1R6T8-lh8zjTEzCT9w?e=lk9hZb | M20: https://gitlab-dc.bni.co.id/coe-duplicate/test-automation/katalon-digisales-generalis-mobile-apk.git | R20: Katalon​ | V20: =E18+E19+E20+#REF! -> #REF! | W20: =F18+F19+F20+#REF! -> #REF!
C21: AMOSAL0068 | D21: Digisales-FTE Mobile Browser (5B) | E21: 311 | F21: 272 | G21: 270 | H21: =G21/F21 -> 0.99264706 | I21: 270 | J21: =I21/F21 -> 0.99264706 | K21: Feb-Mar | L21: https://bankbnitbk.sharepoint.com/:f:/s/TEST212/EiH7yAM0rVtMpHzYtcLAZ2kBfdhgzLfhROjy1G-3181jQA?e=Bii74T | M21: https://gitlab-dc.bni.co.id/coe-duplicate/test-automation/katalon-digisales-fte-mobile-browser.git | R21: Katalon​
C22: AMOSAL0068 | D22: Digisales-FTE Mobile APK (5B) | E22: 311 | F22: 299 | G22: 299 | H22: =G22/$F$22 -> 1 | I22: 299 | J22: =I22/F22 -> 1 | K22: Feb-Mar | L22: https://bankbnitbk.sharepoint.com/:f:/s/TEST212/EhfCiubekcNDqws3_z6Qs88Bf2O8z6EuXbjSBvjxGpV7jg?e=c997oc | M22: https://gitlab-dc.bni.co.id/coe-duplicate/test-automation/katalon-digisales-fte-mobile-apk.git | R22: Katalon​ | W22: 655
C23: AMOSAL0068 | D23: Digisales-Sales Farmer Mobile APK (5B) | E23: 259 | F23: 259 | G23: 259 | H23: =G23/$F$23 -> 1 | I23: 259 | J23: =I23/F23 -> 1 | K23: Feb-Mar | L23: https://bankbnitbk.sharepoint.com/:f:/s/TEST212/EpGn9xd6XFRFhfoQC-4eOp0BnnMmSnqdNgr0oq3Sh9ID_w?e=Tflu2X | M23: https://gitlab-dc.bni.co.id/coe-duplicate/test-automation/katalon-digisales-sales-farmer-mobile-apk.git | R23: Katalon​ | W23: 1952 | Y23: =SUM(W22:W28) -> 4336
C24: AMOSAL0068 | D24: Digisales-Sales Farmer Mobile Browser (5B) | E24: 259 | F24: 259 | G24: 259 | H24: =G24/$F$24 -> 1 | I24: 259 | J24: =I24/F24 -> 1 | K24: Feb-Mar | L24: https://bankbnitbk.sharepoint.com/:f:/s/TEST212/EtfHqjSV8Z9OnE7F75WlelwB3rOpoeV7wr4R181UlVuY8g?e=MXElRq | M24: https://gitlab-dc.bni.co.id/coe-duplicate/test-automation/katalon-digisales-sales-farmer-mobile-browser.git | R24: Katalon​ | W24: 134
C25: AMOSAL0068 | D25: Digisales-Portal (6C) | E25: 145 | F25: 134 | G25: 134 | H25: =G25/$F$25 -> 1 | I25: 134 | J25: =I25/F25 -> 1 | K25: Mei | L25: https://bankbnitbk.sharepoint.com/:f:/s/TEST212/EirMayUabUdEkXIAnu65NS8BqQKjYy3DaHy1YQ6MGjnUig?e=HV7due | M25: https://gitlab-dc.bni.co.id/coe-duplicate/test-automation/katalon-digisales-ms-form-portal-6c.git | R25: Katalon​ | W25: 98
C26: AMOSAL0068 | D26: Digisales-Portal (6D) | E26: 98 | F26: 98 | G26: 98 | H26: =G26/$F$26 -> 1 | I26: 98 | J26: =G26/$F$26 -> 1 | K26: Mei | L26: https://bankbnitbk.sharepoint.com/:f:/s/TEST212/EqKDBXnkBsNKim04CPE06vUBRk2AOSI3jMDlbnJizA-uCA?e=KdvnBn | M26: https://gitlab-dc.bni.co.id/coe-duplicate/test-automation/katalon-digisales-portal-6d/-/tree/dev_gafi?ref_type=heads | R26: Katalon​ | W26: 962
C27: AMOSAL0068 | D27: Digisales-Portal (7A) | E27: 55 | F27: 37 | G27: 37 | H27: =G27/$F$27 -> 1 | I27: 37 | J27: =G27/$F$27 -> 1 | K27: Mei | L27: https://bankbnitbk.sharepoint.com/:f:/s/TEST212/EpOdAPBTKopMnQkLcmeRrysBNqyQHgTEK_twRjTs45MNvw?e=V7pLlp | M27: https://gitlab-dc.bni.co.id/coe-duplicate/test-automation/katalon-digisales-portal-7a-portal.git | R27: Katalon​ | W27: 227
B28: P24015 | C28: ABOAST0111 | D28: BNI Direct FSCM | E28: 125 | F28: 125 | G28: 40 | H28: =G28/$F$28 -> 0.32 | I28: 40 | J28: =G28/$F$28 -> 0.32 | K28: Jun | L28: https://bankbnitbk.sharepoint.com/:f:/s/TEST212/Ev0NXfhPpW5Gkzs-mOGX16gBqNpNkJnpmDZWW9IYNXzwlw?e=F2Gqu2 | M28: https://gitlab-dc.bni.co.id/coe-duplicate/test-automation/bni-direct-fscm.git | R28: Katalon​ | W28: 308
B29: P24015 | C29: AFONFO0032 | D29: BNI Direct Bisnis | E29: =1672+515 -> 2187 | F29: =1653+515 -> 2168 | G29: =1002+644+308+60 -> 2014 | H29: =$G29/$F29 -> 0.92896679 | I29: =1002+644+308+60 -> 2014 | J29: =$I29/$F29 -> 0.92896679 | K29: July - | L29: https://bankbnitbk.sharepoint.com/:f:/s/TEST212/ElnsE9cKzSZNl0y4Yi22lYcB4ut0jQu60FUUFszXnRomWw?e=FBGvLa | M29: https://gitlab-dc.bni.co.id/coe-duplicate/test-automation/katalon-cash-management-lite.git | O29: cmlite_merge | R29: Katalon​
C30: AMOSAL0068 | D30: Digisales-Portal (7B) | E30: 297 | F30: 228 | G30: 227 | H30: =G30/$F$30 -> 0.99561404 | I30: 227 | J30: =G30/$F$30 -> 0.99561404 | K30: Aug | L30: https://bankbnitbk.sharepoint.com/sites/TEST212/Shared%20Documents/Forms/AllItems.aspx?id=%2Fsites%2FTEST212%2FShared%20Documents%2FGeneral%2FScripting%20Report%2FWeb%20Digisales%2FDigisales%20MVP%207B&viewid=5f45ee7e%2D4c73%2D41ad%2Dab32%2Dcf02db1420df&p=true&ga=1 | M30: https://gitlab.bni.co.id/coe-duplicate/test-automation/katalon-digisales-7b | R30: Katalon​
B31: P24015 | C31: AFONFO0032 | D31: BNI Direct Cash | E31: ='Modul BNI Direct 20260626'!C14 -> 12167 | F31: ='Modul BNI Direct 20260626'!D14 -> 7852 | G31: ='Modul BNI Direct 20260626'!E14 -> 5083 | H31: =$G31/$F31 -> 0.64735099 | I31: ='Modul BNI Direct 20260626'!E14 -> 5083 | J31: =$I31/$F31 -> 0.64735099 | K31: Dec-Oct | L31: https://bankbnitbk.sharepoint.com/:f:/s/COETeam/EvEFj3E9tBhCq_RyYCPs4ewBkMey9_B-sLYP-q1rkX5srw?e=0IKCpt | M31: https://gitlab-dc.bni.co.id/coe-duplicate/test-automation/katalon-cash-management-reguler.git
C32: AFONFO0032 | D32: SWMP / Direct Mobile | E32: 102 | F32: 102 | G32: 102 | H32: =$G32/$F32 -> 1 | I32: 102 | J32: =$G32/$F32 -> 1 | K32: Aug | L32: https://bankbnitbk.sharepoint.com/:f:/s/COETeam/EruzHPcPZoZGuA8i1T2C9WMB0fK30ITH24iVi_OLSMsNqA?e=XUTuBI | M32: https://gitlab-dc.bni.co.id/coe-duplicate/katalon-mobile-swmp-android.git
C33: AMOSAL0068 | D33: Digisales-Portal (8A) | E33: 754 | F33: 751 | G33: 751 | H33: =G33/F33 -> 1 | I33: 751 | J33: =G33/$F33 -> 1 | K33: Oct | L33: https://bankbnitbk.sharepoint.com/:f:/s/TEST212/ErRVf1KDEGNLr4zZOhZENJEBLrzdzXGX6LjY_3KXK9aYrA?e=cKfNIX | M33: https://gitlab-dc.bni.co.id/coe-duplicate/test-automation/katalon-digisales-8a | O33: andhini | R33: Katalon​
C34: AMOSAL0068 | D34: Digisales - Mobile Browser (7A) | E34: 499 | F34: 467 | G34: 457 | H34: =G34/F34 -> 0.97858672 | I34: 457 | J34: =G34/F34 -> 0.97858672 | K34: Oct | L34: https://bankbnitbk.sharepoint.com/:f:/s/TEST212/EnV4iKR0IUdBt5LizOfitP4BViEz4hX03Nm3xU-2xP2FNw?e=bxnKXx | M34: https://gitlab-dc.bni.co.id/coe-duplicate/test-automation/katalon-digisales-portal-7a-portal.git | O34: mikhael willy | R34: Katalon​
C35: AMOSAL0068 | D35: Digisales-Mobile APK (7A) | E35: 514 | F35: 468 | G35: 468 | H35: =G35/F35 -> 1 | I35: 468 | J35: =G35/F35 -> 1 | K35: Mei | L35: https://bankbnitbk.sharepoint.com/:f:/s/TEST212/Ev9QjAMCDF5PnE6lSb_cqWEBxNuZJSdHF0QPlrSLXvLIMw?e=Bsc9R0 | M35: https://gitlab-dc.bni.co.id/coe-duplicate/test-automation/katalon-digisales-portal-7a-portal.git | O35: alvin | R35: Katalon​
C36: AMOOES0309 | D36: DigIMS (Latest UI) | E36: 1151 | F36: 1125 | G36: 864 | H36: =G36/F36 -> 0.768 | I36: 864 | J36: =G36/F36 -> 0.768 | K36: Nov 2025 - now | L36: https://bankbnitbk.sharepoint.com/:f:/s/COETeam/IgDXkylQNrYJRqEdNtwzMEmzAe9Aqqc1qNYV3A8qNRTlVBo?e=6VfNeI | M36: https://gitlab-dc.bni.co.id/coe-duplicate/test-automation/katalon-digims.gitt | O36: dev_andhinyaye & dev_ali
C37: AMOSAL0068 | D37: Digisales Mobile APK (8A) | E37: 38 | F37: 38 | G37: 38 | H37: =G37/F37 -> 1 | I37: 38 | J37: =G37/$F37 -> 1 | K37: Oct | L37: https://bankbnitbk.sharepoint.com/:f:/s/TEST212/EqbDzLRXSqBPjveAyS7wVEoBOXJJK6fziPRjsCLc26vn9w?e=dPKnyD
C38: AMOSAL0068 | D38: Digisales Mobile Browser (8A) | E38: 38 | F38: 38 | G38: 38 | H38: =G38/F38 -> 1 | I38: 38 | J38: =G38/$F38 -> 1 | K38: Oct | L38: https://bankbnitbk.sharepoint.com/:f:/s/TEST212/EpX6nYWHcbVMnDs5avPcFJ0BxI7PZPjl8Ve86Mjwl1uT5g?e=7OLKAe | M38: https://gitlab-dc.bni.co.id/coe-duplicate/test-automation/katalon-digisales-8a/-/tree/dev_mobile_browser_mikhael?ref_type=heads
C39: AMOSAL0068 | D39: Digisales Mobile Browser (8b Phase 1) | E39: 1169 | F39: 1074 | G39: 997 | H39: =G39/F39 -> 0.9283054 | I39: 997 | J39: =G39/$F39 -> 0.9283054 | K39: Jan
C40: AMOSAL0068 | D40: Digisales Portal (8b Phase 1) | E40: 1410 | F40: 1410 | G40: 217 | H40: =G40/F40 -> 0.15390071 | I40: 217 | J40: =G40/$F40 -> 0.15390071 | K40: Jan
D41: Dashboard BGN | E41: 448 | F41: 362 | G41: 362 | H41: =G41/F41 -> 1 | I41: 362 | J41: =I41/F41 -> 1 | K41: 46113 | L41: https://bankbnitbk.sharepoint.com/:f:/s/TEST212/IgAmm4yf9iSJTItUHvNqmR9yASSMOa8HHNvDCbKzKykl5nM?e=a88cgn | M41: https://gitlab-dc.bni.co.id/coe-duplicate/test-automation/katalon-bgn | O41: dev
D42: Digisales New Platform (Mobile) | E42: 1123 | F42: 1000 | G42: 135 | H42: =G42/F42 -> 0.135 | I42: 135 | J42: =I42/F42 -> 0.135 | K42: 46174 | L42: https://bankbnitbk.sharepoint.com/sites/TEST212/Shared%20Documents/Forms/AllItems.aspx?id=%2Fsites%2FTEST212%2FShared%20Documents%2FGeneral%2FScripting%20Report%2FDigisales%20New%202026&viewid=5f45ee7e%2D4c73%2D41ad%2Dab32%2Dcf02db1420df&csf=1&CID=8c8ced04%2D801f%2D433a%2Da151%2Da1ae2c72e4a6&FolderCTID=0x01200013C42440C0BE0446A84C2940AA0E2843 | N42: https://bankbnitbk.sharepoint.com/:x:/r/sites/COETeam/_layouts/15/doc2.aspx?sourcedoc=%7Bd174dcaa-5001-4c31-acf0-3b3d63f86bcf%7D&action=edit&wdinitialsession=3f27e13e-2ca5-3928-dbd5-a5c05144c407&wdrldsc=3&wdrldc=1&wdrldr=RefreshingExpiredAccessToken&wdenableroaming=1&wdlcid=en-US&wdorigin=Other&wdredirectionreason=Force_SingleStepBoot
D43: Total | E43: =SUM(E6:E42) -> 30971 | F43: =SUM(F6:F42) -> 25684 | G43: =SUM(G6:G42) -> 19305 | I43: =SUM(I6:I42) -> 19287
G44: =G43/F43 -> 0.75163526 | I44: =I43/F43 -> 0.75093443
D46: 37 aplikasi | E46: =E43-V20 -> #REF! | F46: =F43-W20 -> #REF!
D52: Kelolaan Thomas | V52: Kelolaan Mbincar | AH52: Kelolaan Marin
B78: BNI Direct Cash
C79: Total tc | D79: Script automation
B80: Payroll | C80: 2773 | D80: 751
B81: Bulk Payment | C81: 2152 | D81: 577
B82: Transfer Management | C82: 3122 | D82: 180
B83: Tax Payment | C83: 753 | D83: 502
B84: VA Billing | C84: 979 | D84: 44
B85: Total | C85: =SUM(C80:C84) -> 9779 | D85: =SUM(D80:D84) -> 2054
B87: Api Gateway
C88: Total TC | D88: Scripting Automation
B89: Snap Service | C89: 51 | D89: 46
B90: Token snap v1&v1.0 | C90: 8 | D90: 8
B91: BNIDirect | C91: 37 | D91: 32
B92: OGP H2H | C92: 52 | D92: 47
B93: Snap BI Service (RTL) | C93: 76 | D93: 68
B94: SB Tapcash UBP | C94: 25 | D94: 21
B95: SB | C95: 205 | D95: 205
B96: SB PLN UBP icon+ | C96: 17 | D96: 17
B97: Pulsa Keagenan | C97: 39 | D97: 23
B98: RDN RDL RDF | C98: 150 | D98: 98
B99: Total | C99: 660 | D99: 565

Sheet Daftar Aplikasi BNI (3)
A1: DAFTAR APLIKASI AKTIF BNI
A2: STA - ISA
A4: No | B4: APP ID | C4: New APP ID | D4: Nama Aplikasi | E4: Base Criticality | F4: Transactional/ Mission Critical Product (1) | G4: Regulatory (BI/ OJK/ SWIFT/MC/ VISA/GPN) (2) | H4: Revenue Loss /Biz Critical (1) | I4: Operational Impact (Bank wide (1)/Unit Wide (0.5)) | J4: Reputation/ Customer facing(1) | K4: Criticality Score | L4: Parent App | M4: Parent App Name | N4: Keterangan | O4: Pengganti Sunset | P4: HA (App + DB)? | Q4: Backup/DR | R4: DR Capacity | S4: Monitoring | T4: DC 2
A5: 1 | B5: APP-0001 | C5: AMOLOM0001 | D5: ADK NET - Elektronik Administrasi Kredit | E5: 3-Moderate | H5: 1 | I5: 1 | K5: 2 | N5: 9-Akan sunset
A6: 2 | B6: APP-0002 | C6: AMORAC0002 | D6: Ambit Focus - IRRBB (Interest Rate Risk In The Banking Book) | E6: 2-High | G6: 2 | I6: 1 | K6: 3
A7: 4 | B7: APP-0004 | C7: AMOMWI0004 | D7: API Management | E7: 1-Very Critical | F7: 1 | H7: 1 | I7: 1 | J7: 1 | K7: 4 | Q7: Ya | S7: Ya
A8: 7 | B8: APP-0007 | C8: AMOSAL0007 | D8: Aplikasi Pengundian | E8: 4-Non Critical | I8: 1 | K8: 1
A9: 8 | B9: APP-0008 | C9: AMOOES0008 | D9: ASP | E9: 2-High | G9: 2 | I9: 1 | K9: 3 | N9: 2-Critical B | Q9: New DC
A10: 9 | B10: APP-0009 | C10: AMOOES0009 | D10: Asset Management | E10: 3-Moderate | H10: 1 | I10: 1 | K10: 2
A11: 10 | B11: APP-0010 | C11: AMORAC0010 | D11: Audit Management System (AMS) | E11: 4-Non Critical | I11: 1 | K11: 1
A12: 11 | B12: APP-0011 | C12: AFONFO0011 | D12: Autodebet (baru) | E12: 3-Moderate | H12: 1 | J12: 1 | K12: 2 | Q12: New DC
A13: 12 | B13: APP-0012 | C13: AMORAC0012 | D13: Awareness & Supervision Report (ASR) | E13: 4-Non Critical | I13: 1 | K13: 1
A14: 13 | B14: APP-0013 | C14: AMOCSR0013 | D14: Bancassurance Telesaving | E14: 3-Moderate | H14: 1 | I14: 1 | K14: 2
A15: 14 | B15: APP-0014 | C15: ABOTRX0014 | D15: BaNCS Custody | E15: 1-Very Critical | F15: 1 | G15: 2 | H15: 1 | I15: 1 | K15: 5 | Q15: Ya | S15: Ya
A16: 15 | B16: APP-0015 | C16: AFOAFO0015 | D16: Bancslink | E16: 1-Very Critical | F16: 1 | H16: 1 | I16: 1 | J16: 1 | K16: 4 | Q16: New DC | S16: Ya
A17: 16 | B17: APP-0016 | C17: AMOOES0016 | D17: BaRS | E17: 4-Non Critical | I17: 1 | K17: 1
A18: 17 | B18: APP-0017 | C18: AMOMWI0017 | D18: Base24 | E18: 1-Very Critical | F18: 1 | G18: 2 | H18: 1 | J18: 1 | K18: 5 | Q18: Ya | S18: Ya
A19: 18 | B19: APP-0018 | C19: AMOOES0018 | D19: BB Online | E19: 4-Non Critical | I19: 1 | K19: 1
A20: 19 | B20: APP-0019 | C20: AMORAC0019 | D20: BCP Monitoring (AML System/Regional Compliance Officer) | E20: 2-High | G20: 2 | I20: 1 | K20: 3
A21: 21 | B21: APP-0021 | C21: AMOCSR0021 | D21: BI-FAST - CI Connector | E21: 1-Very Critical | F21: 1 | G21: 2 | H21: 1 | I21: 1 | J21: 1 | K21: 6 | Q21: Ya | S21: Ya
A22: 22 | B22: APP-0022 | C22: AMODAP0022 | D22: Big Data (Cloudera) | E22: 3-Moderate | H22: 1 | I22: 1 | K22: 2
A23: 23 | B23: APP-0023 | C23: AMOCSR0023 | D23: BI-Kliring (TPKServer) | E23: 1-Very Critical | F23: 1 | G23: 2 | H23: 1 | I23: 1 | J23: 1 | K23: 6 | Q23: Ya | S23: Ya
A24: 24 | B24: APP-0024 | C24: AMOCSR0024 | D24: Billing Payment System (BPS) | E24: 2-High | F24: 1 | H24: 1 | I24: 1 | K24: 3 | O24: Digantikan Rekon Citynet (AMOCSR0097) - Tgl Sunset
A25: 25 | B25: APP-0025 | C25: AMOCSR0025 | D25: RTGS | E25: 1-Very Critical | F25: 1 | G25: 2 | H25: 1 | I25: 1 | J25: 1 | K25: 6 | O25: Dipisah RTGS, BI -SSSS, BI-ETP | Q25: Ya | S25: Ya
A26: 27 | B26: APP-0027 | C26: AMORAC0027 | D26: BNI AML (Anti Money Laundering System) | E26: 2-High | G26: 2 | I26: 1 | K26: 3
A27: 28 | B27: APP-0028 | C27: AMORAC0028 | D27: BNI Antasena | E27: 1-Very Critical | G27: 2 | H27: 1 | I27: 1 | K27: 4 | O27: cek apakah masuk LBU juga | Q27: New DC
A28: 29 | B28: APP-0029 | C28: AFOAFO0029 | D28: BNI Contact Center | E28: 2-High | H28: 1 | I28: 1 | J28: 1 | K28: 3 | N28: 2-Critical B | Q28: New DC
A29: 30 | B29: APP-0030 | C29: AMORAC0030 | D29: BNI Control Overview (BCO) | E29: 4-Non Critical | I29: 1 | K29: 1
A30: 31 | B30: APP-0031 | C30: AMOOES0031 | D30: BNI Dashboard | E30: 4-Non Critical | I30: 1 | K30: 1
A31: 32 | B31: APP-0032 | C31: AFONFO0032 | D31: BNI Direct - Cash Management | E31: 1-Very Critical | F31: 1 | H31: 1 | I31: 1 | J31: 1 | K31: 4 | Q31: Ya | S31: Ya
A32: 34 | B32: APP-0034 | C32: AFONFO0034 | D32: BNI Experience | E32: 4-Non Critical | J32: 1 | K32: 1
A33: 35 | B33: APP-0035 | C33: AMORAC0035 | D33: BNI for SLIK | E33: 3-Moderate | I33: 1 | J33: 1 | K33: 2 | N33: 2-Critical A | Q33: New DC
A34: 36 | B34: APP-0036 | C34: AMOOES0036 | D34: BNI Forum | E34: 4-Non Critical | I34: 1 | K34: 1
A35: 38 | B35: APP-0038 | C35: AMOSAL0038 | D35: BNI Move (Digitalisasi KUR) | E35: 3-Moderate | H35: 1 | I35: 1 | K35: 2
A36: 39 | B36: APP-0039 | C36: AFOAFO0039 | D36: BNI Obranch | E36: 4-Non Critical | I36: 1 | K36: 1
A37: 40 | B37: APP-0040 | C37: AMOSAL0040 | D37: BNI Poin Plus | E37: 3-Moderate | I37: 1 | J37: 1 | K37: 2 | N37: 9-Akan sunset
A38: 41 | B38: APP-0041 | C38: AFONFO0041 | D38: BNI Simponi | E38: 3-Moderate | I38: 1 | J38: 1 | K38: 2 | N38: 9-Akan sunset
A39: 42 | B39: APP-0042 | C39: AMOOES0042 | D39: Branch Navigation | E39: 4-Non Critical | I39: 1 | K39: 1
A40: 43 | B40: APP-0043 | C40: AMOOES0043 | D40: B-Secure | E40: 2-High | G40: 2 | I40: 1 | K40: 3 | Q40: Belum Ada | S40: Belum Ada
A41: 44 | B41: APP-0044 | C41: AFONFO0044 | D41: Card Derivative Management (CDMA) | E41: 3-Moderate | H41: 1 | I41: 1 | K41: 2
A42: 45 | B42: APP-0045 | C42: ABOAST0045 | D42: Cardlink | E42: 1-Very Critical | F42: 1 | G42: 2 | H42: 1 | I42: 1 | K42: 5 | Q42: Ya | S42: Ya
A43: 46 | B43: APP-0046 | C43: AMOLOM0046 | D43: Credit Bureau Automation System (CBAS) | E43: 3-Moderate | H43: 1 | I43: 1 | K43: 2
A44: 47 | B44: APP-0048 | C44: AMORAC0048 | D44: CIMS - Compliance Information Management System | E44: 2-High | G44: 2 | I44: 1 | K44: 3
A45: 48 | B45: APP-0049 | C45: AMOLOM0049 | D45: Collateral Data Management System (CDMS) | E45: 3-Moderate | H45: 1 | I45: 1 | K45: 2
A46: 49 | B46: APP-0051 | C46: AMOLOM0051 | D46: Common Collection (CWX) | E46: 3-Moderate | H46: 1 | I46: 1 | K46: 2
A47: 50 | B47: APP-0052 | C47: AMOOES0052 | D47: Content Manager On Demand (CMOD) | E47: 4-Non Critical | I47: 1 | K47: 1 | N47: 9-Akan sunset
A48: 51 | B48: APP-0053 | C48: AMOLOM0053 | D48: Cora - Credit Origination and Risk Assesment | E48: 3-Moderate | H48: 1 | I48: 1 | K48: 2 | N48: 9-Akan sunset
A49: 52 | B49: APP-0054 | C49: AMOOES0054 | D49: Corporate Strategy Management Tools (CSMT) | E49: 4-Non Critical | I49: 1 | K49: 1
A50: 53 | B50: APP-0055 | C50: AFONFO0055 | D50: Corporate Website | E50: 3-Moderate | H50: 0 | I50: 1 | J50: 1 | K50: 2 | Q50: New DC
A51: 54 | B51: APP-0056 | C51: AMOLOM0056 | D51: Credit Card Management System (CCMS) | E51: 2-High | G51: 2 | I51: 1 | K51: 3
A52: 55 | B52: APP-0057 | C52: AMOLOM0057 | D52: Credit Card Origination System (CCOS) | E52: 3-Moderate | H52: 1 | I52: 1 | K52: 2 | N52: 9-Akan sunset
A53: 56 | B53: APP-0058 | C53: AMORAC0058 | D53: Dashboard Hukum (SIPP) | E53: 4-Non Critical | I53: 1 | K53: 1
A54: 57 | B54: APP-0059 | C54: AMOOES0059 | D54: Dashboard Monitoring Agen46 | E54: 4-Non Critical | I54: 1 | K54: 1
A55: 58 | B55: APP-0060 | C55: AMOLOM0060 | D55: Dashboard OPK | E55: 4-Non Critical | I55: 1 | K55: 1
A56: 59 | B56: APP-0061 | C56: AMOOES0061 | D56: Dashboard SMS Banking | E56: 4-Non Critical | I56: 1 | K56: 1
A57: 60 | B57: APP-0062 | C57: AMODAP0062 | D57: Data Warehouse (Teradata) | E57: 1-Very Critical | G57: 2 | H57: 1 | I57: 1 | K57: 4
A58: 61 | B58: APP-0063 | C58: AMOOES0063 | D58: Development Tool Monitoring ATM berbasis Agent (Agent Base) | E58: 4-Non Critical | I58: 1 | K58: 1
A59: 62 | B59: APP-0064 | C59: AFONFO0064 | D59: DigiCS | E59: 3-Moderate | H59: 0 | I59: 1 | J59: 1 | K59: 2
A60: 63 | B60: APP-0065 | C60: AFONFO0065 | D60: Digi Griya | E60: 4-Non Critical | J60: 1 | K60: 1
A61: 64 | B61: APP-0066 | C61: AMOOES0066 | D61: DigiHC | E61: 2-High | F61: 1 | H61: 1 | I61: 1 | K61: 3 | N61: 2-Critical B | Q61: New DC
A62: 65 | B62: APP-0067 | C62: AMOOES0067 | D62: Digipayroll | E62: 2-High | H62: 1 | I62: 1 | J62: 1 | K62: 3 | N62: 2-Critical B | Q62: Belum Ada | S62: Belum Ada
A63: 66 | B63: APP-0068 | C63: AMOSAL0068 | D63: Digisales | E63: 2-High | H63: 1 | I63: 1 | J63: 1 | K63: 3 | N63: 2-Critical B | Q63: New DC
A64: 67 | B64: APP-0069 | C64: AFONFO0069 | D64: Digital Invoice | E64: 3-Moderate | I64: 1 | J64: 1 | K64: 2
A65: 68 | B65: APP-0070 | C65: AFONFO0070 | D65: Digital Platform (Omni Channel) | E65: 3-Moderate | F65: 1 | H65: 1 | K65: 2 | N65: 8-Belum Jalan
A66: 69 | B66: APP-0071 | C66: AMOLOM0071 | D66: Direktori Debitur Ditolak (3D) | E66: 2-High | H66: 1 | I66: 1 | J66: 1 | K66: 3 | N66: 2-Critical B | Q66: New DC
A67: 70 | B67: APP-0072 | C67: AMODAP0072 | D67: DNA (Exadia) | E67: 4-Non Critical | I67: 1 | K67: 1
A68: 71 | B68: APP-0073 | C68: ABOLIB0073 | D68: DPLK Accrual | E68: 3-Moderate | F68: 1 | I68: 1 | K68: 2 | N68: 9-Akan sunset
A69: 72 | B69: APP-0074 | C69: ABOLIB0074 | D69: DPLK Smile | E69: 3-Moderate | H69: 1 | I69: 1 | K69: 2 | N69: 9-Akan sunset
A70: 73 | B70: APP-0075 | C70: AMOLOM0075 | D70: DPMS - Digital Pipeline Management System | E70: 3-Moderate | H70: 1 | I70: 1 | K70: 2
A71: 74 | B71: APP-0076 | C71: AMORAC0076 | D71: Early Warning System (EWS) | E71: 2-High | H71: 1 | I71: 1 | J71: 1 | K71: 3 | N71: 2-Critical B | Q71: New DC
A72: 75 | B72: APP-0077 | C72: AMOOES0077 | D72: e-Arsip | E72: 4-Non Critical | I72: 1 | K72: 1
A73: 76 | B73: APP-0078 | C73: AFONFO0078 | D73: e-Bank Guarantee | E73: 3-Moderate | I73: 1 | J73: 1 | K73: 2
A74: 77 | B74: APP-0079 | C74: AMOOES0079 | D74: E-Cash Supply | E74: 3-Moderate | I74: 1 | J74: 1 | K74: 2
A75: 78 | B75: APP-0080 | C75: AMODAP0080 | D75: ECM - Enterprise Content Management | E75: 3-Moderate | H75: 1 | I75: 1 | K75: 2 | O75: only ePP for now, will be used for others
A76: 79 | B76: APP-0081 | C76: AFONFO0081 | D76: e-Collection | E76: 3-Moderate | H76: 1 | J76: 1 | K76: 2 | N76: 2-Critical B
A77: 80 | B77: APP-0082 | C77: AMOMWI0082 | D77: EDC Android Middleware Platform | E77: 4-Non Critical | K77: 0 | O77: Check GoLive Date | Q77: On Progress | S77: Ya
A78: 81 | B78: APP-0084 | C78: AFONFO0084 | D78: E-Form DAO | E78: 4-Non Critical | J78: 1 | K78: 1 | Q78: New DC
A79: 82 | B79: APP-0085 | C79: AFONFO0085 | D79: E-Form Kartu Kredit | E79: 4-Non Critical | J79: 1 | K79: 1
A80: 83 | B80: APP-0086 | C80: AFONFO0086 | D80: E-Form Payroll | E80: 4-Non Critical | J80: 1 | K80: 1
A81: 84 | B81: APP-0087 | C81: AFONFO0087 | D81: E-Form Pinjaman | E81: 4-Non Critical | J81: 1 | K81: 1
A82: 85 | B82: APP-0088 | C82: AFONFO0088 | D82: E-form Prakerja | E82: 4-Non Critical | J82: 1 | K82: 1
A83: 87 | B83: APP-0090 | C83: AMOOES0090 | D83: Electronic Absensi (E-Absensi) | E83: 4-Non Critical | I83: 1 | K83: 1
A84: 88 | B84: APP-0091 | C84: AMOOES0091 | D84: ELMS - Enterprise Leads Management System | E84: 3-Moderate | H84: 1 | I84: 1 | K84: 2
A85: 89 | B85: APP-0092 | C85: AMOLOM0092 | D85: eLo - Electronic Loan Origination Produktif | E85: 2-High | F85: 1 | H85: 1 | I85: 1 | K85: 3
A86: 90 | B86: APP-0093 | C86: AMOLOM0093 | D86: eLog | E86: 4-Non Critical | I86: 1 | K86: 1
A87: 91 | B87: APP-0094 | C87: AMOLOM0094 | D87: e-Lo Konsumtif - Electronic Loan Origination Konsumtif | E87: 2-High | F87: 1 | H87: 1 | I87: 1 | K87: 3
A88: 92 | B88: APP-0095 | C88: AMOLOM0095 | D88: e-Lo Subsidi (BP Tapera) | E88: 2-High | G88: 2 | I88: 1 | K88: 3
A89: 93 | B89: APP-0096 | C89: AMOOES0096 | D89: Engine Notif CC | E89: 4-Non Critical | I89: 1 | K89: 1
A90: 94 | B90: APP-0097 | C90: AMOCSR0097 | D90: Enterprise Rekon | E90: 2-High | H90: 1 | I90: 1 | J90: 1 | K90: 3 | Q90: Ya | S90: Ya
A91: 95 | B91: APP-0098 | C91: AMOOES0098 | D91: E-Office | E91: 4-Non Critical | I91: 1 | K91: 1
A92: 96 | B92: APP-0099 | C92: AMOSAL0099 | D92: e-PAK Lintas Musim (BNI Move Agri) | E92: 3-Moderate | H92: 1 | I92: 1 | K92: 2
A93: 97 | B93: APP-0100 | C93: AMOOES0100 | D93: ePolicy | E93: 3-Moderate | H93: 1 | I93: 1 | K93: 2
A94: 98 | B94: APP-0102 | C94: AFONFO0102 | D94: E-Procurement | E94: 3-Moderate | I94: 1 | J94: 1 | K94: 2
A95: 99 | B95: APP-0103 | C95: ABOLIB0103 | D95: E-Purse | E95: 2-High | F95: 1 | H95: 1 | J95: 1 | K95: 3
A96: 100 | B96: APP-0104 | C96: AMOOES0104 | D96: e-Purse Portal | E96: 4-Non Critical | I96: 1 | K96: 1
A97: 101 | B97: APP-0105 | C97: AMOOES0105 | D97: Ereimbursement | E97: 4-Non Critical | I97: 1 | K97: 1
A98: 102 | B98: APP-0106 | C98: AMOOES0106 | D98: eStatement | E98: 4-Non Critical | I98: 1 | K98: 1
A99: 103 | B99: APP-0107 | C99: AMOOES0107 | D99: implementasi E-Statement BNI Emerald | E99: 4-Non Critical | I99: 1 | K99: 1
A100: 104 | B100: APP-0108 | C100: AMOOES0108 | D100: Execution Management BNI (4DX) | E100: 4-Non Critical | I100: 1 | K100: 1 | N100: 9-Akan sunset
A101: 105 | B101: APP-0109 | C101: AMOOES0109 | D101: Finance One (F1) | E101: 2-High | G101: 2 | I101: 1 | K101: 3 | Q101: On Progress | S101: Ya
...

Sheet SMS Banking
A1: Scenario ID | B1: TC_ID | C1: Scenario Name | D1: Test Case | E1: Test Case Type | F1: Test Step | G1: List Syntax | H1: Expected Result | I1: Verification | L1: Note | M1: Run Date 1 | N1: Filename 1 | O1: Run Date 2 | P1: Filename 2 | Q1: Status Automation | R1: Note Status Automation | S1: Pass Date (HH Bulan TTTT) (12 Juli 2022) | T1: PIC
I2: SMS | J2: Status Automation Library Dev | K2: Run Status UFT
A3: SCSBK0001 | B3: SBK0001-001 | C3: User melakukan pengecekan Saldo | D3: User melakukan pengecekan informasi saldo | E3: Normal | F3: 1. User menginput sintaks pada aplikasi SMS 2. User mengirimkan SMS ke 3346 3. User menginput PIN Transaksi | G3: SAL | H3: Mendapatkan informasi Saldo sesuai dengan rekening user | I3: Y | J3: DONE | K3: DONE | M3: 44848 | N3: SBK0001-001-User melakukan pengecekan Saldo_Inquiry.doc SBK0001-001-User melakukan pengecekan Saldo_Input PIN.doc | O3: 44959 | P3: SCSBK0001_20230202-164457434.pdf | S3: 44959 | T3: meydita
B4: SBK0001-002 | C4: User melakukan pengecekan Saldo | D4: User salah memasukkan pin transaksi | E4: Abnormal | F4: 1. User menginput sintaks pada aplikasi SMS 2. User mengirimkan SMS ke 3346 3. User menginput PIN transaksi yang salah | G4: SAL | H4: Transaksi gagal dilakukan, muncul pesan "Maaf, Transaksi tidak dapat diproses. Anda melewati batas waktu transaksi. Silakan ulangi transaksi kembali dari awal." | I4: Y | J4: DONE | K4: DONE | M4: 44848 | N4: SBK0001-002-User salah memasukkan pin transaksi_Inquiry.doc SBK0001-002-User salah memasukkan pin transaksi_Input PIN.doc | O4: 44959 | P4: SCSBK0001_20230202-191443642.pdf | S4: 44959 | T4: meydita
A5: SCSBK0002 | B5: SBK0002-001 | C5: User melakukan pengecekan mutasi rekening | D5: User melakukan pemilihan menu informasi mutasi transaksi | E5: Normal | F5: 1. User menginput sintaks pada aplikasi SMS 2. User mengirimkan SMS ke 3346 3. User menginput PIN Transaksi | G5: HST | H5: Mendapatkan informasi Mutasi rekening user | I5: Y | J5: DONE | K5: DONE | M5: 44851 | N5: SBK0002-001-User melakukan pemilihan menu informasi mutasi transaksi.doc | O5: 44959 | P5: SCSBK0002_20230202-111856604.pdf | S5: 44959 | T5: meydita
A6: SCSBK0003 | B6: SBK0003-001 | C6: User melakukan pengecekan Rekening DPLK | D6: User melakukan pengecekan informasi rekening DPLK | E6: Normal | F6: 1. User menginput sintaks pada aplikasi SMS 2. User mengirimkan SMS ke 3346 | G6: INQ DPLK 804193633 | H6: Mendapatkan informasi Rekening DPLK sesuai dengan rekening DPLK yang diinput | I6: Y | J6: DONE | K6: DONE | M6: 44851 | N6: SBK0003-001-User melakukan pengecekan informasi rekening DPLK_Inquiry.doc SBK0003-001-User melakukan pengecekan informasi rekening DPLK_Input PIN.doc | S6: 44851 | T6: meydita
B7: SBK0003-002 | C7: User melakukan pengecekan Rekening DPLK | D7: User Salah menginput rekening DPLK | E7: Abnormal | F7: 1. User menginput sintaks pada aplikasi SMS 2. User mengirimkan SMS ke 3346 | G7: INQ DPLK 804193666 | H7: Transaksi gagal dilakukan, muncul pesan " DPLK02, Rekening belum terdaftar di Channel" | I7: Y | J7: DONE | K7: DONE | M7: 44851 | N7: SBK0003-002-User Salah menginput rekening DPLK_Inquiry.doc SBK0003-002-User Salah menginput rekening DPLK_Input PIN.doc | O7: 44959 | P7: SCSBK0001_20230202-194447018.pdf | S7: 02 Februari 2023 | T7: meydita
B8: SBK0003-003 | C8: User melakukan pengecekan Rekening DPLK | D8: User salah memasukkan pin transaksi | E8: Abnormal | F8: 1. User menginput sintaks pada aplikasi SMS 2. User mengirimkan SMS ke 3346 3. User menginput PIN transaksi yang salah | G8: INQ DPLK 804193633 | H8: Transaksi gagal dilakukan, muncul pesan " Transaksi tidak dapat diproses.PIN yang Anda ketikkan salah.Silakan periksa kembali PIN Anda dan transaksi kembali dari awal" | I8: Y | J8: DONE | K8: DONE | M8: 44851 | N8: SBK0003-003-User salah memasukkan pin transaksi_Inquiry SBK0003-003-User salah memasukkan pin transaksi_Input PIN | O8: 44963 | P8: SCSBK0001_20230206-095637328.pdf | S8: 44963 | T8: meydita
A9: SCSBK0004 | B9: SBK0004-001 | C9: User melakukan pengecekan Daftar Rekening | D9: User melakukan pengecekan Informasi Daftar Rekening | E9: Normal | F9: 1. User menginput sintaks pada aplikasi SMS 2. User Mengirimkan SMS ke 3346 | G9: DAFTAR REKENING | H9: Transaksi berhasil dilakukan, muncul pesan "1000150050 Rp 133.643.447,00 1000158265 Rp 9.000.000,00" | I9: Y | J9: DONE | K9: DONE | M9: 44851 | N9: SBK0004-001-User melakukan pengecekan Informasi Daftar Rekening_Inquiry.doc SBK0004-001-User melakukan pengecekan Informasi Daftar Rekening_Input PIN.doc | O9: 44963 | P9: SCSBK0004_20230206-103017499.pdf | S9: 44963 | T9: meydita
B10: SBK0004-002 | C10: User melakukan pengecekan Daftar Rekening | D10: User salah memasukkan pin transaksi | E10: Abnormal | F10: 1. User menginput sintaks pada aplikasi SMS 2. User mengirimkan SMS ke 3346 3. User menginput PIN transaksi yang salah | G10: DAFTAR REKENING | H10: Transaksi gagal dilakukan, muncul pesan " Transaksi tidak dapat diproses.PIN yang Anda ketikkan salah.Silakan periksa kembali PIN Anda dan transaksi kembali dari awal" | I10: Y | J10: DONE | K10: DONE | M10: 44851 | N10: SBK0004-002-User salah memasukkan pin transaksi_Inquiry.doc SBK0004-002-User salah memasukkan pin transaksi_Input PIN.doc | O10: 44963 | P10: SCSBK0004_20230206-103017499.pdf | S10: 44963 | T10: meydita
A11: SCSBK0005 | B11: SBK0005-001 | C11: User melakukan pengecekan informasi tagihan | D11: User melakukan pengecekan informasi tagihan - Listrik | E11: Normal | F11: 1. User menginput sintaks pada aplikasi SMS 2. User Mengirimkan SMS ke 3346 | G11: TAG PLN 21114567891 | H11: Transaksi berhasil dilakukan, muncul pesan "Tagihan PLN 21114567891/PEL POSTPAID 968894 BL/TH 201506 Rp 300.000 Ref 20221017." | I11: Y | J11: DONE | K11: DONE | M11: 44852 | N11: SBK0005-001-User melakukan pengecekan informasi tagihan - Listrik_Inquiry.doc | O11: 44963 | P11: SCSBK0005_20230206-114546032.pdf | S11: 44963 | T11: meydita
A12: SCSBK0006 | B12: SBK0006-001 | C12: User melakukan pengecekan informasi tagihan | D12: User melakukan pengecekan infromasi tagihan telepon pasca bayar - Kartu Halo | E12: Normal | F12: 1. User menginput sintaks pada aplikasi SMS 2. User Mengirimkan SMS ke 3346 | G12: TAG HALO 123456 | H12: Transaksi berhasil dilakukan, muncul pesan "Tagihan HALO 123456 an sebesar Rp. 525.000]" | I12: Y | J12: DONE | K12: DONE | M12: 44964 | N12: SCSBK0006_20230207-143146361.pdf | S12: 44964 | T12: meydita
B13: SBK0006-002 | C13: User melakukan pengecekan informasi tagihan | D13: User melakukan pengecekan infromasi tagihan telepon pasca bayar - Indosat Ooredoo | E13: Normal | F13: 1. User menginput sintaks pada aplikasi SMS 2. User Mengirimkan SMS ke 3346 | G13: TAG INDOSAT 085656546666 | H13: Transaksi berhasil dilakukan, muncul pesan "Tagihan INDOSAT 085656546666 an SILVIA RAHMAH NUGRAH sebesar Rp. 120.000" | I13: Y | J13: DONE | K13: DONE | M13: 44964 | N13: SCSBK0006_20230207-143146361.pdf | S13: 44964 | T13: meydita
B14: SBK0006-003 | C14: User melakukan pengecekan informasi tagihan | D14: User melakukan pengecekan infromasi tagihan telepon pasca bayar - Telkom Pay | E14: Normal | F14: 1. User menginput sintaks pada aplikasi SMS 2. User Mengirimkan SMS ke 3346 | G14: TAG TELKOM 8114939135 | H14: Transaksi berhasil dilakukan, muncul pesan "Tagihan TELKOM 8114939135 an JOKI VAN NISTELROOY sebesar Rp. 500.000" | I14: Y | J14: DONE | K14: DONE | M14: 44964 | N14: SCSBK0006_20230207-160631928.pdf | S14: 44964 | T14: meydita
B15: SBK0006-004 | C15: User melakukan pengecekan informasi tagihan | D15: User melakukan pengecekan infromasi tagihan telepon pasca bayar - Xplor | E15: Normal | F15: 1. User menginput sintaks pada aplikasi SMS 2. User Mengirimkan SMS ke 3346 | G15: TAG XPLOR 3821230837 | H15: Transaksi berhasil dilakukan, muncul pesan "Tagihan XPLOR 3821230837 an ANDREA BERTOLLACCI sebesar Rp. 150.000" | I15: Y | J15: DONE | K15: DONE | M15: 44964 | N15: SCSBK0006_20230207-160631928.pdf | S15: 44964 | T15: meydita
B16: SBK0006-005 | C16: User melakukan pengecekan informasi tagihan | D16: User melakukan pengecekan infromasi tagihan telepon pasca bayar - 3 (Tri) | E16: Normal | F16: 1. User menginput sintaks pada aplikasi SMS 2. User Mengirimkan SMS ke 3346 | G16: TAG 3 3821230837 | H16: Transaksi berhasil dilakukan, muncul pesan "Tagihan 3 3821230837 an CLOUD SEIFER sebesar Rp. 125.000" | I16: Y | J16: DONE | K16: DONE | M16: 44964 | N16: SCSBK0006_20230207-202034703.pdf | S16: 44964 | T16: meydita
B17: SBK0006-006 | C17: User melakukan pengecekan informasi tagihan | D17: User melakukan pengecekan infromasi tagihan telepon pasca bayar - 3 (smartfren) | E17: Normal | F17: 1. User menginput sintaks pada aplikasi SMS 2. User Mengirimkan SMS ke 3346 | G17: TAG SMARTFREN 3821230837 | H17: Transaksi berhasil ditampilkan dengan isi No. tagihan , Nama dan jumlah tagihan "Tagihan SMARTFREN 3821230837 an SI GANTENG ADI sebesar Rp. 100.000" | I17: Y | J17: DONE | K17: DONE | M17: 44964 | N17: SCSBK0006_20230207-204104861.pdf | S17: 44964 | T17: meydita
A18: SCSBK0007 | B18: SBK0007-001 | C18: User melakukan pengecekan menu informasi tagihan internet/tv berlangganan | D18: User melakukan pengecekan infromasi tagihan telepon pasca bayar - Indovision | E18: Normal | F18: 1. User menginput sintaks pada aplikasi SMS 2. User Mengirimkan SMS ke 3346 | G18: TAG INDOVISION 1234567891234 | H18: Transaksi berhasil dilakukan, muncul pesan "Tagihan INDOVISION No. 1234567891234 an. SARI ANGGRAINI sebesar Rp. 125.000." | I18: Y | J18: DONE | K18: DONE | M18: 44964 | N18: SCSBK0007_20230207-220928202.pdf | S18: 44964 | T18: meydita
B19: SBK0007-002 | C19: User melakukan pengecekan menu informasi tagihan internet/tv berlangganan | D19: User melakukan pengecekan infromasi tagihan telepon pasca bayar - Transvision | E19: Normal | F19: 1. User menginput sintaks pada aplikasi SMS 2. User Mengirimkan SMS ke 3346 | G19: TAG TRANSVISION 1234567891234 | H19: Transaksi berhasil dilakukan, muncul pesan "TRANSVISION 1234567891234 an JOKI VAN NISTELROOY sebesar Rp. 500.000" | I19: Y | J19: DONE | K19: DONE | M19: 44964 | N19: SCSBK0007_20230207-220928202.pdf | S19: 44964 | T19: meydita
B20: SBK0007-003 | C20: User melakukan pengecekan menu informasi tagihan internet/tv berlangganan | D20: User melakukan pengecekan infromasi tagihan telepon pasca bayar - Indihome | E20: Normal | F20: 1. User menginput sintaks pada aplikasi SMS 2. User Mengirimkan SMS ke 3346 | G20: TAG TELKOM 3821230837 | H20: Transaksi berhasil dilakukan, muncul pesan "Tagihan TELKOM 3821230837 an JOKI VAN NISTELROOY sebesar Rp. 500.000." | I20: Y | J20: DONE | K20: DONE | M20: 44964 | N20: SCSBK0007_20230207-220928202.pdf | S20: 44964 | T20: meydita
A21: SCSBK0008 | B21: SBK0008-001 | C21: User melakukan pengecekan menu informasi tagihan kartu kredit BNI | D21: User melakukan pengecekan infromasi tagihan kartu kredit BNI | E21: Normal | F21: 1. User menginput sintaks pada aplikasi SMS 2. User Mengirimkan SMS ke 3346 | G21: TAG BNI 5232390000000012 | H21: Transaksi berhasil dilakukan, muncul pesan "Tagihan BNI No. 5232390000000012 an. BATIK 002 sebesar Rp. -20.054.226. Anda memiliki saldo kredit pada kartu Anda." | I21: Y | J21: DONE | K21: DONE | M21: 44965 | N21: SCSBK0008_20230208-100146292.pdf | S21: 44965 | T21: meydita
A22: SCSBK0009 | B22: SBK0009-001 | C22: User melakukan transfer BNI | D22: User melakukan transfer BNI (Transfer Rekening BNI) | E22: Normal | F22: 1. User menginput sintaks pada aplikasi SMS 2. User Mengirimkan SMS ke 3346 3. User Input PIN Transaksi | G22: TRANSFER 317100155 50000 | H22: Transaksi berhasil dilakukan, muncul pesan "Transfer Rp.10.000 ke 0317100155 an.Bpk FEBY & KOHH & telah berhasil. Reff: 900210." | I22: Y | J22: DONE | K22: DONE | M22: 44965 | N22: SCSBK0009_20230208-144940967.pdf | S22: 44965 | T22: meydita
B23: SBK0009-002 | C23: User melakukan transfer BNI | D23: User melakukan transfer BNI (Transfer Dengan Berita) | E23: Normal | F23: 1. User menginput sintaks pada aplikasi SMS 2. User Mengirimkan SMS ke 3346 3. User Input PIN Transaksi | G23: TRANSFER BERITA 317100155 10000 #HALO# | H23: Transaksi berhasil dilakukan, muncul pesan "Transfer Rp 10.000,- ke 0317100155 an.Bpk FEBY & KOHH Berita: HALO telah berhasil. Reff:900213.." | I23: Y | J23: DONE | K23: DONE | M23: 44965 | N23: SCSBK0009_20230208-144940967.pdf | S23: 44965 | T23: meydita
B24: SBK0009-003 | C24: User melakukan transfer BNI | D24: User melakukan transfer BNI (Transfer Dengan Berita dan Notifikasi) | E24: Normal | F24: 1. User menginput sintaks pada aplikasi SMS 2. User Mengirimkan SMS ke 3346 3. User Input PIN Transaksi | G24: TRANSFER BERITANOTIFIKASI 317100155 10000 #HALO# 081387901103 | H24: Transaksi berhasil dilakukan, muncul pesan "Transfer Rp.10000 ke 0317100155 an.Bpk FEBY & KOHH Berita: HALO telah berhasil. Reff:900216." SMS Notif "Yth Sdr Bpk FEBY &, Anda telah menerima transfer dana melalui BNI SMS Banking, Nama pengirim:Ibu MEYMEY Rp10000. Ref:900216." | I24: Y | J24: DONE | K24: DONE | M24: 44965 | N24: SCSBK0009_20230208-144940967.pdf | S24: 44965 | T24: meydita
B25: SBK0009-004 | C25: User melakukan transfer BNI | D25: User melakukan transfer BNI (Transfer Rekening DPLK/BNI SIMPONI) | E25: Normal | F25: 1. User menginput sintaks pada aplikasi SMS 2. User Mengirimkan SMS ke 3346 3. User Input PIN Transaksi | G25: SETOR DPLK 804193633 100000 | H25: Transaksi berhasil dilakukan, muncul pesan "BNI SMS BANKING:19/10/2022 15:27 Setoran Rp 100.000 ke Rek DPLK 804193633/MEYDITA CAHYANI Berhasil." | I25: Y | J25: DONE | K25: DONE | M25: 44965 | N25: SCSBK0009_20230208-144940967.pdf | S25: 44965 | T25: meydita
B26: SBK0009-005 | C26: User melakukan transfer BNI | D26: User salah input rekening BNI | E26: Abnormal | F26: 1. User menginput sintaks pada aplikasi SMS 2. User Mengirimkan SMS ke 3346 | G26: TRANSFER 317100155 50000 | H26: Transaksi gagal dilakukan, muncul pesan "Transaksi tdk bisa diproses,periksa kembali rekening tujuan transfer Anda. Info:hub BNI Call 1500046 atau Cabang BNI terdekat." | I26: Y | J26: DONE | K26: DONE | M26: 44966 | N26: SCSBK0009_20230209-143101806.pdf | S26: 44966 | T26: meydita
B27: SBK0009-006 | C27: User melakukan transfer BNI | D27: User salah input rekening DPLK/BNI SIMPONI | E27: Abnormal | F27: 1. User menginput sintaks pada aplikasi SMS 2. User Mengirimkan SMS ke 3346 | G27: SETOR DPLK 804193666 100000 | H27: Transaksi gagal dilakukan, muncul pesan "Transaksi tdk bisa diproses,periksa kembali rekening tujuan transfer Anda. Info:hub BNI Call 1500046 atau Cabang BNI terdekat." | I27: Y | J27: DONE | K27: DONE | M27: 44966 | N27: SCSBK0009_20230209-143101806.pdf | S27: 44966 | T27: meydita
B28: SBK0009-007 | C28: User melakukan transfer BNI | D28: User salah input PIN Transaksi | E28: Abnormal | F28: 1. User menginput sintaks pada aplikasi SMS 2. User Mengirimkan SMS ke 3346 3. User Input PIN Transaksi | G28: TRANSFER 317100155 50000 | H28: Transaksi gagal, muncul pesan "Transaksi tidak dapat diproses.PIN yang Anda ketikkan salah.Silakan periksa kembali PIN Anda dan transaksi kembali dari awal" | I28: Y | J28: DONE | K28: DONE | M28: 44967 | N28: SCSBK0009_20230210-091448866.pdf | S28: 44967 | T28: meydita
B29: SBK0009-008 | C29: User melakukan transfer BNI | D29: User melakukan transfer BNI (Transfer Rekening DPLK/BNI SIMPONI) dan User salah input PIN Transaksi | E29: Abnormal | F29: 1. User menginput sintaks pada aplikasi SMS 2. User Mengirimkan SMS ke 3346 3. User Input PIN Transaksi | G29: SETOR DPLK 804193633 100000 | H29: Transaksi gagal, muncul pesan "Transaksi tidak dapat diproses.PIN yang Anda ketikkan salah.Silakan periksa kembali PIN Anda dan transaksi kembali dari awal" | I29: Y | J29: DONE | K29: DONE | M29: 44967 | N29: SCSBK0009_20230210-095443406.pdf | S29: 44967 | T29: meydita
A30: SCSBK0010 | B30: SBK0010-001 | C30: User melakukan transfer antar bank | D30: User melakukan transfer Antar Bank - Realtime Online (BCA) | E30: Normal | F30: 1. User menginput sintaks pada aplikasi SMS 2. User Mengirimkan SMS ke 3346 3. User Input PIN Transaksi | G30: TRANSFER ANTARBANK 014123456 50000 ## | H30: Transaksi berhasil, muncul pesan "Transfer Rp50000 ke BCA 123456/SARI ANGGR telah berhasil. Ref:778716" | I30: Y | J30: DONE | K30: DONE | M30: 44973 | N30: SCSBK0011_20230216-134431560.pdf | S30: 44973 | T30: meydita
B31: SBK0010-002 | C31: User melakukan transfer antar bank | D31: User melakukan transfer Antar Bank - Realtime Online (Bank Mega) | E31: Normal | F31: 1. User menginput sintaks pada aplikasi SMS 2. User Mengirimkan SMS ke 3346 3. User Input PIN Transaksi | G31: TRANSFER ANTARBANK 426123456 50000 ## | H31: Transaksi berhasil, muncul pesan "Transfer Rp50000 ke Bank Mega 123456/SARI ANGGR telah berhasil. Ref:778716" | I31: Y | J31: DONE | K31: DONE | M31: 44973 | N31: SCSBK0010_20230216-163636749.pdf | S31: 44973 | T31: meydita
B32: SBK0010-003 | C32: User melakukan transfer antar bank | D32: User melakukan transfer Antar Bank - Realtime Online (OCBC NISP) | E32: Normal | F32: 1. User menginput sintaks pada aplikasi SMS 2. User Mengirimkan SMS ke 3346 3. User Input PIN Transaksi | G32: TRANSFER ANTARBANK 028123456 50000 ## | H32: Transaksi berhasil, muncul pesan "Transfer Rp50000 ke OCBC NISP 123456/SARI ANGGR telah berhasil. Ref:778716" | I32: Y | J32: DONE | K32: DONE | M32: 44973 | N32: SCSBK0010_20230216-170327125.pdf | S32: 44973 | T32: meydita
B33: SBK0010-004 | C33: User melakukan transfer antar bank | D33: User melakukan transfer Antar Bank - Realtime Online (Bank Maspion) | E33: Normal | F33: 1. User menginput sintaks pada aplikasi SMS 2. User Mengirimkan SMS ke 3346 3. User Input PIN Transaksi | G33: TRANSFER ANTARBANK 157123456 50000 ## | H33: Transaksi berhasil, muncul pesan "Transfer Rp50000 ke Bank Maspion 123456/SARI ANGGR telah berhasil. Ref:778716" | I33: Y | J33: DONE | K33: DONE | M33: 44977 | N33: SCSBK0010_20230220-113824345.pdf | S33: 44977 | T33: meydita
B34: SBK0010-005 | C34: User melakukan transfer antar bank | D34: User melakukan transfer Antar Bank - Realtime Online (CIMB Niaga) | E34: Normal | F34: 1. User menginput sintaks pada aplikasi SMS 2. User Mengirimkan SMS ke 3346 3. User Input PIN Transaksi | G34: TRANSFER ANTARBANK 022123456 50000 ## | H34: Transaksi berhasil, muncul pesan "Transfer Rp50000 ke CIMB Niaga 123456/SARI ANGGR telah berhasil. Ref:778716" | I34: Y | J34: DONE | K34: DONE | M34: 44973 | N34: SCSBK0010_20230216-211336823.pdf | S34: 44973 | T34: meydita
B35: SBK0010-006 | C35: User melakukan transfer antar bank | D35: User melakukan transfer Antar Bank - Realtime Online (BRI) | E35: Normal | F35: 1. User menginput sintaks pada aplikasi SMS 2. User Mengirimkan SMS ke 3346 3. User Input PIN Transaksi | G35: TRANSFER ANTARBANK 002123456 50000 ## | H35: Transaksi berhasil, muncul pesan "Transfer Rp50000 ke BANK BRI 123456/SARI ANGGR telah berhasil. Ref:233022" | I35: Y | J35: DONE | K35: DONE | M35: 45026 | N35: SCSBK0010_20230410-154057418 | S35: 45026 | T35: meydita
B36: SBK0010-007 | C36: User melakukan transfer antar bank | D36: User melakukan transfer Antar Bank - Realtime Online (MANDIRI) | E36: Normal | F36: 1. User menginput sintaks pada aplikasi SMS 2. User Mengirimkan SMS ke 3346 3. User Input PIN Transaksi | G36: TRANSFER ANTARBANK 008123456 50000 ## | H36: Transaksi berhasil dilakukan, muncul pesan "Transfer Rp50000 ke MANDIRI 123456/SARI ANGGR telah berhasil. Ref:294339." | I36: Y | J36: DONE | K36: DONE | M36: 44978 | N36: SCSBK0010_20230221-162917223.pdf | S36: 44978 | T36: Meydita
B37: SBK0010-008 | C37: User melakukan transfer antar bank | D37: User melakukan transfer Antar Bank - Realtime Online (BTN) | E37: Normal | F37: 1. User menginput sintaks pada aplikasi SMS 2. User Mengirimkan SMS ke 3346 3. User Input PIN Transaksi | G37: TRANSFER ANTARBANK 200123456 50000 ## | H37: Transaksi berhasil dilakukan, muncul pesan "Transfer Rp50000 ke BANK BTN 123456/SARI ANGGR telah berhasil. Ref:296693." | I37: Y | J37: DONE | K37: DONE | M37: 44978 | N37: SCSBK0010_20230221-172743267.pdf | S37: 44978 | T37: Meydita
B38: SBK0010-009 | C38: User melakukan transfer antar bank | D38: User melakukan transfer Antar Bank - Realtime Online dengan No HP dan Keterangan | E38: Normal | F38: 1. User menginput sintaks pada aplikasi SMS 2. User Mengirimkan SMS ke 3346 3. User Input PIN Transaksi | G38: TRANSFER ANTARBANK 014123456 50000 6282246954857 #coba-coba# | H38: Transaksi gagal, muncul pesan "Transaksi tidak dapat diproses.PIN yang Anda ketikkan salah.Silakan periksa kembali PIN Anda dan transaksi kembali dari awal" | I38: Y | J38: DONE | K38: DONE | M38: 44978 | N38: SCSBK0010_20230221-173945215.pdf | S38: 44978 | T38: Meydita
B39: SBK0010-010 | C39: User melakukan transfer antar bank | D39: User melakukan transfer Antar Bank - Realtime Online : User salah input PIN Transaksi | E39: Abnormal | F39: 1. User menginput sintaks pada aplikasi SMS 2. User Mengirimkan SMS ke 3346 3. User Input PIN Transaksi | G39: TRANSFER ANTARBANK 014123456 50000 ## | H39: Transaksi gagal, muncul pesan "Transaksi tidak dapat diproses.PIN yang Anda ketikkan salah.Silakan periksa kembali PIN Anda dan transaksi kembali dari awal" | I39: Y | J39: DONE | K39: DONE | M39: 44971 | N39: SCSBK0010_20230214-092245110.pdf | S39: 44971 | T39: Meydita
B40: SBK0010-011 | C40: User melakukan transfer antar bank | D40: User melakukan transfer Antar Bank - Realtime Online : User salah input Rekening | E40: Abnormal | F40: 1. User menginput sintaks pada aplikasi SMS 2. User Mengirimkan SMS ke 3346 | G40: TRANSFER ANTARBANK 011123456 50000 ## | H40: Transaksi gagal dilakukan, muncul pesan "Transaksi tdk bisa diproses,periksa kembali rekening tujuan transfer Anda. Info:hub BNI Call 1500046 atau Cabang BNI terdekat." | I40: Y | J40: DONE | K40: DONE | M40: 44978 | N40: SCSBK0010_20230221-175714247.pdf | S40: 44978 | T40: Meydita
A41: SCSBK0011 | B41: SBK0011-001 | C41: User melakukan Pembayaran Kartu Kredit | D41: User melakukan menu Pembayaran Kartu Kredit (BNI) | E41: Normal | F41: 1. User menginput sintaks pada aplikasi SMS 2. User Mengirimkan SMS ke 3346 3. User Input PIN Transaksi | G41: PAY BNI 5489888809578302 100000 | H41: Transaksi berhasil dilakukan, muncul pesan "BNI SMS BANKING:20/10/2022 14:51 Pembayaran CC BNI No.3563930011130003 an:DEDE PATCH 1 sebesar Rp 100.000,00 telah berhasil dilakukan, reff:245227." | I41: Y | J41: DONE | K41: DONE | M41: 44971 | N41: SCSBK0011_20230214-151532326.pdf | S41: 44971 | T41: Meydita
B42: SBK0011-002 | C42: User melakukan Pembayaran Kartu Kredit | D42: User melakukan menu Pembayaran Kartu Kredit (DBS) | E42: Normal | F42: 1. User menginput sintaks pada aplikasi SMS 2. User Mengirimkan SMS ke 3346 3. User Input PIN Transaksi | G42: PAY DBS 5102176633344886 100000 | H42: Transaksi berhasil dilakukan, muncul pesan "Pembayaran DBS No.5102176633344886 sebesar Rp 100.000,00 telah berhasil dilakukan, reff:245861." | I42: Y | J42: DONE | K42: DONE | M42: 44971 | N42: SCSBK0011_20230214-183128199.pdf | S42: 44971 | T42: Meydita
B43: SBK0011-003 | C43: User melakukan Pembayaran Kartu Kredit | D43: User melakukan menu Pembayaran Kartu Kredit (BRI) | E43: Normal | F43: 1. User menginput sintaks pada aplikasi SMS 2. User Mengirimkan SMS ke 3346 3. User Input PIN Transaksi | G43: PAY BRI 4365028576034567 100000 | H43: Transaksi berhasil dilakukan, muncul pesan "Pembayaran Kartu Kredit BRI No.4365028576034567 sebesar Rp 100.000,00, Adm BNI Rp 7500, Total 107.500,00 berhasil dilakukan, reff:247850" | I43: Y | J43: DONE | K43: DONE | M43: 44971 | N43: SCSBK0011_20230214-184910957.pdf | S43: 44971 | T43: Meydita
B44: SBK0011-004 | C44: User melakukan Pembayaran Kartu Kredit | D44: User melakukan menu Pembayaran Kartu Kredit (Bukopin) | E44: Normal | F44: 1. User menginput sintaks pada aplikasi SMS 2. User Mengirimkan SMS ke 3346 3. User Input PIN Transaksi | G44: PAY BUKOPIN 4211680000000006 100000 | H44: Transaksi berhasil dilakukan, muncul pesan "Pembayaran CC BUKOPIN No.4211680000000006 sebesar Rp 100.000,00 telah berhasil dilakukan, reff:250211." | I44: Y | J44: DONE | K44: DONE | M44: 44971 | N44: SCSBK0011_20230214-195509509.pdf | S44: 44971 | T44: Meydita
B45: SBK0011-005 | C45: User melakukan Pembayaran Kartu Kredit | D45: User melakukan menu Pembayaran Kartu Kredit (Citibank) | E45: Normal | F45: 1. User menginput sintaks pada aplikasi SMS 2. User Mengirimkan SMS ke 3346 3. User Input PIN Transaksi | G45: PAY CITIBANK 4541780000000005 100000 | H45: Transaksi berhasil dilakukan, muncul pesan "Pembayaran CITIBANK CREDIT CARD No.4541780000000005 sebesar Rp 100.000,00 telah berhasil dilakukan, reff:250761." | I45: Y | J45: DONE | K45: DONE
B46: SBK0011-006 | C46: User melakukan Pembayaran Kartu Kredit | D46: User melakukan menu Pembayaran Kartu Kredit (CIMB NIAGA) | E46: Normal | F46: 1. User menginput sintaks pada aplikasi SMS 2. User Mengirimkan SMS ke 3346 3. User Input PIN Transaksi | G46: PAY NIAGA 4599200000000005 100000 | H46: Transaksi berhasil dilakukan, muncul pesan "Pembayaran Niaga No.4599200000000005 sebesar Rp 100.000,00 telah berhasil dilakukan, reff:250802." | I46: Y | J46: DONE | K46: DONE | M46: 44971 | N46: SCSBK0011_20230214-205128378.pdf | S46: 44971 | T46: Meydita
B47: SBK0011-007 | C47: User melakukan Pembayaran Kartu Kredit | D47: User melakukan menu Pembayaran Kartu Kredit (Danamon) | E47: Normal | F47: 1. User menginput sintaks pada aplikasi SMS 2. User Mengirimkan SMS ke 3346 3. User Input PIN Transaksi | G47: PAY DANAMON 2126000000000005 100000 | H47: Transaksi berhasil dilakukan, muncul pesan "Pembayaran Danamon No.2126000000000005 sebesar Rp 100.000,00 telah berhasil dilakukan, reff:250814." | I47: Y | J47: DONE | K47: DONE | M47: 44971 | N47: SCSBK0011_20230214-211449724.pdf | S47: 44971 | T47: Meydita
B48: SBK0011-008 | C48: User melakukan Pembayaran Kartu Kredit | D48: User melakukan menu Pembayaran Kartu Kredit (HSBC) | E48: Normal | F48: 1. User menginput sintaks pada aplikasi SMS 2. User Mengirimkan SMS ke 3346 3. User Input PIN Transaksi | G48: PAY HSBC 4009345924428230 100000 | H48: Transaksi berhasil dilakukan, muncul pesan "Pembayaran HSBC No.4009345924428230 sebesar Rp 100.000,00 telah berhasil dilakukan, reff:250827." | I48: Y | J48: DONE | K48: DONE | M48: 44971 | N48: SCSBK0011_20230214-211449724.pdf | S48: 44971 | T48: Meydita
B49: SBK0011-009 | C49: User melakukan Pembayaran Kartu Kredit | D49: User melakukan menu Pembayaran Kartu Kredit (Bank Mega) | E49: Normal | F49: 1. User menginput sintaks pada aplikasi SMS 2. User Mengirimkan SMS ke 3346 3. User Input PIN Transaksi | G49: PAY MEGA 4201920068593803 100000 | H49: Transaksi berhasil dilakukan, muncul pesan "Pembayaran MEGA No.4201920068593803 sebesar Rp 100.000,00 telah berhasil dilakukan, reff:245861." | I49: Y | J49: DONE | K49: DONE
B50: SBK0011-010 | C50: User melakukan Pembayaran Kartu Kredit | D50: User melakukan menu Pembayaran Kartu Kredit (Bank Permata) | E50: Normal | F50: 1. User menginput sintaks pada aplikasi SMS 2. User Mengirimkan SMS ke 3346 3. User Input PIN Transaksi | G50: PAY PERMATA 4249730000000005 100000 | I50: Y | J50: DONE | K50: DONE
B51: SBK0011-011 | C51: User melakukan Pembayaran Kartu Kredit | D51: User melakukan menu Pembayaran Kartu Kredit (Standard Chartered Bank) | E51: Normal | F51: 1. User menginput sintaks pada aplikasi SMS 2. User Mengirimkan SMS ke 3346 3. User Input PIN Transaksi | G51: PAY SCB 4511960000000009 100000 | H51: Transaksi berhasil dilakukan, muncul pesan "Pembayaran SCB No.4511960000000009 sebesar Rp 100.000,00 telah berhasil dilakukan, reff:250908." | I51: Y | J51: DONE | K51: DONE | M51: 44979 | N51: SCSBK0011_20230222-143146639.pdf | S51: 44979 | T51: Meydita
B52: SBK0011-012 | C52: User melakukan Pembayaran Kartu Kredit | D52: User melakukan menu Pembayaran Kartu Kredit (Panin Bank) | E52: Normal | F52: 1. User menginput sintaks pada aplikasi SMS 2. User Mengirimkan SMS ke 3346 3. User Input PIN Transaksi | G52: PAY PANIN 4377000000000009 100000 | H52: Transaksi berhasil dilakukan, muncul pesan "Pembayaran PANIN No.4377000000000009 sebesar Rp 100.000,00 telah berhasil dilakukan, reff:250908." | I52: Y | J52: DONE | K52: DONE | M52: 44979 | N52: SCSBK0011_20230222-150343283.pdf | S52: 44979 | T52: Meydita
B53: SBK0011-013 | C53: User melakukan Pembayaran Kartu Kredit | D53: User melakukan menu Pembayaran Kartu Kredit (UOB) | E53: Normal | F53: 1. User menginput sintaks pada aplikasi SMS 2. User Mengirimkan SMS ke 3346 3. User Input PIN Transaksi | G53: PAY UOB 4026950000000008 100000 | H53: Transaksi berhasil dilakukan, muncul pesan "Pembayaran UOB No.4026950000000008 sebesar Rp 100.000,00 telah berhasil dilakukan, reff:250931." | I53: Y | J53: DONE | K53: DONE | M53: 44973 | N53: SCSBK0011_20230216-134431560.pdf | S53: 44973 | T53: Meydita
B54: SBK0011-014 | C54: User melakukan Pembayaran Kartu Kredit | D54: User salah input No Kartu Kredit | E54: Abnormal | F54: 1. User menginput sintaks pada aplikasi SMS 2. User Mengirimkan SMS ke 3346 3. User Input PIN Transaksi | G54: PAY BRI 1234520068593803 100000 | H54: Transaksi gagal dilakukan, muncul pesan "Transaksi tidak diproses.Nomor Kartu Kredit/KTA tidak dikenal.Info:hub BNI Call 1500046 atau Cabang BNI terdekat." | I54: Y | J54: DONE | K54: DONE | M54: 44979 | N54: SCSBK0011_20230222-162155909.pdf | S54: 44979 | T54: Meydita
B55: SBK0011-015 | C55: User melakukan Pembayaran Kartu Kredit | D55: User salah input PIN Transaksi | E55: Abnormal | F55: 1. User menginput sintaks pada aplikasi SMS 2. User Mengirimkan SMS ke 3346 3. User Input PIN Transaksi | G55: PAY BNI 3563930011130003 100000 | H55: Transaksi gagal, muncul pesan "Transaksi tidak dapat diproses.PIN yang Anda ketikkan salah.Silakan periksa kembali PIN Anda dan transaksi kembali dari awal" | I55: Y | J55: DONE | K55: DONE | M55: 44979 | N55: SCSBK0011_20230222-162155909.pdf | S55: 44979 | T55: Meydita
A56: SCSBK0012 | B56: SBK0012-001 | C56: User melakukan Pembayaran Telepon Pasca Bayar | D56: User melakukan pembayaran telepon pasca bayar - Kartu Halo | E56: Normal | F56: 1. User menginput sintaks pada aplikasi SMS 2. User Mengirimkan SMS ke 3346 3. User Input PIN Transaksi | G56: PAY HALO 082123083768 | H56: Transaksi berhasil dilakukan, muncul pesan "Pby HALO 082123083768 tag: 525.000 adm: 2500 total: 527500 telah berhasil. Reff: 151301" | I56: Y | J56: DONE | K56: DONE | M56: 44984 | N56: SCSBK0006_20230227-111341249.pdf | S56: 44984 | T56: Meydita
B57: SBK0012-002 | C57: User melakukan Pembayaran Telepon Pasca Bayar | D57: User melakukan pembayaran telepon pasca bayar - Indosat Ooredoo | E57: Normal | F57: 1. User menginput sintaks pada aplikasi SMS 2. User Mengirimkan SMS ke 3346 3. User Input PIN Transaksi | G57: PAY INDOSAT 082123083768 | H57: Transaksi berhasil dilakukan, muncul pesan "Pby INDOSAT 082123083768 tag: 120.000 adm: 2500 total: 122500 telah berhasil. Reff: 151327" | I57: Y | J57: DONE | K57: DONE | M57: 44984 | N57: SCSBK0006_20230227-145044951.pdf | S57: 44984 | T57: Meydita
B58: SBK0012-003 | C58: User melakukan Pembayaran Telepon Pasca Bayar | D58: User melakukan pembayaran telepon pasca bayar - Telkom Pay | E58: Normal | F58: 1. User menginput sintaks pada aplikasi SMS 2. User Mengirimkan SMS ke 3346 3. User Input PIN Transaksi | G58: PAY TELKOM 082123083768 | H58: Transaksi berhasil dilakukan, muncul pesan "Pby TELKOM 082123083768 tag: 500.000 adm: 0 total: 500000 telah berhasil. Reff: 151329" | I58: Y | J58: DONE | K58: DONE | M58: 44984 | N58: SCSBK0006_20230227-151542790.pdf | S58: 44984 | T58: Meydita
B59: SBK0012-004 | C59: User melakukan Pembayaran Telepon Pasca Bayar | D59: User melakukan pembayaran telepon pasca bayar - Xplor | E59: Normal | F59: 1. User menginput sintaks pada aplikasi SMS 2. User Mengirimkan SMS ke 3346 3. User Input PIN Transaksi | G59: PAY XPLOR 082123083768 | H59: Transaksi berhasil dilakukan, muncul pesan "Pby XPLOR 082123083768 tag: 150.000 adm: 2500 total: 152500 telah berhasil. Reff: 156444" | I59: Y | J59: DONE | K59: DONE | M59: 44984 | N59: SCSBK0006_20230227-154950121.pdf | S59: 44984 | T59: Meydita
B60: SBK0012-005 | C60: User melakukan Pembayaran Telepon Pasca Bayar | D60: User melakukan pembayaran telepon pasca bayar - 3 (Tri) | E60: Normal | F60: 1. User menginput sintaks pada aplikasi SMS 2. User Mengirimkan SMS ke 3346 3. User Input PIN Transaksi | G60: PAY 3 082123083768 | H60: Transaksi berhasil dilakukan, muncul pesan "Pby 3 082123083768 tag: 125.000 adm: 2500 total: 127500 telah berhasil. Reff: 152680" | I60: Y | J60: DONE | K60: DONE | M60: 45026 | N60: SCSBK0006_20230410-165339165 | S60: 45026 | T60: Meydita
B61: SBK0012-006 | C61: User melakukan Pembayaran Telepon Pasca Bayar | D61: User melakukan pembayaran telepon pasca bayar - Smartfren | E61: Normal | F61: 1. User menginput sintaks pada aplikasi SMS 2. User Mengirimkan SMS ke 3346 3. User Input PIN Transaksi | G61: PAY SMARTFREN 082123083768 | H61: Transaksi berhasil dilakukan, muncul pesan "Pby SMARTFREN 082123083768 tag: 100.000 adm: 2500 total: 102500 telah berhasil. Reff: 153793" | I61: Y | J61: DONE | K61: DONE | M61: 45026 | N61: SCSBK0006_20230410-171801572 | S61: 45026 | T61: Meydita
B62: SBK0012-007 | C62: User melakukan Pembayaran Telepon Pasca Bayar | D62: User salah input No HP | E62: Abnormal | F62: 1. User menginput sintaks pada aplikasi SMS 2. User Mengirimkan SMS ke 3346 | G62: PAY HALO 08212308376 | H62: Transaksi gagal dilakukan, muncul pesan "Transaksi tdk dpt diproses. Nomor HP Anda:08212308376 belum terdaftar BNI SMS Banking. Silahkan kunjungi Cabang BNI Terdekat" | I62: Y | J62: DONE | K62: DONE
B63: SBK0012-008 | C63: User melakukan Pembayaran Telepon Pasca Bayar | D63: User salah input PIN Transaksi | E63: Abnormal | F63: 1. User menginput sintaks pada aplikasi SMS 2. User Mengirimkan SMS ke 3346 3. User Input PIN Transaksi | G63: PAY HALO 08212308376 | H63: Transaksi gagal, muncul pesan "Transaksi tidak dapat diproses.PIN yang Anda ketikkan salah.Silakan periksa kembali PIN Anda dan transaksi kembali dari awal" | I63: Y | J63: DONE | K63: DONE
A64: SCSBK0013 | B64: SBK0013-001 | C64: User melakukan Pembayaran Listrik | D64: User melakukan Pembayaran Listrik - Tagihan Listrik PLN | E64: Normal | F64: 1. User menginput sintaks pada aplikasi SMS 2. User Mengirimkan SMS ke 3346 3. User Input PIN Transaksi | G64: PAY PLN 150000000014 | H64: Transaksi berhasil dilakukan, muncul pesan "21/10/22 14:11 100914V0009683942017 150000000014 PEL POSTPAID 968894 R1/1300VA Bln JUN15-AGU15 Std 00000100-00000100 Rp 300000 Adm 9000 SUKSES" | I64: Y | J64: DONE | K64: DONE | M64: 44984 | N64: SCSBK0013_20230227-201059909.pdf | S64: 44984 | T64: Meydita
B65: SBK0013-002 | C65: User melakukan Pembayaran Listrik | D65: User melakukan Pembayaran Listrik - TNon Tagihan Listrik | E65: Normal | F65: 1. User menginput sintaks pada aplikasi SMS 2. User Mengirimkan SMS ke 3346 3. User Input PIN Transaksi | G65: PAY PLNNONTAGLIS 01070123 | H65: Transaksi berhasil dilakukan, muncul pesan "21/10/22 14:15 NOMOR RECEIPT4567890 PERUBAHAN DAYA1234567890A 150000000014 08DES11 JACKY CHAN123456789012345 537123456789 Rp 250.000,00 Adm 3000 SUKSES" | I65: Y | J65: DONE | K65: DONE | M65: 45058 | N65: SCSBK0013_20230512-100846362 | S65: 45056 | T65: Meydita
B66: SBK0013-003 | C66: User melakukan Pembayaran Listrik | D66: User salah input PIN Transaksi | E66: Abnormal | F66: 1. User menginput sintaks pada aplikasi SMS 2. User Mengirimkan SMS ke 3346 3. User Input PIN Transaksi | G66: PAY PLN 150000000014 | H66: Transaksi gagal, muncul pesan "Transaksi tidak dapat diproses.PIN yang Anda ketikkan salah.Silakan periksa kembali PIN Anda dan transaksi kembali dari awal" | I66: Y | J66: DONE | K66: DONE | M66: 44984 | N66: SCSBK0013_20230227-201059909.pdf | S66: 44984 | T66: Meydita
A67: SCSBK0014 | B67: SBK0014-001 | C67: User melakukan Pembayaran BPJS | D67: User melakukan pembayaran BPJS Kesehatan | E67: Normal | F67: 1. User menginput sintaks pada aplikasi SMS 2. User Mengirimkan SMS ke 3346 3. User Input PIN Transaksi | G67: PAY BPJSKES 8888801738035562 4 | H67: Transaksi berhasil dilakukan, muncul pesan "Pby BPJS KES 8888801738035562 IDTrx:8D1EBCBD497BAAB0 PADLIAL MUBA utk 4bln Rp 25.500 adm Rp0 Jml:1 Sukses.Ref:023464" | I67: Y | J67: DONE | K67: DONE | M67: 44985 | N67: SCSBK0014_20230228-113047776.pdf | S67: 44985 | T67: Meydita
B68: SBK0014-002 | C68: User melakukan Pembayaran BPJS | D68: User melakukan pembayaran BPJS Ketenagakerjaan (PU) | E68: Normal | F68: 1. User menginput sintaks pada aplikasi SMS 2. User Mengirimkan SMS ke 3346 3. User Input PIN Transaksi | G68: PAY BPJSTK PU 140520210010 1 | H68: Transaksi berhasil dilakukan, muncul pesan "Pby BPJSTK PU 140520210010 SUMITOMO HEAVY NPP:JJ0P6895 Bulan:12/2021 Total:Rp1.800.000,00 Berhasil.Ref:252147" | I68: Y | J68: DONE | K68: DONE | M68: 44985 | N68: SCSBK0014_20230228-143509733.pdf | S68: 44985 | T68: Meydita
B69: SBK0014-003 | C69: User melakukan Pembayaran BPJS | D69: User melakukan pembayaran BPJS Ketenagakerjaan (BPU) | E69: Normal | F69: 1. User menginput sintaks pada aplikasi SMS 2. User Mengirimkan SMS ke 3346 3. User Input PIN Transaksi | G69: PAY BPJSTK BPU 3174042905850005 2 | H69: Transaksi berhasil dilakukan, muncul pesan "Pby BPJSTK BPU 3174042905850005 TEGUH PRASETYO KodeIuran:900000054765 2 bulan Total: Rp 1.500.000 Berhasil. Ref:151313" | I69: Y | J69: DONE | K69: DONE | M69: 45000 | N69: SCSBK0014_20230315-133806775.pdf | S69: 45000 | T69: Meydita
B70: SBK0014-004 | C70: User melakukan Pembayaran BPJS | D70: User melakukan pembayaran BPJS Ketenagakerjaan (PMI) | E70: Normal | F70: 1. User menginput sintaks pada aplikasi SMS 2. User Mengirimkan SMS ke 3346 3. User Input PIN Transaksi | G70: PAY BPJSTK PMI 3174042905850005 1 | H70: Transaksi berhasil dilakukan, muncul pesan "Pby BPJSTK PMI 3174042905850005 TEGUH PRASETYO KodeIuran:900000054765 12 bulan Total: Rp 3.229.200 Berhasil. Ref:136499" | I70: Y | J70: DONE | K70: DONE | M70: 44995 | N70: SCSBK0014_20230310-110512513.pdf | S70: 44995 | T70: Meydita
B71: SBK0014-005 | C71: User melakukan Pembayaran BPJS | D71: User salah input Nomor Tagihan BPJS Kesehatan | E71: Abnormal | F71: 1. User menginput sintaks pada aplikasi SMS 2. User Mengirimkan SMS ke 3346 | G71: PAY BPJSKES 1234501738035562 4 | H71: Transaksi gagal dilakukan, muncul pesan "Pembayaran untuk nomor tersebut tidak tersedia. Hubungi BNI Call di 1500046 atau 0211500046 (ponsel)." | I71: Y | J71: DONE | K71: DONE | M71: 45019 | N71: SCSBK0014_20230403-101701042.pdf | S71: 45019 | T71: Meydita
B72: SBK0014-006 | C72: User melakukan Pembayaran BPJS | D72: User salah input Nomor Tagihan BPJS Ketenagakerjaan | E72: Abnormal | F72: 1. User menginput sintaks pada aplikasi SMS 2. User Mengirimkan SMS ke 3346 | G72: PAY BPJSTK PMI 1234567890150005 1 | H72: Transaksi gagal dilakukan, muncul pesan "Pembayaran untuk nomor tersebut tidak tersedia. Hubungi BNI Call di 1500046 atau 0211500046 (ponsel)." | I72: Y | J72: DONE | K72: DONE | M72: 45058 | N72: SCSBK0014_20230512-103124020 | S72: 45056 | T72: Meydita
B73: SBK0014-007 | C73: User melakukan Pembayaran BPJS | D73: User salah input PIN Transaksi BPJS Kesehatan | E73: Abnormal | F73: 1. User menginput sintaks pada aplikasi SMS 2. User Mengirimkan SMS ke 3346 3. User Input PIN Transaksi | G73: PAY BPJSKES 8888801738035562 4 | H73: Transaksi gagal, muncul pesan "Transaksi tidak dapat diproses.PIN yang Anda ketikkan salah.Silakan periksa kembali PIN Anda dan transaksi kembali dari awal" | I73: Y | J73: DONE | K73: DONE | M73: 45000 | N73: SCSBK0014_20230315-161527424.pdf | S73: 45000 | T73: Meydita
B74: SBK0014-008 | C74: User melakukan Pembayaran BPJS | D74: User salah input PIN Transaksi BPJS Ketenagakerjaan | E74: Abnormal | F74: 1. User menginput sintaks pada aplikasi SMS 2. User Mengirimkan SMS ke 3346 3. User Input PIN Transaksi | G74: PAY BPJSTK PMI 3174042905850005 1 | H74: Transaksi gagal, muncul pesan "Transaksi tidak dapat diproses.PIN yang Anda ketikkan salah.Silakan periksa kembali PIN Anda dan transaksi kembali dari awal" | I74: Y | J74: DONE | K74: DONE | M74: 45000 | N74: SCSBK0014_20230315-163253620.pdf | S74: 45000 | T74: Meydita
A75: SCSBK0015 | B75: SBK0015-001 | C75: User melakukan Pembayaran PDAM & IPL | D75: User melakukan pembayaran PDAM & IPL - AETRA Air Jakarta | E75: Normal | F75: 1. User menginput sintaks pada aplikasi SMS 2. User Mengirimkan SMS ke 3346 3. User Input PIN Transaksi | G75: PAY PAM AETRA 123456 | H75: Transaksi berhasil dilakukan, muncul pesan "AETRA 123456 SRIYANTO SEP18 Tag:87490 Denda:284068 Total:374.058,00 Adm2500 Sukses.Ref:260083" | I75: Y | J75: DONE | K75: DONE
B76: SBK0015-002 | C76: User melakukan Pembayaran PDAM & IPL | D76: User melakukan pembayaran PDAM & IPL - Air Manado | E76: Normal | F76: 1. User menginput sintaks pada aplikasi SMS 2. User Mengirimkan SMS ke 3346 3. User Input PIN Transaksi | G76: PAY PAM Manado 3812346 | H76: Transaksi berhasil dilakukan, muncul pesan "Manado 3812346 SRIYANTO SEP18 Tag:87490 Denda:284068 Total:374.058,00 Adm2500 Sukses.Ref:260083" | I76: Y | J76: DONE | K76: DONE
B77: SBK0015-003 | C77: User melakukan Pembayaran PDAM & IPL | D77: User melakukan Pembayaran PDAM & IPL - IPL/PAM BSD | E77: Normal | F77: 1. User menginput sintaks pada aplikasi SMS 2. User Mengirimkan SMS ke 3346 3. User Input PIN Transaksi | G77: PAY PAM BSD 11001234 | H77: Transaksi berhasil dilakukan, muncul pesan "PAM BSD No:20032164 Nama:ROZI LAWATI Tagihan:Rp20000 Total:Rp22.500 Admin:Rp2500 Berhasil. No Reff:155464" | I77: Y | J77: DONE | K77: DONE
B78: SBK0015-004 | C78: User melakukan Pembayaran PDAM & IPL | D78: User melakukan Pembayaran PDAM & IPL - PALYJA | E78: Normal | F78: 1. User menginput sintaks pada aplikasi SMS 2. User Mengirimkan SMS ke 3346 3. User Input PIN Transaksi | G78: PAY PAM PALYJA 38123456 | H78: Transaksi berhasil dilakukan, muncul pesan "PALYJA 38123456 a/n REPITA SIL APR13 Tag:31698 Denda:0 Total:Rp31698 Adm 0. Berhasil. No Reff:155464" | I78: Y | J78: DONE | K78: DONE
B79: SBK0015-005 | C79: User melakukan Pembayaran PDAM & IPL | D79: User melakukan pembayaran PDAM & IPL - PDAM ATB BATAM | E79: Normal | F79: 1. User menginput sintaks pada aplikasi SMS 2. User Mengirimkan SMS ke 3346 3. User Input PIN Transaksi | G79: PAY PAM ATBBatam 123456 | H79: Transaksi berhasil dilakukan, muncul pesan "PDAM ATBBATAM 123456 JAELANI MEI13 Tag:0 Denda:147500 Total:150.000,00 Adm2500 Sukses.Ref:266027" | I79: Y | J79: DONE | K79: DONE
B80: SBK0015-006 | C80: User melakukan Pembayaran PDAM & IPL | D80: User melakukan pembayaran PDAM & IPL - PDAM ATS PALEMBANG | E80: Normal | F80: 1. User menginput sintaks pada aplikasi SMS 2. User Mengirimkan SMS ke 3346 3. User Input PIN Transaksi | G80: PAY PAM ATSPalembang 123456 | H80: Transaksi berhasil dilakukan, muncul pesan "PDAM ATSPalembang 123456 JAELANI MEI13 Tag:0 Denda:147500 Total:150.000,00 Adm2500 Sukses.Ref:266179" | I80: Y | J80: DONE | K80: DONE
B81: SBK0015-007 | C81: User melakukan Pembayaran PDAM & IPL | D81: User melakukan pembayaranPDAM & IPL - PDAM Balangan | E81: Normal | F81: 1. User menginput sintaks pada aplikasi SMS 2. User Mengirimkan SMS ke 3346 3. User Input PIN Transaksi | G81: PAY PAM Balangan 123456 | H81: Transaksi berhasil dilakukan, muncul pesan "PDAM Balangan 123456 JAELANI MEI13 Tag:0 Denda:147500 Total:150.000,00 Adm2500 Sukses.Ref:266179" | I81: Y | J81: DONE | K81: DONE
B82: SBK0015-008 | C82: User melakukan Pembayaran PDAM & IPL | D82: User melakukan pembayaran PDAM & IPL - PDAM Balikpapan | E82: Normal | F82: 1. User menginput sintaks pada aplikasi SMS 2. User Mengirimkan SMS ke 3346 3. User Input PIN Transaksi | G82: PAY PAM Balikpapan 123456 | H82: Transaksi berhasil dilakukan, muncul pesan "PDAM Balikpapan 123456 JAELANI MEI13 Tag:0 Denda:147500 Total:150.000,00 Adm2500 Sukses.Ref:266179" | I82: Y | J82: DONE | K82: DONE
B83: SBK0015-009 | C83: User melakukan Pembayaran PDAM & IPL | D83: User melakukan pembayaran PDAM & IPL - PDAM Bandar Lampung | E83: Normal | F83: 1. User menginput sintaks pada aplikasi SMS 2. User Mengirimkan SMS ke 3346 3. User Input PIN Transaksi | G83: PAY PAM BandarLampung 123456 | H83: Transaksi berhasil dilakukan, muncul pesan "PDAM BandarLampung 123456 JAELANI MEI13 Tag:0 Denda:147500 Total:150.000,00 Adm2500 Sukses.Ref:266027" | I83: Y | J83: DONE | K83: DONE
B84: SBK0015-010 | C84: User melakukan Pembayaran PDAM & IPL | D84: User melakukan pembayaran PDAM & IPL - PDAM Bangka Barat | E84: Normal | F84: 1. User menginput sintaks pada aplikasi SMS 2. User Mengirimkan SMS ke 3346 3. User Input PIN Transaksi | G84: PAY PAM BangkaBarat 123456 | H84: Transaksi berhasil dilakukan, muncul pesan "PDAM BangkaBarat 123456 JAELANI MEI13 Tag:0 Denda:147500 Total:150.000,00 Adm2500 Sukses.Ref:266027" | I84: Y | J84: DONE | K84: DONE
B85: SBK0015-011 | C85: User melakukan Pembayaran PDAM & IPL | D85: User melakukan pembayaran PDAM & IPL - PDAM Banjarmasin | E85: Normal | F85: 1. User menginput sintaks pada aplikasi SMS 2. User Mengirimkan SMS ke 3346 3. User Input PIN Transaksi | G85: PAY PAM Banjarmasin 123456 | H85: Transaksi berhasil dilakukan, muncul pesan "PDAM Banjarmasin 123456 JAELANI MEI13 Tag:0 Denda:147500 Total:150.000,00 Adm2500 Sukses.Ref:266027" | I85: Y | J85: DONE | K85: DONE
B86: SBK0015-012 | C86: User melakukan Pembayaran PDAM & IPL | D86: User melakukan pembayaran PDAM & IPL - PDAM Banyumas | E86: Normal | F86: 1. User menginput sintaks pada aplikasi SMS 2. User Mengirimkan SMS ke 3346 3. User Input PIN Transaksi | G86: PAY PAM Banyumas 90041801 | H86: Transaksi berhasil dilakukan, muncul pesan "PDAM Banyumas 90041801 HAMZUN ALI JUN21 Tag:10000 Denda:5000 Total:17.500 Adm2500 Sukses.Ref:111319" | I86: Y | J86: DONE | K86: DONE
B87: SBK0015-013 | C87: User melakukan Pembayaran PDAM & IPL | D87: User melakukan pembayaran PDAM & IPL - PDAM Barabai | E87: Normal | F87: 1. User menginput sintaks pada aplikasi SMS 2. User Mengirimkan SMS ke 3346 3. User Input PIN Transaksi | G87: PAY PAM Barabai 123456 | H87: Transaksi berhasil dilakukan, muncul pesan "PDAM Barabai 123456 HAMZUN ALI JUN21 Tag:10000 Denda:5000 Total:17.500 Adm2500 Sukses.Ref:111319" | I87: Y | J87: DONE | K87: DONE
... B179: SBK0015-105 | C179: User melakukan Pembayaran PDAM & IPL | D179: User melakukan pembayaran PDAM & IPL - PDAM Kab. Karanganyar | E179: Normal | F179: 1. User menginput sintaks pada aplikasi SMS 2. User Mengirimkan SMS ke 3346 3. User Input PIN Transaksi | G179: PAY PAM KabKaranganyar 010400225 | H179: Transaksi berhasil dilakukan, muncul pesan "PDAM KabKaranganyar 010400225 SASTRO MUG AGU21 Tag:31500 Denda:5000 Total:39.000 Adm2500 Sukses.Ref:126278" | I179: Y | J179: DONE | K179: DONE
B180: SBK0015-106 | C180: User melakukan Pembayaran PDAM & IPL | D180: User melakukan pembayaran PDAM & IPL - PDAM Tirta Sakti Kab. Kerinci | E180: Normal | F180: 1. User menginput sintaks pada aplikasi SMS 2. User Mengirimkan SMS ke 3346 3. User Input PIN Transaksi | G180: PAY PAM KabKerinci 1234567 | I180: Y | J180: DONE | K180: DONE
B181: SBK0015-107 | C181: User melakukan Pembayaran PDAM & IPL | D181: User melakukan pembayaran PDAM & IPL - PDAM Kab. Kolaka | E181: Normal | F181: 1. User menginput sintaks pada aplikasi SMS 2. User Mengirimkan SMS ke 3346 3. User Input PIN Transaksi | G181: PAY PAM KabKolaka 123456 | I181: Y | J181: DONE | K181: DONE
B182: SBK0015-108 | C182: User melakukan Pembayaran PDAM & IPL | D182: User melakukan pembayaran PDAM & IPL - PDAM Limau Kunci Kab. Lampung Barat | E182: Normal | F182: 1. User menginput sintaks pada aplikasi SMS 2. User Mengirimkan SMS ke 3346 3. User Input PIN Transaksi | G182: PAY PAM KabLampungBarat 123456 | I182: Y | J182: DONE | K182: DONE
B183: SBK0015-109 | C183: User melakukan Pembayaran PDAM & IPL | D183: User melakukan pembayaran PDAM & IPL - PDAM Tirta Gemilang Kab. Magelang | E183: Normal | F183: 1. User menginput sintaks pada aplikasi SMS 2. User Mengirimkan SMS ke 3346 3. User Input PIN Transaksi | G183: PAY PAM KabLampungBarat 123456 | I183: Y | J183: DONE | K183: DONE
B184: SBK0015-110 | C184: User melakukan Pembayaran PDAM & IPL | D184: User melakukan pembayaran PDAM & IPL - PDAM Kabupaten Tirta Mahakam | E184: Normal | F184: 1. User menginput sintaks pada aplikasi SMS 2. User Mengirimkan SMS ke 3346 3. User Input PIN Transaksi | G184: PAY PAM KabMagelang 14060439 | I184: Y | J184: DONE | K184: DONE
B185: SBK0015-111 | C185: User melakukan Pembayaran PDAM & IPL | D185: User melakukan pembayaran PDAM & IPL - PDAM Kab. Majalengka | E185: Normal | F185: 1. User menginput sintaks pada aplikasi SMS 2. User Mengirimkan SMS ke 3346 3. User Input PIN Transaksi | G185: PAY PAM KabMajalengka 14060439 | I185: Y | J185: DONE | K185: DONE
B186: SBK0015-112 | C186: User melakukan Pembayaran PDAM & IPL | D186: User melakukan pembayaran PDAM & IPL - PDAM Apa Mening Kab. Malinau | E186: Normal | F186: 1. User menginput sintaks pada aplikasi SMS 2. User Mengirimkan SMS ke 3346 3. User Input PIN Transaksi | G186: PAY PAM KabMalinau 123456 | I186: Y | J186: DONE | K186: DONE
B187: SBK0015-113 | C187: User melakukan Pembayaran PDAM & IPL | D187: User melakukan pembayaran PDAM & IPL - PDAM Kab. Merauke | E187: Normal | F187: 1. User menginput sintaks pada aplikasi SMS 2. User Mengirimkan SMS ke 3346 3. User Input PIN Transaksi | G187: PAY PAM KabMerauke | I187: Y | J187: DONE | K187: DONE
B188: SBK0015-114 | C188: User melakukan Pembayaran PDAM & IPL | D188: User melakukan pembayaran PDAM & IPL - PDAM Kabupaten Mojokerto | E188: Normal | F188: 1. User menginput sintaks pada aplikasi SMS 2. User Mengirimkan SMS ke 3346 3. User Input PIN Transaksi | G188: PAY PAM KabMojokerto 1234567 | I188: Y | J188: DONE | K188: DONE
B189: SBK0015-115 | C189: User melakukan Pembayaran PDAM & IPL | D189: User melakukan pembayaran PDAM & IPL - PDAM Kab. Ngawi | E189: Normal | F189: 1. User menginput sintaks pada aplikasi SMS 2. User Mengirimkan SMS ke 3346 3. User Input PIN Transaksi | G189: PAY PAM KabNgawi 1234567 | I189: Y | J189: DONE | K189: DONE
B190: SBK0015-116 | C190: User melakukan Pembayaran PDAM & IPL | D190: User melakukan pembayaran PDAM & IPL - PDAM Kabupaten Nunukan | E190: Normal | F190: 1. User menginput sintaks pada aplikasi SMS 2. User Mengirimkan SMS ke 3346 3. User Input PIN Transaksi | G190: PAY PAM KabNunukan 1234567 | I190: Y | J190: DONE | K190: DONE
B191: SBK0015-117 | C191: User melakukan Pembayaran PDAM & IPL | D191: User melakukan pembayaran PDAM & IPL - PDAM Kab. Pamekasan | E191: Normal | F191: 1. User menginput sintaks pada aplikasi SMS 2. User Mengirimkan SMS ke 3346 3. User Input PIN Transaksi | G191: PAY PAM KabPamekasan 1234567 | I191: Y | J191: DONE | K191: DONE
...

Sheet OMNI
A1: Scenario ID | B1: TC_ID | C1: Scenario Name | D1: Test Case | E1: Test Case Type | F1: Test Step | H1: List Data | I1: Expected Result | J1: Verification | M1: Note | N1: Run Date 1 | O1: Filename 1 | P1: Run Date 2 | Q1: Filename 2 | R1: Status Automation | S1: Note Status Automation | T1: Pass Date (HH Bulan TTTT) (12 Juli 2022) | U1: PIC
J2: Screen OMNI | K2: Status Automation Library Dev | L2: Run Status UFT
A3: OMNI0001 | B3: OMNI0001-001 | C3: Login | D3: Normal - Login with valid password and captcha (numeric) | E3: Normal | F3: 1. Login aplikasi omni 2. Masukan User ID 3. Masukan Kata sandi 4. Masukan kode captcha | I3: Successfully logged in | J3: Y | K3: DONE | L3: DONE | M3: Bisa semiAutomate | N3: 4 Januari 2023 | O3: OMNI0001 - Login_20230104-140426809 | U3: Kevin
B4: OMNI0001-002 | C4: Login | D4: Normal - Login with valid password and captcha (alphanumeric) | E4: Normal | F4: 1. Login aplikasi omni 2. Masukan User ID 3. Masukan Kata sandi 4. Masukan kode captcha | I4: Successfully logged in | J4: Y | K4: DONE | L4: DONE | M4: Bisa semiAutomate | N4: 4 Januari 2023 | O4: OMNI0001 - Login_20230104-140737618 | U4: Kevin
B5: OMNI0001-003 | C5: Login | D5: Abnormal - Login with invalid captcha 1x | E5: Abnormal | F5: 1. Login aplikasi omni 2. Masukan User ID 3. Masukan Kata sandi 4. Masukan kode captcha salah | I5: Failed to login and got an invalid captcha message | J5: Y | K5: DONE | L5: DONE | M5: Bisa semiAutomate | N5: 4 Januari 2023 | O5: OMNI0001 - Login_20230104-171240170 | U5: Kevin
B6: OMNI0001-004 | C6: Login | D6: Abnormal - Login with invalid captcha 3x | E6: Abnormal | F6: 1. Login aplikasi omni 2. Masukan User ID 3. Masukan Kata sandi 4. Masukan kode captcha salah ke 3 kali | I6: Failed to login and account is temporarily blocked | J6: Y | K6: DONE | L6: DONE | M6: Bisa semiAutomate | N6: 6 Februari 2023 | O6: OMNI0001 - Login_20230206-122525785 | U6: Kevin
B7: OMNI0001-005 | C7: Login | D7: Abnormal - Login with invalid password 1x | E7: Abnormal | F7: 1. Login aplikasi omni 2. Masukan User ID 3. Masukan Kata sandi salah 4. Masukan kode captcha | I7: Failed to Login | J7: Y | K7: DONE | L7: DONE | M7: Bisa semiAutomate | N7: 4 Januari 2023 | O7: OMNI0001 - Login_20230104-172113813 | U7: Kevin
B8: OMNI0001-006 | C8: Login | D8: Abnormal - Login with invalid password 3x | E8: Abnormal | F8: 1. Login aplikasi omni 2. Masukan User ID 3. Masukan Kata sandi salah ke 3 kali 4. Masukan kode captcha | J8: Y | K8: DONE | L8: DONE | M8: Bisa semiAutomate | N8: 6 Februari 2023 | O8: OMNI0001 - Login_20230206-150251934 | U8: Kevin
B9: OMNI0001-007 | C9: Login | D9: Abnormal - Login with invalid user id | E9: Abnormal | F9: 1. Login aplikasi omni 2. Masukan User ID salah 3. Masukan Kata sandi 4. Masukan kode captcha | I9: Failed to Login | J9: Y | K9: DONE | L9: DONE | M9: Bisa semiAutomate | N9: 4 Januari 2023 | O9: OMNI0001 - Login_20230104-170642168 | U9: Kevin
A10: OMNI0002 | B10: OMNI0002-001 | C10: Homepage | D10: Normal - Name from core banking shown | E10: Normal | F10: 1. Login aplikasi omni 2. Masukan User ID 3. Masukan Kata sandi 4. Masukan kode captcha 5. Masuk ke halaman homepage | I10: success shown name from core banking | J10: Y | K10: DONE | L10: DONE | N10: 29 Desember 2022 | O10: OMNI0002 - Homepage_20221229-122713170 | T10: 29 Desember 2022 | U10: Kevin
B11: OMNI0002-002 | C11: Homepage | D11: Normal - New name from core banking shown | E11: Normal | F11: 1. Login aplikasi omni 2. Masukan User ID 3. Masukan Kata sandi 4. Masukan kode captcha 5. Masuk ke halaman homepage | I11: success shown new name from core banking | J11: Y | K11: DONE | L11: DONE | N11: 29 Desember 2022 | O11: OMNI0002 - Homepage_20221229-123041739 | T11: 29 Desember 2022 | U11: Kevin
B12: OMNI0002-003 | C12: Homepage | D12: Normal - Foto from DB shown | E12: Normal | F12: 1. Login aplikasi omni 2. Masukan User ID 3. Masukan Kata sandi 4. Masukan kode captcha 5. Masuk ke halaman homepage | I12: success shown foto from DB | J12: Y | K12: DONE | L12: DONE | N12: 29 Desember 2022 | O12: OMNI0002 - Homepage_20221229-123614676 | T12: 29 Desember 2022 | U12: Kevin
B13: OMNI0002-004 | C13: Homepage | D13: Normal - Greeting shown according to server time | E13: Normal | F13: 1. Login aplikasi omni 2. Masukan User ID 3. Masukan Kata sandi 4. Masukan kode captcha 5. Masuk ke halaman homepage | I13: greeting shown to server time | J13: Y | K13: DONE | L13: DONE | N13: 29 Desember 2022 | O13: OMNI0002 - Homepage_20221229-124730310 | T13: 29 Desember 2022 | U13: Kevin
B14: OMNI0002-005 | C14: Homepage | D14: Abnormal - Name from core is more than max length (30char) | E14: Abnormal | J14: Y | K14: DONE | L14: DONE | N14: 29 Desember 2022 | O14: OMNI0002 - Homepage_20221229-130443682 | T14: 29 Desember 2022 | U14: Kevin
A15: OMNI0003 | B15: OMNI0003-001 | C15: Homepage Portofolio | D15: Normal - Show 1 DPLK account balance | E15: Normal | I15: 1 of DPLK balance is added to the total savings and is displayed on the savings card on the homepage. | J15: Y | U15: Kevin
B16: OMNI0003-002 | C16: Homepage Portofolio | D16: Normal - Show total of several DPLK accounts balance | E16: Normal | I16: The total DPLK balance is added to the total savings and is displayed on the savings card on the homepage. | J16: Y | U16: Kevin
B17: OMNI0003-003 | C17: Homepage Portofolio | D17: Abnormal - No DPLK account | E17: Abnormal | I17: - | J17: Y | K17: DONE | L17: DONE | N17: 3 Januari 2023 | O17: OMNI0003 - Homepage Portofolio_20230103-141743753 | T17: 3 Januari 2023 | U17: Kevin
B18: OMNI0003-004 | C18: Homepage Portofolio | D18: Abnormal - DPLK Account closed | E18: Abnormal | I18: DPLK account balances that have been closed are not included in the total savings balance card. | J18: Y | U18: Kevin
B19: OMNI0003-005 | C19: Homepage Portofolio | D19: Normal - Show 1 rekening surat berharga balance | E19: Normal | F19: Sedang ada maintenance, tested on 16/02/2023 | I19: Successfully show 1 account of SBN in detail feature card invest. | J19: Y | U19: Kevin
B20: OMNI0003-006 | C20: Homepage Portofolio | D20: Normal - Show all rekening surat berharga balance | E20: Normal | F20: Sedang ada maintenance, tested on 16/02/2023 | I20: Successfully to show all rekening surat berharga balance in detail feature card invest. | J20: Y | U20: Kevin
B21: OMNI0003-007 | C21: Homepage Portofolio | D21: Normal - Show update balance of redempted SBN account | E21: Normal | F21: Sedang ada maintenance, tested on 16/02/2023 | I21: Successfully to show update balance of redempted SBN account in detail feature card invest. | J21: Y | U21: Kevin
B22: OMNI0003-008 | C22: Homepage Portofolio | D22: Abnormal - No SBN account | E22: Abnormal | I22: Failed to show SBN account in feature detail card invest. | J22: Y | K22: DONE | L22: DONE | N22: 26 Januari 2023 | O22: OMNI0003 - Homepage Portofolio_20230126-150334083 | U22: Kevin
B23: OMNI0003-009 | C23: Homepage Portofolio | D23: Abnormal - Rekening surat berharga with completed order status | E23: Abnormal | J23: Y | U23: Kevin
B24: OMNI0003-010 | C24: Homepage Portofolio | D24: Normal - Show 1 reksadana account balance | E24: Normal | F24: Sedang ada maintenance, tested on 16/02/2023 | I24: Successfully show 1 account of Mutual Funds in detail feature card invest. | J24: Y | U24: Kevin
B25: OMNI0003-011 | C25: Homepage Portofolio | D25: Normal - Show all reksadana account balance | E25: Normal | F25: Sedang ada maintenance, tested on 16/02/2023 | I25: Successfully to show all Mutual Funds in detail feature card invest. | J25: Y | U25: Kevin
B26: OMNI0003-012 | C26: Homepage Portofolio | D26: Normal - Show update balance of redempted reksadana account | E26: Abnormal | F26: Sedang ada maintenance, tested on 16/02/2023 | I26: Successfully to show update balance of redempted reksadana account in detail feature card invest. | J26: Y | U26: Kevin
B27: OMNI0003-013 | C27: Homepage Portofolio | D27: Abnormal - No reksadana account | E27: Abnormal | I27: Failed to show reksadana account in feature detail | J27: Y | K27: DONE | L27: DONE | N27: 26 Januari 2023 | O27: OMNI0003 - Homepage Portofolio_20230126-151915898 | U27: Kevin
B28: OMNI0003-014 | C28: Homepage Portofolio | D28: Abnormal - Reksadana account with no balance | E28: Abnormal | I28: Failed to show reksadana account with no balance in card invest | J28: Y | U28: Kevin
B29: OMNI0003-015 | C29: Homepage Portofolio | D29: Normal - Show total balance of Taplus, Tapenas, Giro, Deposito (IDR) | E29: Normal | I29: success shown total balance of tabungan (IDR) | J29: Y | K29: DONE | L29: DONE | N29: 28 Desember 2022 | O29: OMNI0003 - Homepage Portofolio_20221228-150359748 | T29: 28 Desember 2022 | U29: Kevin
B30: OMNI0003-016 | C30: Homepage Portofolio | D30: Normal - Show total balance of Taplus, Tapenas, Giro, Deposito (IDR dan non IDR) | E30: Normal | I30: success shown total balance of tabungan (IDR & Non IDR) | J30: Y | K30: DONE | L30: DONE | N30: 28 Desember 2022 | O30: OMNI0003 - Homepage Portofolio_20221228-150740489 | T30: 28 Desember 2022 | U30: Kevin
B31: OMNI0003-017 | C31: Homepage Portofolio | D31: Abnormal - Tabungan with closed status | E31: Abnormal | I31: not accumulate taplus account closed status | J31: Y | K31: DONE | L31: DONE | N31: 16 Februari 2023 | O31: OMNI0003 - Homepage Portofolio_20230216-111403471 | U31: Kevin
B32: OMNI0003-018 | C32: Homepage Portofolio | D32: Abnormal - No balance | E32: Abnormal | I32: sucess accumulation total balance of tabungan | J32: Y | U32: Kevin
B33: OMNI0003-019 | C33: Homepage Portofolio | D33: Normal - Show total balance of pinjaman | E33: Normal | I33: success shown total balance of pinjaman | J33: Y | K33: DONE | L33: DONE | N33: 26 Januari 2023 | O33: OMNI0003 - Homepage Portofolio_20230126-143458963 | U33: Kevin
B34: OMNI0003-020 | C34: Homepage Portofolio | D34: Abnormal - Pinjaman with closed status | E34: Abnormal | I34: not accumulate pinjaman account closed status | J34: Y | U34: Kevin
B35: OMNI0003-021 | C35: Homepage Portofolio | D35: Abnormal - No account | E35: Abnormal | I35: not shown accumulation and success shown according to figma | J35: Y | K35: DONE | L35: DONE | N35: 26 Januari 2023 | O35: OMNI0003 - Homepage Portofolio_20230126-151534662 | U35: Kevin
A36: OMNI0004 | B36: OMNI0004-001 | C36: My Account | D36: Normal - Show list of DPLK Account | E36: Normal | I36: - Success to show DPLK account in list - Screen ui is as designed as figma | J36: Y | K36: DONE | L36: DONE | N36: 29 Desember 2022 | O36: OMNI0004 - My Account_20221229-150044903 | T36: 29 Desember 2022 | U36: Kevin
B37: OMNI0004-002 | C37: My Account | D37: Normal - Show Detail of DPLK Account | E37: Normal | I37: - Success to view detail of DPLK account - Screen ui is as designed as figma | J37: Y | K37: DONE | L37: DONE | N37: 3 Januari 2023 | O37: OMNI0004 - My Account_20230103-102622479 | T37: 3 Januari 2023 | U37: Kevin
B38: OMNI0004-003 | C38: My Account | D38: Abnormal - No DPLK Account | E38: Abnormal | I38: - Success to show list with no DPLK account - Screen ui is as designed as figma | J38: Y | K38: DONE | L38: DONE | N38: 29 Desember 2022 | O38: OMNI0004 - My Account_20221229-141401494 | T38: 29 Desember 2022 | U38: Kevin
B39: OMNI0004-004 | C39: My Account | D39: Normal - Mutasi Rekening DPLK Bassed On Last Transactions | E39: Normal | J39: Y | K39: DONE | L39: DONE | N39: 18 Januari 2023 | O39: OMNI0004 - My Account_20230118-134338568 | U39: Kevin
B40: OMNI0004-005 | C40: My Account | D40: Normal - Mutasi Rekening DPLK Bassed On This Week Transactions | E40: Normal | J40: Y | K40: DONE | L40: DONE | N40: 7 Februari 2023 | O40: OMNI0004 - My Account_20230207-120344811 | U40: Kevin
B41: OMNI0004-006 | C41: My Account | D41: Normal - Mutasi Rekening DPLK Bassed On This month Transactions | E41: Normal | J41: Y | K41: DONE | L41: DONE | N41: 18 Januari 2023 | O41: OMNI0004 - My Account_20230118-135409384 | U41: Kevin
B42: OMNI0004-007 | C42: My Account | D42: Normal - Mutasi Rekening DPLK Bassed On This Time Period Transactions | E42: Normal | J42: Y | K42: DONE | L42: DONE | N42: 20 Januari 2023 | O42: OMNI0004 - My Account_20230120-143345771 | U42: Kevin
B43: OMNI0004-008 | C43: My Account | D43: Abnormal - Transaction History No Found | E43: Abnormal | J43: Y | K43: DONE | L43: DONE | N43: 20 Januari 2023 | O43: OMNI0004 - My Account_20230120-142119457 | U43: Kevin
A44: OMNI0005 | B44: OMNI0005-001 | C44: Transfer Reguler | D44: Normal - Transfer To Bank Himbara (Mandiri) | E44: Normal | I44: - Transaction Success - Screen ui is as designed as figma | J44: Y | K44: DONE | L44: DONE | N44: 1 Februari 2023 | O44: OMNI0005 - Transfer Reguler_20230201-125705836 | U44: Kevin
B45: OMNI0005-002 | C45: Transfer Reguler | D45: Normal - Transfer To Bank Himbara (BRI) | E45: Normal | I45: - Transaction Success - Screen ui is as designed as figma | J45: Y | K45: DONE | L45: DONE | N45: 4 Januari 2023 | O45: OMNI0005 - Transfer Reguler_20230104-174240426 | U45: Kevin
B46: OMNI0005-003 | C46: Transfer Reguler | D46: Normal - Transfer To Bank Prima (BCA) Add To Daftar Favorite | E46: Normal | I46: - Transaction Success - Screen ui is as designed as figma | J46: Y | K46: DONE | L46: DONE | N46: 5 Januari 2023 | O46: OMNI0005 - Transfer Reguler_20230105-132406356 | U46: Kevin
B47: OMNI0005-004 | C47: Transfer Reguler | D47: Normal - Transfer To Bank Prima (BCA) Transaction Again | E47: Normal | J47: Y | K47: DONE | L47: DONE | N47: 5 Januari 2023 | O47: OMNI0005 - Transfer Reguler_20230105-125558560 | U47: Kevin
B48: OMNI0005-005 | C48: Transfer Reguler | D48: Abnormal - Transfer To Bank Himbara insuficient fund (Mandiri) | E48: Abnormal | I48: - Transaction Fail - Screen ui is as designed as figma | J48: Y | K48: DONE | L48: DONE | N48: 5 Desember 2022 | O48: OMNI0005 - Transfer Reguler_20221205-155652731 | T48: 5 Desember 2022 | U48: Kevin
B49: OMNI0005-006 | C49: Transfer Reguler | D49: Abnormal - Transfer To Bank Prima insuficient fund (BCA) | E49: Abnormal | I49: - Transaction Fail - Screen ui is as designed as figma | J49: Y | K49: DONE | L49: DONE | N49: 5 Desember 2022 | O49: OMNI0005 - Transfer Reguler_20221205-155652731 | T49: 5 Desember 2022 | U49: Kevin
